Workbook

Sheet PETUNJUK PENGERJAAN
B6: PETUNJUK PENGERJAAN LAPORAN ADMIN TERBARU
A7: 1. | B7: LAPORAN LPKK
B9: Form laporan LPKK tidak diprotect/dikunci, supervisor dapat menambahkan kolom LPKK apabila nota pembelanjaan dalam satu hari melebihi kolom yang disediakan
B10: Pada format laporan LPKK terbaru, kolom Bahan Roti dan Bahan Perkedel dihilangkan.
B11: Nota - nota belanja Bahan Roti dialihkan masuk ke kolom Bahan Pelengkap dan untuk nota- nota Bahan Perkedel masuk kolom Bumbu/Groceries
A13: 2. | B13: LAPORAN VENDOR
B14: Pembelian ayam cash diisi secara manual dan pembelian ayam kredit wajib diisi dikolom khusus pembelian ayam kredit dan marinade
B15: Pengerjaan laporan secara online/komputer nota ayam kredit diisi pada kolom kanan atas laporan vendor yang secara otomatis mengisi pada kolom khusus ayam kredit pada vendor
B16: Kolom TO/TI pada vendor dikerjakan secara manual dan pencatatan diperhatikan, apabila Ada TO (Transfer Out) pencatatan nominal harus diberi tanda (-).
B17: Penambahan keterangan bahan baku pada kolom vendor dapat diisi lewat laporan weekly pada kolom bahan sesuai dengan pengelompokkan bahan bakunya, maka secara langsung akan ngelink ke kolom keterangan bahan baku di laporan vendor
B18: Hasil print out laporan vendor pengerjaan secara online/komputer menjadi 3 lembar, pengerjaan secara manual vendor menjadi 5 lembar
A20: 3. | B20: COST ANALYSIS
B21: Kolom penjualan pada laporan cost analysis diisi secara manual. Kolom penjualan bisa dibuat rumus oleh supervisor sesuai dengan kelas masing - masing dengan cara total unit penjualan ngelink dengan semua laporan penjualan offline/online (gofood, grabfood, shopee food) contoh penghitungan MENCARI PENJUALAN PRODUK P. BAWAH (KETIK = pada laporan cost analysis kolom penjualan P. BAWAH kemudian klik pada laporan LP, Total unit penjualan P. BAWAH pada setiap produk item satuan/paket yang ada produk P. BAWAH dengan menambahkan tanda + pada semua Laporan penjualan termasuk LP online) KEMUDIAN TEKAN ENTER.
A23: 4. | B23: LAPORAN KAS & PENJUALAN PER PERIODE
B24: Kolom Tax/Pajak (FULL PPN) wajib diisi store yang sudah mengenakan harga jual ke customer plus PPN/Pajak (full customer dikenakan pajak) Harga jual produk per item di laporan penjualan harga menu price harus sudah plus PPN
B25: Kolom Tax/Pajak (SEBAGIAN PPN), wajib diisi store yang sudah mengenakan harga jual ke customer plus PPN/Pajak (sebagian cutomer yang dikenakan pajak) Harga jual produk per item di laporan penjualan harga menu price tanpa plus PPN
B26: Store yang belum mengenakan pajak kepada customer kolom tax atau pajak tidak perlu diisi/dikosongkan
A28: 5. | B28: LAPORAN TO/TI
B29: Laporan TO/TI hasil jumlah akan ngelink dengan laporan ikhtisar food cost
B30: Pengerjaan TO/TI terdapat petunjuk pengerjaan di sheet TO/TI
A33: 6. | B33: LAPORAN LKK
B34: Store yang belum mengenakan PPN kepada customer mengunakan lkk dengan rumus Penjualan Kotor - Komisi - Koreksi - Diskon = Penjualan Bersih
B35: Store yang sudah mengenakan PPN kepada customer sebagian mengunakan lkk dengan rumus Penjualan Kotor - Komisi - Koreksi - Diskon = Penjualan Bersih
B36: Store yang sudah mengenakan FULL PPN kepada customer mengunakan lkk dengan rumus Penjualan Kotor - Komisi - Koreksi - Diskon - PAJAK/TAX = Penjualan Bersih
A38: 7. | B38: LAPORAN PENJUALAN
B39: Pengisian tanggal pada kolom unit penjualan per hari hanya diisi tanggalnya saja, tidak dengan Bulan dan Tahun agar saat diprint out hasil lebih maksimal
B40: Laporan penjualan untuk store yang sudah mengenakan FULL PPN harga wajib disesuaikan + PPN
B41: Laporan penjualan PPN 10 % untuk Harga (unit) diisi manual sesuai harga menu price sebelum tambah PPN
B42: Laporan admin terbaru terdapat 4 laporan penjualan (LP) yaitu LP Penjualan Reguler, LP Gofood, LP Grabfood dan LP Shopee food. Apabila store tidak ada penjualan via online atau hanya salah satu yang ada, maka LP yang lain/yang tidak dipakai TIDAK BOLEH DIHAPUS (CUKUP KOSONGKAN SAJA)
B43: Laporan penjualan hasil print out menjadi 3 lembar/disesuaikan dengan ukuran yang layak agar dapat dibaca dan dikoreksi
B44: Apabila dalam laporan LP kolom yang disediakan kurang karena penambahan produk baru, supervisor bisa konfirm ke Area Manger untuk segera diteruskan dan di follow up/atau di perbaiki oleh team TC
A46: 8. | B46: Apabila saat pengerjaan laporan menemukan kendala pada rumus seperti Reff!, solusi awal bisa dilakukan undo typing (ctrl + Z) untuk mengembalikan kesalahan saat pengerjaan atau bisa dengan menutup file pengerjaan laporan dan untuk tidak di simpan atau don't save pada laporan tersebut. Apabila laporan masih erorr supervisor bisa konfirm team TC agar dapat dibantu perbaiki laporan yang error atau tidak sesuai
A48: 9. | B48: Sheet food cost per item dibuat untuk acuan cara pengerjaan/mencari food cost pada setiap menu. Food cost item per paket supervisor bisa modifikasi dengan acuan hitungan yang sudah ada sesuai dengan komposisi paket dan kelas masing - masing
A50: 10. | B50: Apabila pada setiap format laporan mengharuskan adanya penambahan kolom, supervisor bisa menyampaikan kepada Area Manager untuk diteruskan ke team TC agar segera di follow up
A52: 11. | B52: Supervisor dapat memodifikasi laporan pada kolom - kolom yang tidak dikunci oleh team TC dengan catatan tidak untuk merubah rumus yang sudah ada yang akan mempengaruhi hasil penghitungan
A54: 12. | B54: Supervisor harus tetap memperhatikan hasil print out dari laporan - laporan yang sudah dikerjakan untuk melakukan pengecekan dari ukuran kertas, ukuran tulisan dan skala print out dan diperhatikan tulisan kiranya dapat dibaca dengan jelas atau tidaknya sebelum dikirim ke kantor dan dicek oleh team acoounting
A56: 13 | B56: TO/TI PERKEDEL MANUAL TIDAK TERUMUS PENGERJAAN SECARA MANUAL
A58: 14 | B58: PENCATATAN UNIT CABAI RAWIT PADA KOLOM VENDOR ADALAH GRAMASI CABAI YANG SUDAH DIPETIK (CABAI TANPA TANGKAI)

Sheet SOP ADMINISTRASI
B6: SOP PENGERJAAN ADMINISTRASI STORE
A8: 1 | B8: Pembelian paper polos seperti tutup cup minum polos/karakter, kertas KFC/kertas minyak (kertas warna coklat), kantong kertas ayam/burger, cup saos/cup pudding/cup 35ml, cover nasi polos tidak diperbolehkan beli dari luar warehouse RC dengan alasan apapun (NB : untuk plastik jumbo polos selama warehouse belum tersedia, masih ada toleransi untuk beli di luar)
A10: 2 | B10: Reimburse pulsa store (Rp 40.000) harus disertai screenshoot-an SMS masuk pulsa tersebut/nota asli dari counter dan harus tertera nomor yang diisi pulsa tersebut yaitu nomor store
A12: 3 | B12: Standarisasi nota adalah harus tertera tanggal, nama toko barang/item yang dibeli dengan jelas (jika hanya tertera kode barang, harap dituliskan dengan jelas barang tersebut) disertai stempel dan nomor HP toko, tanda tangan dan nama SPV
A14: 4 | B14: Transport pesanan/klaim free pesanan harus melampirkan nota pesanan dan struk postingan pesanan tersebut
A16: 5 | B16: Untuk vitamin, tidak diperbolehkan (yang termasuk ke dalam P3K adalah obat-obatan untuk kecelakaan yang terjadi saat di store, misalnya luka bakar/luka terkena pisau)
A18: 6 | B18: Gunting kuku, cukur kumis, semir sepatu, sisir (keperluan pribadi) dan lain-lain atau peralatan yang digunakan untuk penunjang kerapihan penampilan karyawan tidak diperbolehkan reimburst store (tunjangan penampilan sudah tertera pada gaji)
A20: 7 | B20: All administrasi staff (LKK, STOCK CONTROL, MCC, LO) dan all administrasi supervisor yang dikirim ke kantor wajib dikroscek dan diparaf supervisor
A22: 8 | B22: All laporan sebelum dikirim ke kantor/accounting, supervisor wajib kroscek form laporan-laporan dari kelengkapan form laporan, ukuran font dan kerapihan cetak/print laporan
A24: 9 | B24: BAHAN BAKU TELUR DAN CABAI RAWIT DI VENDOR TIDAK LAGI MASUK KEDALAM BAHAN NASGOR
A26: 10 | B26: PENCATATAN UNIT CABAI RAWIT PADA KOLOM VENDOR ADALAH GRAMASI CABAI YANG SUDAH DIPETIK (CABAI TANPA TANGKAI)

Sheet WEEKLY FC
A3: WEEKLY / MONTHLY INVENTORI
E5: Cabang : | F5: =LPKK!O4 -> RC SAMATA GOWA
E6: Periode : | F6: =LPKK!O5 -> 8-14 JANUARI 2025
A9: NO | B9: BAHAN | C9: UNIT | D9: QTY | E9: PRICE | F9: TOTAL (Rp)
A10: I | B10: BAHAN AYAM
A11: 1 | B11: DADA MENTOK | C11: PCS | D11: 112.3 | E11: 6154.7692 | F11: =D11*E11 -> 691180.58
A12: 2 | B12: DADA | C12: PCS | D12: 208 | E12: 7385.7231 | F12: =D12*E12 -> 1536230.4
A13: 3 | B13: PAHA ATAS | C13: PCS | D13: 208 | E13: 5949.6103 | F13: =D13*E13 -> 1237518.9
A14: 4 | B14: PAHA BAWAH | C14: PCS | D14: 240 | E14: 3898.0192 | F14: =D14*E14 -> 935524.62
A15: 5 | B15: SAYAP | C15: PCS | D15: 210 | E15: 4308.3385 | F15: =D15*E15 -> 904751.08 | K15: PRINT LEMBAR 1 | L15: =SUM(D11:D15) -> 978.3
A16: 6 | B16: CHICKEN PATTY | C16: PCS | D16: 11 | E16: 3729.3603 | F16: =D16*E16 -> 41022.963 | L16: =L15/414 -> 2.3630435
A17: 7 | B17: SAYAP TANPA KOLAR | C17: PCS | F17: =D17*E17 -> 0
A18: 8 | B18: PATTY BEEF | C18: PCS | F18: =D18*E18 -> 0
A19: 9 | B19: BEEF STEAK | C19: PCS | F19: =D19*E19 -> 0
A20: 10 | B20: DADA MENTOK TAKJIL | C20: PCS | E20: 4904.8889 | F20: =D20*E20 -> 0
A21: 11 | B21: DADA TAKJIL | C21: PCS | E21: 5722.3704 | F21: =D21*E21 -> 0
A22: 12 | B22: PAHA ATAS TAKJIL | C22: PCS | E22: 5313.6296 | F22: =D22*E22 -> 0
A23: 13 | B23: PAHA BAWAH TAKJIL | C23: PCS | E23: 3269.9259 | F23: =D23*E23 -> 0
A24: 14 | B24: SAYAP TAKJIL | C24: PCS | E24: 3678.6667 | F24: =D24*E24 -> 0
A25: 15 | B25: AYAM UTUH | C25: EKOR | D25: 30 | E25: 35000 | F25: =D25*E25 -> 1050000
A26: 16 | F26: =D26*E26 -> 0
A27: 17 | F27: =D27*E27 -> 0
A28: 18 | F28: =D28*E28 -> 0
A29: 19 | F29: =D29*E29 -> 0
A30: 20 | F30: =D30*E30 -> 0
E31: JUMLAH | F31: =SUM(F11:F30) -> 6396228.6
A32: II | B32: BAHAN PELENGKAP
A33: 1 | B33: VEGETABLE MIX | C33: KG | D33: 2.5 | E33: 30000 | F33: =D33*E33 -> 75000
A34: 2 | B34: BERAS | C34: KG | D34: 78 | E34: 14000 | F34: =D34*E34 -> 1092000
A35: 3 | B35: FRENCH FRIES | C35: KG | D35: 2.3 | E35: 26000 | F35: =D35*E35 -> 59800
A36: 4 | B36: ROTI BURGER | C36: PCS | D36: 69 | E36: 2907.0833 | F36: =D36*E36 -> 200588.75
A37: 5 | B37: SOSIS | C37: PCS | F37: =D37*E37 -> 0
A38: 6 | B38: PERKEDEL | C38: PCS | D38: 72 | E38: ='TO - TI'!D22 -> 1649.8049 | F38: =D38*E38 -> 118785.95
A39: 7 | B39: CRINKLE | C39: KG | D39: 0.7 | E39: 32000 | F39: =D39*E39 -> 22400
A40: 8 | B40: NUGGET COIN | C40: PCS | F40: =D40*E40 -> 0
A41: 9 | B41: NUGGET STICK | C41: PCS | F41: =D41*E41 -> 0
A42: 10 | B42: SOSIS MINI JUMBO | C42: PCS | F42: =D42*E42 -> 0
A43: 11 | B43: INDOMIE GORENG | C43: PACK | F43: =D43*E43 -> 0
A44: 12 | B44: KERUPUK UDANG | C44: PACK | F44: =D44*E44 -> 0
A45: 13 | B45: BUN BURGER BEEF | C45: PCS | F45: =D45*E45 -> 0
A46: 14 | B46: CHEESE UNTUK BEEF | C46: PCS | F46: =D46*E46 -> 0
A47: 15 | F47: =D47*E47 -> 0
A48: 16 | F48: =D48*E48 -> 0
A49: 17 | F49: =D49*E49 -> 0
A50: 18 | F50: =D50*E50 -> 0
A51: 19 | F51: =D51*E51 -> 0
A52: 20 | F52: =D52*E52 -> 0
B53: BAHAN ROTI
A54: 1 | B54: SLICED CHEESE | C54: KG | D54: 17 | E54: 858 | F54: =D54*E54 -> 14586
A55: 2 | B55: KEJU BATANG (170 GR ) | C55: PACK | D55: 0.5 | E55: 15900 | F55: =D55*E55 -> 7950
A56: 3 | B56: TEPUNG ROTI | C56: PACK | D56: 2 | E56: 10000 | F56: =D56*E56 -> 20000
A57: 4 | B57: CUKA DIXI 150 ML | C57: BOTOL | E57: 6600 | F57: =D57*E57 -> 0
A58: 5 | B58: BAWANG BOMBAY | C58: KG | E58: 5000 | F58: =D58*E58 -> 0
A59: 6 | B59: DRESSING BURGER | C59: RESEP | D59: 1 | E59: ='[1]HITUNGAN FC ITEM'!H109 -> 52887.469 | F59: =D59*E59 -> 52887.469
A60: 7 | B60: MARGARINE (200 GR ) | C60: PACK | D60: 2 | E60: 6100 | F60: =D60*E60 -> 12200
A61: 8 | B61: TOMAT | C61: KG | D61: 0.6 | E61: 10000 | F61: =D61*E61 -> 6000
A62: 9 | B62: ROTI TAWAR | C62: PCS | E62: 933 | F62: =D62*E62 -> 0
A63: 10 | B63: SELADA | C63: PACK | D63: 0.45 | E63: 15000 | F63: =D63*E63 -> 6750
A64: 11 | B64: GULA HALUS 250 GR | C64: KG | D64: 0.25 | E64: 10200 | F64: =D64*E64 -> 2550
A65: 12 | B65: SUSU ULTRA (250 ML ) | C65: PACK | E65: 4700 | F65: =D65*E65 -> 0
A66: 13 | F66: =D66*E66 -> 0
A67: 14 | F67: =D67*E67 -> 0
A68: 15 | F68: =D68*E68 -> 0
E69: JUMLAH | F69: =SUM(F33:F68) -> 1691498.2 | G69: JML BAHAN ROTI | I69: =SUM(F54:F68) -> 122923.47
A70: III | B70: BAHAN ES | K70: PRINT LEMBAR 2
A72: 1 | B72: GULA PASIR | C72: KG | D72: 3 | E72: 17600 | F72: =D72*E72 -> 52800
A73: 2 | B73: ICE CREAM ROCKET | C73: CUP | F73: =D73*E73 -> 0
A74: 3 | B74: ICE CREAM EMBER | C74: PAIL | E74: 160000 | F74: =D74*E74 -> 0
B75: BAHAN ES
A76: 4 | B76: SUSU PUTIH | C76: KLG | F76: =D76*E76 -> 0
A77: 5 | B77: AIR GALON | C77: GLN | D77: 6 | E77: 5000 | F77: =D77*E77 -> 30000
A78: 6 | B78: ES BATU | C78: PACK | E78: 16000 | F78: =D78*E78 -> 0
A79: 7 | B79: SIMPLE SYRUP | C79: LTR | E79: ='[1]HITUNGAN FC ITEM'!B17 -> 17463.158 | F79: =D79*E79 -> 0
A80: 8 | B80: GULA AREN | C80: KG | F80: =D80*E80 -> 0
A81: 9 | B81: NESTLE CARNATION (SKM) | C81: KG | D81: 1.5 | E81: 14100 | F81: =D81*E81 -> 21150
A82: 10 | F82: =D82*E82 -> 0
A83: 11 | F83: =D83*E83 -> 0
A84: 12 | F84: =D84*E84 -> 0
A85: 13 | F85: =D85*E85 -> 0
A86: 14 | F86: =D86*E86 -> 0
E87: JUMLAH | F87: =SUM(F72:F86) -> 103950 | G87: JUMLAH BAHAN ES | I87: =SUM(F76:F86) -> 51150
E88: TOTAL LEMBAR 1 | F88: =F31+F69+F87 -> 8191676.7
A92: NO | B92: BAHAN | C92: UNIT | D92: QTY | E92: PRICE | F92: TOTAL (Rp)
A93: IV | B93: BAHAN MINUMAN
A94: 1 | B94: TEH BOTOL SOSRO (TBS) | C94: PCS | D94: 56 | E94: 2167 | F94: =D94*E94 -> 121352
A95: 2 | B95: TEH SOSRO POUCH (TBO) | C95: PCS | D95: 48 | E95: 2271 | F95: =D95*E95 -> 109008
A96: 3 | B96: FRUIT TEA BOTOL | C96: PCS | D96: 13 | E96: 3500 | F96: =D96*E96 -> 45500
A97: 4 | B97: FRUIT TEA POUCH (FTG) | C97: PCS | F97: =D97*E97 -> 0
A98: 5 | B98: TEBS | C98: PCS | D98: 14 | E98: 3500 | F98: =D98*E98 -> 49000
A99: 6 | B99: AIR MINERAL BOTOL (AMB) | C99: PCS | D99: 275 | E99: 1667 | F99: =D99*E99 -> 458425
A100: 7 | B100: AIR MINERAL CUP (AMC) | C100: PCS | D100: 46 | E100: 458 | F100: =D100*E100 -> 21068
A101: 8 | B101: MILO | C101: PACK | D101: 3.69 | E101: 97450 | F101: =D101*E101 -> 359590.5
A102: 9 | B102: NESTEA | C102: PACK | D102: 3.2 | E102: 54570 | F102: =D102*E102 -> 174624
A103: 10 | B103: ORANGE | C103: PACK | E103: 54100 | F103: =D103*E103 -> 0
A104: 11 | B104: BUAH FROZEN JAMBU | C104: PCS | F104: =D104*E104 -> 0
A105: 12 | B105: BUAH FROZEN MELON | C105: PCS | F105: =D105*E105 -> 0
A106: 13 | B106: BUAH FROZEN STRAWBERRY | C106: PCS | F106: =D106*E106 -> 0
A107: 14 | B107: BUAH FROZEN SIRSAK | C107: PCS | F107: =D107*E107 -> 0
A108: 15 | B108: BUAH FROZEN MANGGA | C108: PCS | F108: =D108*E108 -> 0
A109: 16 | B109: BUAH FROZEN DURIAN | C109: PCS | F109: =D109*E109 -> 0
...

Sheet PEMBELIAN KREDIT
A5: LAPORAN PEMBELIAN BAHAN ( KREDIT )
H7: CABANG | I7: : | J7: =LPKK!O4 -> RC SAMATA GOWA
H8: PERIODE | I8: : | J8: =LPKK!O5 -> 8-14 JANUARI 2025
A10: TANGGAL | B10: NAMA SUPLIER | C10: NAMA BAHAN | D10: NOMOR | E10: JUMLAH | F10: HARGA | G10: TOTAL | H10: LAMA | K10: TANGGAL
D11: FAKTUR | E11: ( UNIT ) | F11: ( UNIT ) | H11: KREDIT | J11: JATUH TEMPO | K11: DIBAYAR
B14: PT CIOMAS ADISATWA | C14: MENTOK | E14: 130 | F14: =G14/E14 -> 5981.5865 | G14: =6220850/1200*150 -> 777606.25 | L14: =E14/46 -> 2.826087
C15: DADA | E15: 260 | F15: =G15/E15 -> 7177.9038 | G15: =6220850/1200*180*2 -> 1866255 | M15: =E20/60 -> 0.5
C16: PAHA ATAS | E16: 260 | F16: =G16/E16 -> 5782.2003 | G16: =6220850/1200*145*2 -> 1503372.1
C17: PAHA BAWAH | E17: 260 | F17: =G17/E17 -> 3788.3381 | G17: =6220850/1200*95*2 -> 984967.92
C18: SAYAP | E18: 260 | F18: =G18/E18 -> 4187.1106 | G18: =6220850/1200*105*2 -> 1088648.8
A20: 46035 | C20: AYAM UTUH | E20: 30 | F20: =G20/E20 -> 34000 | G20: 1020000
G21: =SUM(G14:G20) -> 7240850 | L21: =G14*11% -> 85536.688
A22: 46034 | B22: PT SINAR GOWA SUKSES | C22: PRIMA BOTOL | E22: 120 | F22: =G22/E22 -> 1666.6667 | G22: 200000
C23: STEE KOTAK | E23: 240 | F23: =G23/E23 -> 1583.9708 | G23: 380153
C24: TEH BOTOL 220ML | E24: 48 | F24: =G24/E24 -> 2166.6667 | G24: 104000
C25: TEH BOTOL 250ML | E25: 48 | F25: =G25/E25 -> 2500 | G25: 120000
C26: TEH BOTOL 1 LTR | E26: 36 | F26: =G26/E26 -> 7875 | G26: 283500
F27: =G27/E27 -> #DIV/0!
F28: =G28/E28 -> #DIV/0!
F29: =G29/E29 -> #DIV/0!
F30: =G30/E30 -> #DIV/0!
F31: =G31/E31 -> #DIV/0!
F32: =G32/E32 -> #DIV/0!
F33: =G33/E33 -> #DIV/0!
F34: =G34/E34 -> #DIV/0!
F35: =G35/E35 -> #DIV/0!
F36: =G36/E36 -> #DIV/0!
F37: =G37/E37 -> #DIV/0!
C38: FRUITEA | E38: 12 | F38: =G38/E38 -> 3500 | G38: 42000
C39: TEBS | E39: 12 | F39: =G39/E39 -> 3500 | G39: 42000
G40: =SUM(G22:G39) -> 1171653
B41: PT ROCKET CHICKEN INDONESIA | C41: MARINASI | E41: =L14+M15 -> 3.326087 | F41: ='WEEKLY FC'!E324 -> 82362 | G41: =F41*E41 -> 273943.17
G42: =G41 -> 273943.17
L44: =M44/486 -> 0.90123457 | M44: {=SUM(E20:E24+E33:E37)} -> 438
L48: =M48/414 -> 2.826087 | M48: {=SUM(E14:E18+E27:E31)} -> 1170
G49: =G43 -> 0 | L49: =30/60 -> 0.5
A50: 46033 | B50: CELEBES RICE | C50: BERAS | E50: 100 | F50: 14000 | G50: 1400000
G51: =G50 -> 1400000
G53: =G52 -> 0
B54: CV SUKSES BERSAMA | C54: SAOS CHILI | E54: 2500 | F54: =G54/E54 -> 200.9076 | G54: 502269 | L54: =G26+G40+G49+G51+G53+G54+G59+G60+G61 -> 3357422
A55: 46035 | C55: SAOS TOMAT | E55: 2500 | F55: =G55/E55 -> 206.002 | G55: 515005
C56: CHILI JRG | E56: 3 | F56: =G56/E56 -> 64854 | G56: 194562
F57: =G57/E57 -> #DIV/0!
F58: =G58/E58 -> #DIV/0!
F59: =G59/E59 -> #DIV/0!
F60: =G60/E60 -> #DIV/0!
F61: =G61/E61 -> #DIV/0!
G62: =SUM(G54:G56) -> 1211836
A63: 46029 | B63: PT MITRA ABADIJAYA SUKSES | C63: TEPUNG GERBANG | E63: 100 | F63: =G63/E63 -> 9362.64 | G63: 936264
G64: =G63 -> 936264
L89: =H92+H91+H90+H61+H44+G48+G39 -> 42000
L91: =(E33+E49)/46 -> 0
L92: =(E40+E41+E42+E43+E44+E58+E59+E60+E61+E62)/486 -> 0.0068438003
L93: =(E48+E63)/60 -> 1.6666667
L113: =E48+E63 -> 100 | M113: =L113/60 -> 1.6666667
G114: =SUM(G65:G113) -> 0
G115: =G21+G40+G42+G49+G51+G53+G62+G64+G113 -> 12234546
J117: Paraf Supervisor
J121: ( )
A124: NOTE :
A125: 1. SELECT BAGIAN YANG AKAN DIPRINT
A126: 2. SETELAH ITU PILIH FILE => PRINT
A127: 3. PADA BAGIAN SETTINGS ATUR SEBAGAI BERIKUT :
A128: - PILIH PRINT SELECTION
A129: - LANDSCAPE ORIENTATION
A130: - SESUAIKAN UKURAN KERTAS YANG AKAN DIPRINT, A4/F4
A131: - ATUR MARGIN SEBAGAI BERIKUT :
A132: - TOP : 1
A133: - RIGHT : 0,3
A134: - LEFT : 0,3
A135: - BOTTOM : 0,3
A136: - LALU PILIH FIT ALL COLUMNS ON ONE PAGE

Sheet LPKK
A2: LAPORAN PENGELUARAN KAS KECIL
N4: CABANG : | O4: RC SAMATA GOWA
N5: PERIODE : | O5: 8-14 JANUARI 2025
A8: TGL | B8: NO | C8: BAHAN | D8: BAHAN | E8: BAHAN | F8: BAHAN | G8: BAHAN | H8: MINYAK | I8: GROCERIES / | J8: BAHAN | K8: TRANSPORT | L8: FOTO COPY / | M8: NO ACC | N8: LAIN - LAIN | Q8: SALDO
B9: NOTA | C9: AYAM | D9: PELENGKAP | E9: ES | F9: MINUMAN | G9: PEMBUNGKUS | H9: GORENG | I9: BUMBU | J9: PEMBERSIH | L9: ATK | N9: ( Rp ) | O9: KETERANGAN | P9: JUMLAH
B10: 1 | N10: 4621304 | O10: TRANSFER OWNER CASH | P10: =SUM(C10:N10) -> 4621304
A11: 46030 | B11: 2 | N11: 90300 | O11: XL PRABAYAR | P11: =SUM(C11:N11) -> 90300
B12: 3 | N12: 371300 | O12: WIFI | P12: =SUM(C12:N12) -> 371300
B13: 4 | N13: 203000 | O13: TOKEN LISTRIK | P13: =SUM(C13:N13) -> 203000
B14: 5 | E14: 16000 | O14: ES BATU | P14: =SUM(C14:N14) -> 16000 | Q14: =SUM(P10:P17) -> 5449904
B15: 6 | D15: 5000 | I15: 143000 | O15: SAYURAN | P15: =SUM(C15:N15) -> 148000
P16: =SUM(C16:N16) -> 0
P17: =SUM(C17:N17) -> 0
P18: =SUM(C18:N18) -> 0
P19: =SUM(C19:N19) -> 0
P20: =SUM(C20:N20) -> 0
P21: =SUM(C21:N21) -> 0
N22: ='LAPORAN KAS PERIODE'!C18 -> 221018 | O22: TF OWNER GOFOOD | P22: =SUM(C22:N22) -> 221018
N23: ='LAPORAN KAS PERIODE'!C19 -> 379318 | O23: TF OWNER GRAB FOOD | P23: =SUM(C23:N23) -> 379318 | Q23: =SUM(P22:P25) -> 1892686
N24: ='LAPORAN KAS PERIODE'!C20 -> 349496 | O24: TF OWNER SHOPEE FOOD' | P24: =SUM(C24:N24) -> 349496
N25: ='LAPORAN KAS PERIODE'!C21 -> 942854 | O25: TF OWNER QRIS | P25: =SUM(C25:N25) -> 942854
N26: ='LAPORAN KAS PERIODE'!C24 -> 6647 | O26: ADMIN OVO | P26: =SUM(C26:N26) -> 6647
P27: =SUM(C27:N27) -> 0
P28: =SUM(C28:N28) -> 0
B29: 14 | P29: =SUM(C29:N29) -> 0
B30: 15 | P30: =SUM(C30:N30) -> 0
B31: 16 | P31: =SUM(C31:N31) -> 0
B32: 17 | P32: =SUM(C32:N32) -> 0
B33: 18 | P33: =SUM(C33:N33) -> 0
B34: 19 | P34: =SUM(C34:N34) -> 0
B35: 20 | P35: =SUM(C35:N35) -> 0
B36: 21 | P36: =SUM(C36:N36) -> 0
B37: 22 | P37: =SUM(C37:N37) -> 0
B38: 23 | P38: =SUM(C38:N38) -> 0
B39: 24 | P39: =SUM(C39:N39) -> 0
B40: 25 | P40: =SUM(C40:N40) -> 0
C41: =SUM(C11:C40) -> 0 | D41: =SUM(D11:D40) -> 5000 | E41: =SUM(E11:E40) -> 16000 | F41: =SUM(F11:F40) -> 0 | G41: =SUM(G11:G40) -> 0 | H41: =SUM(H11:H40) -> 0 | I41: =SUM(I11:I40) -> 143000 | J41: =SUM(J11:J40) -> 0 | ... N41: =SUM(N11:N40) -> 2563933 | P41: =SUM(P10:P40) -> 7349237 | Q41: =P41 -> 7349237
A42: 45666 | B42: 7 | D42: 18000 | O42: ROTI TAWAR | P42: =SUM(C42:N42) -> 18000
B43: 8 | D43: 40900 | N43: 200 | O43: BAHAN PATTY | P43: =SUM(C43:N43) -> 41100
B44: 9 | E44: 16000 | O44: ES BATU | P44: =SUM(C44:N44) -> 16000
B45: 10 | D45: 6000 | I45: 116000 | O45: SAYURAN/TELUR | P45: =SUM(C45:N45) -> 122000
B46: 11 | L46: 20000 | O46: PRINT | P46: =SUM(C46:N46) -> 20000 | Q46: =SUM(P42:P51) -> 217100
P47: =SUM(C47:N47) -> 0 | Q47: =Q46-P44 -> 201100
P48: =SUM(C48:N48) -> 0
P49: =SUM(C49:N49) -> 0
P50: =SUM(C50:N50) -> 0
P51: =SUM(C51:N51) -> 0
P52: =SUM(C52:N52) -> 0
P53: =SUM(C53:N53) -> 0
P54: =SUM(C54:N54) -> 0
N55: ='LAPORAN KAS PERIODE'!D18 -> 226409 | O55: TF OWNER GOFOOD | P55: =SUM(C55:N55) -> 226409
N56: ='LAPORAN KAS PERIODE'!D19 -> 541038 | O56: TF OWNER GRAB FOOD | P56: =SUM(C56:N56) -> 541038
N57: ='LAPORAN KAS PERIODE'!D20 -> 77854 | O57: TF OWNER SHOPEE FOOD' | P57: =SUM(C57:N57) -> 77854
P58: =SUM(C58:N58) -> 0
O59: TF OWNER SHOPEE FOOD' | P59: =SUM(C59:N59) -> 0
O60: TF OWNER QRIS | P60: =SUM(C60:N60) -> 0
O61: ADMIN OVO | P61: =SUM(C61:N61) -> 0
P62: =SUM(C62:N62) -> 0
N63: ='LAPORAN KAS PERIODE'!D21 -> 1894644 | O63: TF OWNER QRIS | P63: =SUM(C63:N63) -> 1894644 | R63: =SUM(P43:P62) -> 1044401
N64: ='LAPORAN KAS PERIODE'!D24 -> 13356 | O64: ADMINOVO | P64: =SUM(C64:N64) -> 13356
P65: =SUM(C65:N65) -> 0
P66: =SUM(C66:N66) -> 0
P67: =SUM(C67:N67) -> 0
P68: =SUM(C68:N68) -> 0
P69: =SUM(C69:N69) -> 0
P70: =SUM(C70:N70) -> 0
P71: =SUM(C71:N71) -> 0
P72: =SUM(C72:N72) -> 0
P73: =SUM(C73:N73) -> 0
P74: =SUM(C74:N74) -> 0
P75: =SUM(C75:N75) -> 0
P76: =SUM(C76:N76) -> 0
... P78: =SUM(C78:N78) -> 0
C79: =SUM(C42:C78) -> 0 | D79: =SUM(D42:D78) -> 64900 | E79: =SUM(E42:E78) -> 16000 | F79: =SUM(F42:F78) -> 0 | G79: =SUM(G42:G78) -> 0 | H79: =SUM(H42:H78) -> 0 | I79: =SUM(I42:I78) -> 116000 | J79: =SUM(J42:J78) -> 0 | ... N79: =SUM(N42:N78) -> 2753501 | P79: =SUM(P42:P78) -> 2970401 | Q79: =Q41+P79 -> 10319638
A80: 46032 | B80: 12 | E80: 16000 | O80: ES BATU | P80: =SUM(C80:N80) -> 16000
B81: 13 | N81: 68500 | O81: RENOVASI DAPUR | P81: =SUM(C81:N81) -> 68500
B82: 14 | E82: 75000 | O82: AIR GALON | P82: =SUM(C82:N82) -> 75000
B83: 15 | N83: 130000 | O83: IURAN SAMPAH | P83: =SUM(C83:N83) -> 130000 | Q83: =SUM(P80:P94) -> 402500
B84: 16 | L84: 5000 | N84: 108000 | O84: PRINT/MATERAI 9 LBR | P84: =SUM(C84:N84) -> 113000
B85: 17 | P85: =SUM(C85:N85) -> 0
B86: 18 | P86: =SUM(C86:N86) -> 0
B87: 19 | P87: =SUM(C87:N87) -> 0
B88: 20 | P88: =SUM(C88:N88) -> 0
B89: 21 | P89: =SUM(C89:N89) -> 0
B90: 22 | P90: =SUM(C90:N90) -> 0
B91: 23 | P91: =SUM(C91:N91) -> 0
B92: 24 | P92: =SUM(C92:N92) -> 0
B93: 25 | P93: =SUM(C93:N93) -> 0
B94: 26 | P94: =SUM(C94:N94) -> 0
N95: ='LAPORAN KAS PERIODE'!E18 -> 81209 | O95: TF OWNER GOFOOD | P95: =SUM(C95:N95) -> 81209
N96: ='LAPORAN KAS PERIODE'!E19 -> 634741 | O96: TF OWNER GRAB FOOD | P96: =SUM(C96:N96) -> 634741
N97: ='LAPORAN KAS PERIODE'!E20 -> 122797 | O97: TF OWNER SHOPEE FOOD' | P97: =SUM(C97:N97) -> 122797
N98: ='LAPORAN KAS PERIODE'!E21 -> 1622562 | O98: TF OWNER QRIS | P98: =SUM(C98:N98) -> 1622562
N99: ='LAPORAN KAS PERIODE'!E24 -> 11438 | O99: ADMIN OVO | P99: =SUM(C99:N99) -> 11438
A100: SUB TOTAL | C100: =SUM(C80:C99) -> 0 | D100: =SUM(D80:D99) -> 0 | E100: =SUM(E80:E99) -> 91000 | F100: =SUM(F80:F99) -> 0 | G100: =SUM(G80:G99) -> 0 | H100: =SUM(H80:H99) -> 0 | I100: =SUM(I80:I99) -> 0 | J100: =SUM(J80:J99) -> 0 | ... N100: =SUM(N80:N99) -> 2779247 | P100: =SUM(P80:P99) -> 2875247 | Q100: =Q79+P100 -> 13194885
A101: 46033 | B101: 17 | N101: 30100 | O101: KIRIM LAPORAN | P101: =SUM(C101:N101) -> 30100
B102: 18 | N102: 203000 | O102: LISTRIK | P102: =SUM(C102:N102) -> 203000
B103: 19 | D103: 38300 | E103: 88000 | H103: 40700 | J103: 44200 | O103: BAHAN ROTI/GULA/MINYAK/PEMBERSIH | P103: =SUM(C103:N103) -> 211200
B104: 20 | N104: 410000 | O104: GAS 2 | P104: =SUM(C104:N104) -> 410000 | Q104: =SUM(P101:P114) -> 872300
B105: 21 | J105: 18000 | O105: SABUN CUCI PIRING | P105: =SUM(C105:N105) -> 18000
...

Sheet VENDOR
M2: VENDOR REPORT | AI2: CABANG : | AJ2: =LPKK!O4 -> RC SAMATA GOWA
AI3: PERIODE : | AJ3: =LPKK!O5 -> 8-14 JANUARI 2025 | AQ3: RINCIAN PENCATATAN PEMBELIAN AYAM KREDIT
B5: TGL FAKTUR | C5: NO | E5: PEMAKAIAN | G5: PERSEDIAAN | I5: 46030 | K5: 46031 | M5: 46032 | O5: 46033 | Q5: 46034 | S5: 46035 | U5: 46036 | AC5: KHUSUS TO / TI ( - ) | AE5: KREDIT BARGUD | AG5: KREDIT BAHAN BAKU | AI5: TOTAL | AK5: PERSEDIAAN | AM5: PEMAKAIAN
D6: KETERANGAN BAHAN | E6: MINGGU LALU | G6: AWAL | AC6: C. PATTY / CATERING STAFF ( - ) | AI6: PEMBELIAN | AK6: AKHIR | AM6: MINGGU INI | AP6: TGL FAKTUR
B7: HARI | E7: DLM SATUAN | G7: DLM SATUAN | I7: KAMIS | K7: JUMAT | M7: SABTU | O7: MINGGU | Q7: SENIN | S7: SELASA | U7: RABU | AC7: PERKEDEL / BARGUD | AG7: AYAM DLL | AI7: DLM SATUAN | AK7: DLM SATUAN | AM7: DLM SATUAN | AP7: HARI
E8: Rp | F8: Unit | G8: Rp | H8: Unit | I8: Rp | J8: Unit | K8: Rp | L8: Unit | M8: Rp | N8: Unit | O8: Rp | P8: Unit | Q8: Rp | R8: Unit | S8: Rp | T8: Unit | U8: Rp | V8: Unit | W8: Rp | X8: Unit | Y8: Rp | Z8: Unit | AA8: Rp | AB8: Unit | AC8: Rp | AD8: Unit | AE8: Rp | AF8: Unit | AG8: Rp | AH8: Unit | AI8: Rp | AJ8: Unit | AK8: Rp | AL8: Unit | AM8: Rp | AN8: Unit | AQ8: RP | AR8: UNIT | AS8: RP | AT8: UNIT | AU8: RP | AV8: UNIT | AW8: RP | AX8: UNIT | AY8: RP | AZ8: UNIT | BA8: RP | BB8: UNIT | BC8: RP | BD8: UNIT
D9: AYAM | I9: =SUM(I10:I14) -> 0 | K9: =SUM(K10:K14) -> 0 | M9: =SUM(M10:M14) -> 0 | O9: =SUM(O10:O14) -> 0 | Q9: =SUM(Q10:Q14) -> 0 | S9: =SUM(S10:S14) -> 0 | U9: =SUM(U10:U14) -> 0 | W9: =SUM(W10:W14) -> 0 | Y9: =SUM(Y10:Y14) -> 0 | AA9: =SUM(AA10:AA14) -> 0 | AG9: =SUM(AG10:AG14) -> 6220850 | AI9: =SUM(AI10:AI14) -> 5939783.4 | AP9: AYAM | AQ9: =SUM(AQ10:AQ14) -> 6220850 | AS9: =SUM(AS10:AS14) -> 0 | AU9: =SUM(AU10:AU14) -> 0 | AW9: =SUM(AW10:AW14) -> 0 | AY9: =SUM(AY10:AY14) -> 0 | BA9: =SUM(BA10:BA14) -> 0 | BC9: =SUM(BC10:BC14) -> 0
C10: 1 | D10: ='WEEKLY FC'!B11 -> DADA MENTOK | E10: 1119761.3 | F10: 191.4 | G10: 818584.31 | H10: 133 | AC10: =-'TO - TI'!I20-'TO - TI'!S7 -> -30773.846 | AD10: =-'TO - TI'!Q7-'TO - TI'!G7 -> -12 | AG10: =SUM(AQ10+AS10+AU10+AW10+AY10+BA10+BC10) -> 777606.25 | AH10: =SUM(AR10+AT10+AV10+AX10+AZ10+BB10+BD10) -> 130 | AI10: =SUM(I10,K10,M10,O10,Q10,S10,U10,W10,Y10,AA10,AC10,AE10,AG10) -> 746832.4 | AJ10: =SUM(J10,L10,N10,P10,R10,T10,V10,X10,Z10,AB10,AD10,AF10,AH10) -> 118 | AK10: =('WEEKLY FC'!F11) -> 691180.58 | AL10: ='WEEKLY FC'!D11 -> 112.3 | AM10: =G10+AI10-AK10 -> 874236.13 | AN10: =H10+AJ10-AL10 -> 138.7 | AP10: DADA MENTOK | AQ10: ='PEMBELIAN KREDIT'!G14 -> 777606.25 | AR10: ='PEMBELIAN KREDIT'!E14 -> 130
C11: 2 | D11: ='WEEKLY FC'!B12 -> DADA | E11: 2846596.6 | F11: 391 | G11: 1824273.6 | H11: 247 | AC11: =-'TO - TI'!I7-'TO - TI'!N7 -> -55391.748 | AD11: =-'TO - TI'!G7-'TO - TI'!L7 -> -7 | AG11: =SUM(AQ11+AS11+AU11+AW11+AY11+BA11+BC11) -> 1866255 | AH11: =SUM(AR11+AT11+AV11+AX11+AZ11+BB11+BD11) -> 260 | AI11: =SUM(I11,K11,M11,O11,Q11,S11,U11,W11,Y11,AA11,AC11,AE11,AG11) -> 1810863.3 | AJ11: =SUM(J11,L11,N11,P11,R11,T11,V11,X11,Z11,AB11,AD11,AF11,AH11) -> 253 | AK11: =('WEEKLY FC'!F12) -> 1536230.4 | AL11: ='WEEKLY FC'!D12 -> 208 | AM11: =G11+AI11-AK11 -> 2098906.5 | AN11: =H11+AJ11-AL11 -> 292 | AP11: DADA | AQ11: ='PEMBELIAN KREDIT'!G15 -> 1866255 | AR11: ='PEMBELIAN KREDIT'!E15 -> 260
C12: 3 | D12: ='WEEKLY FC'!B13 -> PAHA ATAS | E12: 2357685.9 | F12: 401 | G12: 1481453 | H12: 249 | AG12: =SUM(AQ12+AS12+AU12+AW12+AY12+BA12+BC12) -> 1503372.1 | AH12: =SUM(AR12+AT12+AV12+AX12+AZ12+BB12+BD12) -> 260 | AI12: =SUM(I12,K12,M12,O12,Q12,S12,U12,W12,Y12,AA12,AC12,AE12,AG12) -> 1503372.1 | AJ12: =SUM(J12,L12,N12,P12,R12,T12,V12,X12,Z12,AB12,AD12,AF12,AH12) -> 260 | AK12: =('WEEKLY FC'!F13) -> 1237518.9 | AL12: ='WEEKLY FC'!D13 -> 208 | AM12: =G12+AI12-AK12 -> 1747306.1 | AN12: =H12+AJ12-AL12 -> 301 | AP12: PAHA ATAS | AQ12: ='PEMBELIAN KREDIT'!G16 -> 1503372.1 | AR12: ='PEMBELIAN KREDIT'!E16 -> 260
C13: 4 | D13: ='WEEKLY FC'!B14 -> PAHA BAWAH | E13: 1451138.1 | F13: 377 | G13: 1064159.2 | H13: 273 | AC13: =-'TO - TI'!S8-'TO - TI'!N9-'TO - TI'!D19 -> -194900.96 | AD13: =-'TO - TI'!Q8-'TO - TI'!L9-'TO - TI'!B19 -> -50 | AG13: =SUM(AQ13+AS13+AU13+AW13+AY13+BA13+BC13) -> 984967.92 | AH13: =SUM(AR13+AT13+AV13+AX13+AZ13+BB13+BD13) -> 260 | AI13: =SUM(I13,K13,M13,O13,Q13,S13,U13,W13,Y13,AA13,AC13,AE13,AG13) -> 790066.96 | AJ13: =SUM(J13,L13,N13,P13,R13,T13,V13,X13,Z13,AB13,AD13,AF13,AH13) -> 210 | AK13: =('WEEKLY FC'!F14) -> 935524.62 | AL13: ='WEEKLY FC'!D14 -> 240 | AM13: =G13+AI13-AK13 -> 918701.59 | AN13: =H13+AJ13-AL13 -> 243 | AP13: PAHA BAWAH | AQ13: ='PEMBELIAN KREDIT'!G17 -> 984967.92 | AR13: ='PEMBELIAN KREDIT'!E17 -> 260
B14: A | C14: 5 | D14: ='WEEKLY FC'!B15 -> SAYAP | E14: 1929424.8 | F14: 453 | G14: 1085701.3 | H14: 252 | AC14: =-'TO - TI'!N10 -> 0 | AD14: =-'TO - TI'!L10 -> 0 | AG14: =SUM(AQ14+AS14+AU14+AW14+AY14+BA14+BC14) -> 1088648.8 | AH14: =SUM(AR14+AT14+AV14+AX14+AZ14+BB14+BD14) -> 260 | AI14: =SUM(I14,K14,M14,O14,Q14,S14,U14,W14,Y14,AA14,AC14,AE14,AG14) -> 1088648.8 | AJ14: =SUM(J14,L14,N14,P14,R14,T14,V14,X14,Z14,AB14,AD14,AF14,AH14) -> 260 | AK14: =('WEEKLY FC'!F15) -> 904751.08 | AL14: ='WEEKLY FC'!D15 -> 210 | AM14: =G14+AI14-AK14 -> 1269599 | AN14: =H14+AJ14-AL14 -> 302 | AP14: SAYAP | AQ14: ='PEMBELIAN KREDIT'!G18 -> 1088648.8 | AR14: ='PEMBELIAN KREDIT'!E18 -> 260
B15: Y | C15: 6 | D15: ='WEEKLY FC'!B16 -> CHICKEN PATTY | E15: 201385.46 | F15: 54 | G15: 22376.162 | H15: 6 | AC15: ='TO - TI'!S21 -> 264706.31 | AD15: ='TO - TI'!Q23 -> 69 | AI15: =SUM(I15,K15,M15,O15,Q15,S15,U15,W15,Y15,AA15,AC15,AE15,AG15) -> 264706.31 | AJ15: =SUM(J15,L15,N15,P15,R15,T15,V15,X15,Z15,AB15,AD15,AF15,AH15) -> 69 | AK15: =('WEEKLY FC'!F16) -> 41022.963 | AL15: ='WEEKLY FC'!D16 -> 11 | AM15: =G15+AI15-AK15 -> 246059.51 | AN15: =H15+AJ15-AL15 -> 64
B16: A | C16: 7 | D16: ='WEEKLY FC'!B17 -> SAYAP TANPA KOLAR | E16: 0 | F16: 0 | G16: 0 | H16: 0 | AI16: =SUM(I16,K16,M16,O16,Q16,S16,U16,W16,Y16,AA16,AC16,AE16,AG16) -> 0 | AJ16: =SUM(J16,L16,N16,P16,R16,T16,V16,X16,Z16,AB16,AD16,AF16,AH16) -> 0 | AK16: =('WEEKLY FC'!F17) -> 0 | AL16: ='WEEKLY FC'!D17 -> 0 | AM16: =G16+AI16-AK16 -> 0 | AN16: =H16+AJ16-AL16 -> 0
B17: M | C17: 8 | D17: ='WEEKLY FC'!B18 -> PATTY BEEF | E17: 0 | F17: 0 | G17: 0 | H17: 0 | AI17: =SUM(I17,K17,M17,O17,Q17,S17,U17,W17,Y17,AA17,AC17,AE17,AG17) -> 0 | AJ17: =SUM(J17,L17,N17,P17,R17,T17,V17,X17,Z17,AB17,AD17,AF17,AH17) -> 0 | AK17: ='WEEKLY FC'!F18 -> 0 | AL17: ='WEEKLY FC'!D18 -> 0 | AM17: =G17+AI17-AK17 -> 0 | AN17: =H17+AJ17-AL17 -> 0 | AP17: NB. RINCIAN PENCATATAN PEMBELIAN AYAM KREDIT TIDAK PERLU DI PRINT
C18: 9 | D18: ='WEEKLY FC'!B19 -> BEEF STEAK | E18: 0 | F18: 0 | G18: 0 | H18: 0 | AI18: =SUM(I18,K18,M18,O18,Q18,S18,U18,W18,Y18,AA18,AC18,AE18,AG18) -> 0 | AJ18: =SUM(J18,L18,N18,P18,R18,T18,V18,X18,Z18,AB18,AD18,AF18,AH18) -> 0 | AK18: ='WEEKLY FC'!F19 -> 0 | AL18: ='WEEKLY FC'!D19 -> 0 | AM18: =G18+AI18-AK18 -> 0 | AN18: =H18+AJ18-AL18 -> 0
C19: 10 | D19: ='WEEKLY FC'!B20 -> DADA MENTOK TAKJIL | E19: 0 | F19: 0 | G19: 0 | H19: 0 | AG19: =SUM(AQ23+AS23+AU23+AW23+AY23+BA23+BC23) -> 0 | AH19: =SUM(AR23+AT23+AV23+AX23+AZ23+BB23+BD23) -> 0 | AI19: =SUM(I19,K19,M19,O19,Q19,S19,U19,W19,Y19,AA19,AC19,AE19,AG19) -> 0 | AJ19: =SUM(J19,L19,N19,P19,R19,T19,V19,X19,Z19,AB19,AD19,AF19,AH19) -> 0 | AK19: ='WEEKLY FC'!F20 -> 0 | AL19: ='WEEKLY FC'!D20 -> 0 | AM19: =G19+AI19-AK19 -> 0 | AN19: =H19+AJ19-AL19 -> 0 | AP19: TGL FAKTUR
C20: 11 | D20: ='WEEKLY FC'!B21 -> DADA TAKJIL | E20: 0 | F20: 0 | G20: 0 | H20: 0 | AG20: =SUM(AQ24+AS24+AU24+AW24+AY24+BA24+BC24) -> 0 | AH20: =SUM(AR24+AT24+AV24+AX24+AZ24+BB24+BD24) -> 0 | AI20: =SUM(I20,K20,M20,O20,Q20,S20,U20,W20,Y20,AA20,AC20,AE20,AG20) -> 0 | AJ20: =SUM(J20,L20,N20,P20,R20,T20,V20,X20,Z20,AB20,AD20,AF20,AH20) -> 0 | AK20: ='WEEKLY FC'!F21 -> 0 | AL20: ='WEEKLY FC'!D21 -> 0 | AM20: =G20+AI20-AK20 -> 0 | AN20: =H20+AJ20-AL20 -> 0 | AP20: HARI
C21: 12 | D21: ='WEEKLY FC'!B22 -> PAHA ATAS TAKJIL | E21: 0 | F21: 0 | G21: 0 | H21: 0 | AG21: =SUM(AQ25+AS25+AU25+AW25+AY25+BA25+BC25) -> 0 | AH21: =SUM(AR25+AT25+AV25+AX25+AZ25+BB25+BD25) -> 0 | AI21: =SUM(I21,K21,M21,O21,Q21,S21,U21,W21,Y21,AA21,AC21,AE21,AG21) -> 0 | AJ21: =SUM(J21,L21,N21,P21,R21,T21,V21,X21,Z21,AB21,AD21,AF21,AH21) -> 0 | AK21: ='WEEKLY FC'!F22 -> 0 | AL21: ='WEEKLY FC'!D22 -> 0 | AM21: =G21+AI21-AK21 -> 0 | AN21: =H21+AJ21-AL21 -> 0 | AQ21: RP | AR21: UNIT | AS21: RP | AT21: UNIT | AU21: RP | AV21: UNIT | AW21: RP | AX21: UNIT | AY21: RP | AZ21: UNIT | BA21: RP | BB21: UNIT | BC21: RP | BD21: UNIT
C22: 13 | D22: ='WEEKLY FC'!B23 -> PAHA BAWAH TAKJIL | E22: 0 | F22: 0 | G22: 0 | H22: 0 | AG22: =SUM(AQ26+AS26+AU26+AW26+AY26+BA26+BC26) -> 0 | AH22: =SUM(AR26+AT26+AV26+AX26+AZ26+BB26+BD26) -> 0 | AI22: =SUM(I22,K22,M22,O22,Q22,S22,U22,W22,Y22,AA22,AC22,AE22,AG22) -> 0 | AJ22: =SUM(J22,L22,N22,P22,R22,T22,V22,X22,Z22,AB22,AD22,AF22,AH22) -> 0 | AK22: ='WEEKLY FC'!F23 -> 0 | AL22: ='WEEKLY FC'!D23 -> 0 | AM22: =G22+AI22-AK22 -> 0 | AN22: =H22+AJ22-AL22 -> 0 | AP22: AYAM | AQ22: =SUM(AQ23:AQ27) -> 0 | AS22: =SUM(AS23:AS27) -> 0 | AU22: =SUM(AU23:AU27) -> 0 | AW22: =SUM(AW23:AW27) -> 0 | AY22: =SUM(AY23:AY27) -> 0 | BA22: =SUM(BA23:BA27) -> 0 | BC22: =SUM(BC23:BC27) -> 0
C23: 14 | D23: ='WEEKLY FC'!B24 -> SAYAP TAKJIL | E23: 0 | F23: 0 | G23: 0 | H23: 0 | AG23: =SUM(AQ27+AS27+AU27+AW27+AY27+BA27+BC27) -> 0 | AH23: =SUM(AR27+AT27+AV27+AX27+AZ27+BB27+BD27) -> 0 | AI23: =SUM(I23,K23,M23,O23,Q23,S23,U23,W23,Y23,AA23,AC23,AE23,AG23) -> 0 | AJ23: =SUM(J23,L23,N23,P23,R23,T23,V23,X23,Z23,AB23,AD23,AF23,AH23) -> 0 | AK23: ='WEEKLY FC'!F24 -> 0 | AL23: ='WEEKLY FC'!D24 -> 0 | AM23: =G23+AI23-AK23 -> 0 | AN23: =H23+AJ23-AL23 -> 0 | AP23: DADA MENTOK TAKJIL
C24: 15 | D24: ='WEEKLY FC'!B25 -> AYAM UTUH | E24: 980000 | F24: 28 | G24: 315000 | H24: 9 | AG24: =SUM(AQ28+AS28+AU28+AW28+AY28+BA28+BC28) -> 1020000 | AH24: =SUM(AR28+AT28+AV28+AX28+AZ28+BB28+BD28) -> 30 | AI24: =SUM(I24,K24,M24,O24,Q24,S24,U24,W24,Y24,AA24,AC24,AE24,AG24) -> 1020000 | AJ24: =SUM(J24,L24,N24,P24,R24,T24,V24,X24,Z24,AB24,AD24,AF24,AH24) -> 30 | AK24: ='WEEKLY FC'!F25 -> 1050000 | AL24: ='WEEKLY FC'!D25 -> 30 | AM24: =G24+AI24-AK24 -> 285000 | AN24: =H24+AJ24-AL24 -> 9 | AP24: DADA TAKJIL
C25: 16 | D25: ='WEEKLY FC'!B30 -> 0 | E25: 0 | F25: 0 | G25: 0 | H25: 0 | AI25: =SUM(I25,K25,M25,O25,Q25,S25,U25,W25,Y25,AA25,AC25,AE25,AG25) -> 0 | AJ25: =SUM(J25,L25,N25,P25,R25,T25,V25,X25,Z25,AB25,AD25,AF25,AH25) -> 0 | AK25: ='WEEKLY FC'!F26 -> 0 | AL25: ='WEEKLY FC'!D26 -> 0 | AM25: =G25+AI25-AK25 -> 0 | AN25: =H25+AJ25-AL25 -> 0 | AP25: PAHA ATAS TAKJIL
C26: 1 | D26: ='WEEKLY FC'!B33 -> VEGETABLE MIX | E26: 34500 | F26: 1.15 | G26: 97500 | H26: 3.25 | AI26: =SUM(I26,K26,M26,O26,Q26,S26,U26,W26,Y26,AA26,AC26,AE26,AG26) -> 0 | AJ26: =SUM(J26,L26,N26,P26,R26,T26,V26,X26,Z26,AB26,AD26,AF26,AH26) -> 0 | AK26: ='WEEKLY FC'!F33 -> 75000 | AL26: ='WEEKLY FC'!D33 -> 2.5 | AM26: =G26+AI26-AK26 -> 22500 | AN26: =H26+AJ26-AL26 -> 0.75 | AP26: PAHA BAWAH TAKJIL
B27: P | C27: 2 | D27: ='WEEKLY FC'!B34 -> BERAS | E27: 1420085.9 | F27: 106.54545 | G27: 826000 | H27: 59 | AC27: =-'TO - TI'!I23-'TO - TI'!N11 -> -126609.71 | AD27: =-'TO - TI'!G23/11 -> -4.7272727 | AG27: ='PEMBELIAN KREDIT'!G50 -> 1400000 | AH27: 100 | AI27: =SUM(I27,K27,M27,O27,Q27,S27,U27,W27,Y27,AA27,AC27,AE27,AG27) -> 1273390.3 | AJ27: =SUM(J27,L27,N27,P27,R27,T27,V27,X27,Z27,AB27,AD27,AF27,AH27) -> 95.272727 | AK27: ='WEEKLY FC'!F34 -> 1092000 | AL27: ='WEEKLY FC'!D34 -> 78 | AM27: =G27+AI27-AK27 -> 1007390.3 | AN27: =H27+AJ27-AL27 -> 76.272727 | AP27: SAYAP TAKJIL
B28: E | C28: 3 | D28: ='WEEKLY FC'!B35 -> FRENCH FRIES | E28: 114400 | F28: 4.4 | G28: 130000 | H28: 5 | AI28: =SUM(I28,K28,M28,O28,Q28,S28,U28,W28,Y28,AA28,AC28,AE28,AG28) -> 0 | AJ28: =SUM(J28,L28,N28,P28,R28,T28,V28,X28,Z28,AB28,AD28,AF28,AH28) -> 0 | AK28: ='WEEKLY FC'!F35 -> 59800 | AL28: ='WEEKLY FC'!D35 -> 2.3 | AM28: =G28+AI28-AK28 -> 70200 | AN28: =H28+AJ28-AL28 -> 2.7 | AP28: AYAM UTUH | AQ28: 1020000 | AR28: 30
B29: L | C29: 4 | D29: ='WEEKLY FC'!B36 -> ROTI BURGER | E29: 278554.33 | F29: 53 | G29: 372106.67 | H29: 128 | AI29: =SUM(I29,K29,M29,O29,Q29,S29,U29,W29,Y29,AA29,AC29,AE29,AG29) -> 0 | AJ29: =SUM(J29,L29,N29,P29,R29,T29,V29,X29,Z29,AB29,AD29,AF29,AH29) -> 0 | AK29: ='WEEKLY FC'!F36 -> 200588.75 | AL29: ='WEEKLY FC'!D36 -> 69 | AM29: =G29+AI29-AK29 -> 171517.92 | AN29: =H29+AJ29-AL29 -> 59
B30: E | C30: 5 | D30: ='WEEKLY FC'!B37 -> SOSIS | E30: 0 | F30: 0 | G30: 0 | H30: 0 | AI30: =SUM(I30,K30,M30,O30,Q30,S30,U30,W30,Y30,AA30,AC30,AE30,AG30) -> 0 | AJ30: =SUM(J30,L30,N30,P30,R30,T30,V30,X30,Z30,AB30,AD30,AF30,AH30) -> 0 | AK30: ='WEEKLY FC'!F37 -> 0 | AL30: ='WEEKLY FC'!D37 -> 0 | AM30: =G30+AI30-AK30 -> 0 | AN30: =H30+AJ30-AL30 -> 0
B31: N | C31: 6 | D31: ='WEEKLY FC'!B38 -> PERKEDEL | E31: 139681.93 | F31: 95 | G31: 10140.264 | H31: 7 | AC31: ='TO - TI'!D20 -> 237571.91 | AD31: ='TO - TI'!B22-4 -> 140 | AI31: =SUM(I31,K31,M31,O31,Q31,S31,U31,W31,Y31,AA31,AC31,AE31,AG31) -> 237571.91 | AJ31: =SUM(J31,L31,N31,P31,R31,T31,V31,X31,Z31,AB31,AD31,AF31,AH31) -> 140 | AK31: ='WEEKLY FC'!F38 -> 118785.95 | AL31: ='WEEKLY FC'!D38 -> 72 | AM31: =G31+AI31-AK31 -> 128926.22 | AN31: =H31+AJ31-AL31 -> 75
B32: G | C32: 7 | D32: ='WEEKLY FC'!B39 -> CRINKLE | E32: 92800 | F32: 2.9 | G32: 60800 | H32: 1.9 | AI32: =SUM(I32,K32,M32,O32,Q32,S32,U32,W32,Y32,AA32,AC32,AE32,AG32) -> 0 | AJ32: =SUM(J32,L32,N32,P32,R32,T32,V32,X32,Z32,AB32,AD32,AF32,AH32) -> 0 | AK32: ='WEEKLY FC'!F39 -> 22400 | AL32: ='WEEKLY FC'!D39 -> 0.7 | AM32: =G32+AI32-AK32 -> 38400 | AN32: =H32+AJ32-AL32 -> 1.2
B33: K | C33: 8 | D33: ='WEEKLY FC'!B40 -> NUGGET COIN | E33: 0 | F33: 0 | G33: 0 | H33: 0 | AI33: =SUM(I33,K33,M33,O33,Q33,S33,U33,W33,Y33,AA33,AC33,AE33,AG33) -> 0 | AJ33: =SUM(J33,L33,N33,P33,R33,T33,V33,X33,Z33,AB33,AD33,AF33,AH33) -> 0 | AK33: ='WEEKLY FC'!F40 -> 0 | AL33: ='WEEKLY FC'!D40 -> 0 | AM33: =G33+AI33-AK33 -> 0 | AN33: =H33+AJ33-AL33 -> 0
B34: A | C34: 9 | D34: ='WEEKLY FC'!B41 -> NUGGET STICK | E34: 0 | F34: 0 | G34: 0 | H34: 0 | AI34: =SUM(I34,K34,M34,O34,Q34,S34,U34,W34,Y34,AA34,AC34,AE34,AG34) -> 0 | AJ34: =SUM(J34,L34,N34,P34,R34,T34,V34,X34,Z34,AB34,AD34,AF34,AH34) -> 0 | AK34: ='WEEKLY FC'!F41 -> 0 | AL34: ='WEEKLY FC'!D41 -> 0 | AM34: =G34+AI34-AK34 -> 0 | AN34: =H34+AJ34-AL34 -> 0
B35: P | C35: 10 | D35: ='WEEKLY FC'!B42 -> SOSIS MINI JUMBO | E35: 0 | F35: 0 | G35: 0 | H35: 0 | AI35: =SUM(I35,K35,M35,O35,Q35,S35,U35,W35,Y35,AA35,AC35,AE35,AG35) -> 0 | AJ35: =SUM(J35,L35,N35,P35,R35,T35,V35,X35,Z35,AB35,AD35,AF35,AH35) -> 0 | AK35: ='WEEKLY FC'!F42 -> 0 | AL35: ='WEEKLY FC'!D42 -> 0 | AM35: =G35+AI35-AK35 -> 0 | AN35: =H35+AJ35-AL35 -> 0
C36: 11 | D36: ='WEEKLY FC'!B43 -> INDOMIE GORENG | E36: 0 | F36: 0 | G36: 0 | H36: 0 | AI36: =SUM(I36,K36,M36,O36,Q36,S36,U36,W36,Y36,AA36,AC36,AE36,AG36) -> 0 | AJ36: =SUM(J36,L36,N36,P36,R36,T36,V36,X36,Z36,AB36,AD36,AF36,AH36) -> 0 | AK36: ='WEEKLY FC'!F43 -> 0 | AL36: ='WEEKLY FC'!D43 -> 0 | AM36: =G36+AI36-AK36 -> 0 | AN36: =H36+AJ36-AL36 -> 0
C37: 12 | D37: ='WEEKLY FC'!B44 -> KERUPUK UDANG | E37: 0 | F37: 0 | G37: 0 | H37: 0 | AI37: =SUM(I37,K37,M37,O37,Q37,S37,U37,W37,Y37,AA37,AC37,AE37,AG37) -> 0 | AJ37: =SUM(J37,L37,N37,P37,R37,T37,V37,X37,Z37,AB37,AD37,AF37,AH37) -> 0 | AK37: ='WEEKLY FC'!F44 -> 0 | AL37: ='WEEKLY FC'!D44 -> 0 | AM37: =G37+AI37-AK37 -> 0 | AN37: =H37+AJ37-AL37 -> 0
C38: 13 | D38: ='WEEKLY FC'!B45 -> BUN BURGER BEEF | E38: 0 | F38: 0 | G38: 0 | H38: 0 | AI38: =SUM(I38,K38,M38,O38,Q38,S38,U38,W38,Y38,AA38,AC38,AE38,AG38) -> 0 | AJ38: =SUM(J38,L38,N38,P38,R38,T38,V38,X38,Z38,AB38,AD38,AF38,AH38) -> 0 | AK38: ='WEEKLY FC'!F45 -> 0 | AL38: ='WEEKLY FC'!D45 -> 0 | AM38: =G38+AI38-AK38 -> 0 | AN38: =H38+AJ38-AL38 -> 0
C39: 14 | D39: ='WEEKLY FC'!B46 -> CHEESE UNTUK BEEF | E39: 0 | F39: 0 | G39: 0 | H39: 0 | AI39: =SUM(I39,K39,M39,O39,Q39,S39,U39,W39,Y39,AA39,AC39,AE39,AG39) -> 0 | AJ39: =SUM(J39,L39,N39,P39,R39,T39,V39,X39,Z39,AB39,AD39,AF39,AH39) -> 0 | AK39: ='WEEKLY FC'!F46 -> 0 | AL39: ='WEEKLY FC'!D46 -> 0 | AM39: =G39+AI39-AK39 -> 0 | AN39: =H39+AJ39-AL39 -> 0
C40: 15 | D40: ='WEEKLY FC'!B47 -> 0 | E40: 0 | F40: 0 | G40: 0 | H40: 0 | AI40: =SUM(I40,K40,M40,O40,Q40,S40,U40,W40,Y40,AA40,AC40,AE40,AG40) -> 0 | AJ40: =SUM(J40,L40,N40,P40,R40,T40,V40,X40,Z40,AB40,AD40,AF40,AH40) -> 0 | AK40: ='WEEKLY FC'!F47 -> 0 | AL40: ='WEEKLY FC'!D47 -> 0 | AM40: =G40+AI40-AK40 -> 0 | AN40: =H40+AJ40-AL40 -> 0
C41: 16 | D41: ='WEEKLY FC'!B48 -> 0 | E41: 0 | F41: 0 | G41: 0 | H41: 0 | AI41: =SUM(I41,K41,M41,O41,Q41,S41,U41,W41,Y41,AA41,AC41,AE41,AG41) -> 0 | AJ41: =SUM(J41,L41,N41,P41,R41,T41,V41,X41,Z41,AB41,AD41,AF41,AH41) -> 0 | AK41: ='WEEKLY FC'!F48 -> 0 | AL41: ='WEEKLY FC'!D48 -> 0 | AM41: =G41+AI41-AK41 -> 0 | AN41: =H41+AJ41-AL41 -> 0
C42: 17 | D42: ='WEEKLY FC'!B49 -> 0 | E42: 0 | F42: 0 | G42: 0 | H42: 0 | AI42: =SUM(I42,K42,M42,O42,Q42,S42,U42,W42,Y42,AA42,AC42,AE42,AG42) -> 0 | AJ42: =SUM(J42,L42,N42,P42,R42,T42,V42,X42,Z42,AB42,AD42,AF42,AH42) -> 0 | AK42: ='WEEKLY FC'!F49 -> 0 | AL42: ='WEEKLY FC'!D49 -> 0 | AM42: =G42+AI42-AK42 -> 0 | AN42: =H42+AJ42-AL42 -> 0
C43: 18 | D43: ='WEEKLY FC'!B50 -> 0 | E43: 0 | F43: 0 | G43: 0 | H43: 0 | AI43: =SUM(I43,K43,M43,O43,Q43,S43,U43,W43,Y43,AA43,AC43,AE43,AG43) -> 0 | AJ43: =SUM(J43,L43,N43,P43,R43,T43,V43,X43,Z43,AB43,AD43,AF43,AH43) -> 0 | AK43: ='WEEKLY FC'!F50 -> 0 | AL43: ='WEEKLY FC'!D50 -> 0 | AM43: =G43+AI43-AK43 -> 0 | AN43: =H43+AJ43-AL43 -> 0
C44: 19 | D44: BAHAN ROTI | E44: 108888.75 | F44: 0 | G44: 76494.722 | I44: 5000 | K44: 64900 | O44: 38300 | Q44: 11000 | S44: 42380 | U44: 5000 | AC44: =-'TO - TI'!S10-'TO - TI'!S11-'TO - TI'!S12-'TO - TI'!S13 -> -17435.5 | AI44: =SUM(I44,K44,M44,O44,Q44,S44,U44,W44,Y44,AA44,AC44,AE44,AG44) -> 149144.5 | AJ44: =SUM(J44,L44,N44,P44,R44,T44,V44,X44,Z44,AB44,AD44,AF44,AH44) -> 0 | AK44: ='WEEKLY FC'!I69 -> 122923.47 | AM44: =G44+AI44-AK44 -> 102715.75 | AN44: =H44+AJ44-AL44 -> 0 | AO44: =SUM(AK26:AK44) -> 1691498.2
C45: 20 | E45: 0 | F45: 0 | AI45: =SUM(I45,K45,M45,O45,Q45,S45,U45,W45,Y45,AA45,AC45,AE45,AG45) -> 0 | AJ45: =SUM(J45,L45,N45,P45,R45,T45,V45,X45,Z45,AB45,AD45,AF45,AH45) -> 0 | AM45: =G45+AI45-AK45 -> 0 | AN45: =H45+AJ45-AL45 -> 0
B46: BAHAN ES | C46: 1 | D46: ='WEEKLY FC'!B72 -> GULA PASIR | E46: 130500 | F46: 7.5 | G46: 79200 | H46: 4.5 | O46: 88000 | P46: 5 | AI46: =SUM(I46,K46,M46,O46,Q46,S46,U46,W46,Y46,AA46,AC46,AE46,AG46) -> 88000 | AJ46: =SUM(J46,L46,N46,P46,R46,T46,V46,X46,Z46,AB46,AD46,AF46,AH46) -> 5 | AK46: ='WEEKLY FC'!F72 -> 52800 | AL46: ='WEEKLY FC'!D72 -> 3 | AM46: =G46+AI46-AK46 -> 114400 | AN46: =H46+AJ46-AL46 -> 6.5
C47: 2 | D47: ICE CREAM | E47: 0 | F47: 0 | G47: 0 | H47: 0 | AI47: =SUM(I47,K47,M47,O47,Q47,S47,U47,W47,Y47,AA47,AC47,AE47,AG47) -> 0 | AJ47: =SUM(J47,L47,N47,P47,R47,T47,V47,X47,Z47,AB47,AD47,AF47,AH47) -> 0 | AK47: ='WEEKLY FC'!F73 -> 0 | AL47: ='WEEKLY FC'!D73 -> 0 | AM47: =G47+AI47-AK47 -> 0 | AN47: =H47+AJ47-AL47 -> 0
C48: 3 | D48: ICE CREAM EMBER | E48: 0 | F48: 0 | G48: 0 | H48: 0 | AI48: =SUM(I48,K48,M48,O48,Q48,S48,U48,W48,Y48,AA48,AC48,AE48,AG48) -> 0 | AJ48: =SUM(J48,L48,N48,P48,R48,T48,V48,X48,Z48,AB48,AD48,AF48,AH48) -> 0 | AK48: ='WEEKLY FC'!F74 -> 0 | AL48: ='WEEKLY FC'!D74 -> 0 | AM48: =G48+AI48-AK48 -> 0 | AN48: =H48+AJ48-AL48 -> 0
C49: 4 | D49: BAHAN ES | E49: 200210.53 | F49: 0 | G49: 75100 | I49: 16000 | K49: 16000 | M49: 91000 | Q49: 16000 | S49: 42100 | U49: 16000 | AC49: =-'TO - TI'!D9 -> -1578.9474 | AI49: =SUM(I49,K49,M49,O49,Q49,S49,U49,W49,Y49,AA49,AC49,AE49,AG49) -> 195521.05 | AJ49: =SUM(J49,L49,N49,P49,R49,T49,V49,X49,Z49,AB49,AD49,AF49,AH49) -> 0 | AK49: ='WEEKLY FC'!I87 -> 51150 | AM49: =G49+AI49-AK49 -> 219471.05 | AN49: =H49+AJ49-AL49 -> 0
C50: 5
C51: 1 | D51: ='WEEKLY FC'!B94 -> TEH BOTOL SOSRO (TBS) | E51: 13002 | F51: 6 | G51: 34672 | H51: 16 | AG51: ='PEMBELIAN KREDIT'!G24 -> 104000 | AH51: ='PEMBELIAN KREDIT'!E24 -> 48 | AI51: =SUM(I51,K51,M51,O51,Q51,S51,U51,W51,Y51,AA51,AC51,AE51,AG51) -> 104000 | AJ51: =SUM(J51,L51,N51,P51,R51,T51,V51,X51,Z51,AB51,AD51,AF51,AH51) -> 48 | AK51: ='WEEKLY FC'!F94 -> 121352 | AL51: ='WEEKLY FC'!D94 -> 56 | AM51: =G51+AI51-AK51 -> 17320 | AN51: =H51+AJ51-AL51 -> 8
C52: 2 | D52: ='WEEKLY FC'!B95 -> TEH SOSRO POUCH (TBO) | E52: 13626 | F52: 6 | G52: 0 | H52: 0 | AG52: ='PEMBELIAN KREDIT'!G25 -> 120000 | AH52: ='PEMBELIAN KREDIT'!E25 -> 48 | AI52: =SUM(I52,K52,M52,O52,Q52,S52,U52,W52,Y52,AA52,AC52,AE52,AG52) -> 120000 | AJ52: =SUM(J52,L52,N52,P52,R52,T52,V52,X52,Z52,AB52,AD52,AF52,AH52) -> 48 | AK52: ='WEEKLY FC'!F95 -> 109008 | AL52: ='WEEKLY FC'!D95 -> 48 | AM52: =G52+AI52-AK52 -> 10992 | AN52: =H52+AJ52-AL52 -> 0
C53: 3 | D53: ='WEEKLY FC'!B96 -> FRUIT TEA BOTOL | E53: 10500 | F53: 3 | G53: 10500 | H53: 3 | AG53: ='PEMBELIAN KREDIT'!G38 -> 42000 | AH53: ='PEMBELIAN KREDIT'!E38 -> 12 | AI53: =SUM(I53,K53,M53,O53,Q53,S53,U53,W53,Y53,AA53,AC53,AE53,AG53) -> 42000 | AJ53: =SUM(J53,L53,N53,P53,R53,T53,V53,X53,Z53,AB53,AD53,AF53,AH53) -> 12 | AK53: ='WEEKLY FC'!F96 -> 45500 | AL53: ='WEEKLY FC'!D96 -> 13 | AM53: =G53+AI53-AK53 -> 7000 | AN53: =H53+AJ53-AL53 -> 2
C54: 4 | D54: ='WEEKLY FC'!B97 -> FRUIT TEA POUCH (FTG) | E54: 0 | F54: 0 | G54: 0 | H54: 0 | AI54: =SUM(I54,K54,M54,O54,Q54,S54,U54,W54,Y54,AA54,AC54,AE54,AG54) -> 0 | AJ54: =SUM(J54,L54,N54,P54,R54,T54,V54,X54,Z54,AB54,AD54,AF54,AH54) -> 0 | AK54: ='WEEKLY FC'!F97 -> 0 | AL54: ='WEEKLY FC'!D97 -> 0 | AM54: =G54+AI54-AK54 -> 0 | AN54: =H54+AJ54-AL54 -> 0
C55: 5 | D55: ='WEEKLY FC'!B98 -> TEBS | E55: 7000 | F55: 2 | G55: 7000 | H55: 2 | AG55: ='PEMBELIAN KREDIT'!G39 -> 42000 | AH55: ='PEMBELIAN KREDIT'!E39 -> 12 | AI55: =SUM(I55,K55,M55,O55,Q55,S55,U55,W55,Y55,AA55,AC55,AE55,AG55) -> 42000 | AJ55: =SUM(J55,L55,N55,P55,R55,T55,V55,X55,Z55,AB55,AD55,AF55,AH55) -> 12 | AK55: ='WEEKLY FC'!F98 -> 49000 | AL55: ='WEEKLY FC'!D98 -> 14 | AM55: =G55+AI55-AK55 -> 0 | AN55: =H55+AJ55-AL55 -> 0
C56: 6 | D56: ='WEEKLY FC'!B99 -> AIR MINERAL BOTOL (AMB) | E56: 89964 | F56: 54 | G56: 363188 | H56: 218 | AC56: =-26627 -> -26627 | AD56: =-16 -> -16 | AG56: ='PEMBELIAN KREDIT'!G22 -> 200000 | AH56: ='PEMBELIAN KREDIT'!E22 -> 120 | AI56: =SUM(I56,K56,M56,O56,Q56,S56,U56,W56,Y56,AA56,AC56,AE56,AG56) -> 173373 | AJ56: =SUM(J56,L56,N56,P56,R56,T56,V56,X56,Z56,AB56,AD56,AF56,AH56) -> 104 | AK56: ='WEEKLY FC'!F99 -> 458425 | AL56: ='WEEKLY FC'!D99 -> 275 | AM56: =G56+AI56-AK56 -> 78136 | AN56: =H56+AJ56-AL56 -> 47
C57: 7 | D57: ='WEEKLY FC'!B100 -> AIR MINERAL CUP (AMC) | E57: 0 | F57: 0 | G57: 21068 | H57: 46 | AI57: =SUM(I57,K57,M57,O57,Q57,S57,U57,W57,Y57,AA57,AC57,AE57,AG57) -> 0 | AJ57: =SUM(J57,L57,N57,P57,R57,T57,V57,X57,Z57,AB57,AD57,AF57,AH57) -> 0 | AK57: ='WEEKLY FC'!F100 -> 21068 | AL57: ='WEEKLY FC'!D100 -> 46 | AM57: =G57+AI57-AK57 -> 0 | AN57: =H57+AJ57-AL57 -> 0
C58: 8 | D58: ='WEEKLY FC'!B101 -> MILO | E58: 70902 | F58: 0.96 | G58: 478479.5 | H58: 4.91 | AI58: =SUM(I58,K58,M58,O58,Q58,S58,U58,W58,Y58,AA58,AC58,AE58,AG58) -> 0 | AJ58: =SUM(J58,L58,N58,P58,R58,T58,V58,X58,Z58,AB58,AD58,AF58,AH58) -> 0 | AK58: ='WEEKLY FC'!F101 -> 359590.5 | AL58: ='WEEKLY FC'!D101 -> 3.69 | AM58: =G58+AI58-AK58 -> 118889 | AN58: =H58+AJ58-AL58 -> 1.22
B59: M | C59: 9 | D59: ='WEEKLY FC'!B102 -> NESTEA | E59: 147884.7 | F59: 2.71 | G59: 315960.3 | H59: 5.79 | AI59: =SUM(I59,K59,M59,O59,Q59,S59,U59,W59,Y59,AA59,AC59,AE59,AG59) -> 0 | AJ59: =SUM(J59,L59,N59,P59,R59,T59,V59,X59,Z59,AB59,AD59,AF59,AH59) -> 0 | AK59: ='WEEKLY FC'!F102 -> 174624 | AL59: ='WEEKLY FC'!D102 -> 3.2 | AM59: =G59+AI59-AK59 -> 141336.3 | AN59: =H59+AJ59-AL59 -> 2.59
B60: I | C60: 10 | D60: ='WEEKLY FC'!B103 -> ORANGE | E60: 0 | F60: 0 | G60: 0 | H60: 0 | AI60: =SUM(I60,K60,M60,O60,Q60,S60,U60,W60,Y60,AA60,AC60,AE60,AG60) -> 0 | AJ60: =SUM(J60,L60,N60,P60,R60,T60,V60,X60,Z60,AB60,AD60,AF60,AH60) -> 0 | AK60: ='WEEKLY FC'!F103 -> 0 | AL60: ='WEEKLY FC'!D103 -> 0 | AM60: =G60+AI60-AK60 -> 0 | AN60: =H60+AJ60-AL60 -> 0
B61: N | C61: 11 | D61: ='WEEKLY FC'!B104 -> BUAH FROZEN JAMBU | E61: 0 | F61: 0 | G61: 0 | H61: 0 | AI61: =SUM(I61,K61,M61,O61,Q61,S61,U61,W61,Y61,AA61,AC61,AE61,AG61) -> 0 | AJ61: =SUM(J61,L61,N61,P61,R61,T61,V61,X61,Z61,AB61,AD61,AF61,AH61) -> 0 | AK61: ='WEEKLY FC'!F104 -> 0 | AL61: ='WEEKLY FC'!D104 -> 0 | AM61: =G61+AI61-AK61 -> 0 | AN61: =H61+AJ61-AL61 -> 0
B62: U | C62: 12 | D62: ='WEEKLY FC'!B105 -> BUAH FROZEN MELON | E62: 0 | F62: 0 | G62: 0 | H62: 0 | AI62: =SUM(I62,K62,M62,O62,Q62,S62,U62,W62,Y62,AA62,AC62,AE62,AG62) -> 0 | AJ62: =SUM(J62,L62,N62,P62,R62,T62,V62,X62,Z62,AB62,AD62,AF62,AH62) -> 0 | AK62: ='WEEKLY FC'!F105 -> 0 | AL62: ='WEEKLY FC'!D105 -> 0 | AM62: =G62+AI62-AK62 -> 0 | AN62: =H62+AJ62-AL62 -> 0
B63: M | C63: 13 | D63: ='WEEKLY FC'!B106 -> BUAH FROZEN STRAWBERRY | E63: 0 | F63: 0 | G63: 0 | H63: 0 | AI63: =SUM(I63,K63,M63,O63,Q63,S63,U63,W63,Y63,AA63,AC63,AE63,AG63) -> 0 | AJ63: =SUM(J63,L63,N63,P63,R63,T63,V63,X63,Z63,AB63,AD63,AF63,AH63) -> 0 | AK63: ='WEEKLY FC'!F106 -> 0 | AL63: ='WEEKLY FC'!D106 -> 0 | AM63: =G63+AI63-AK63 -> 0 | AN63: =H63+AJ63-AL63 -> 0
B64: A | C64: 14 | D64: ='WEEKLY FC'!B107 -> BUAH FROZEN SIRSAK | E64: 0 | F64: 0 | G64: 0 | H64: 0 | AI64: =SUM(I64,K64,M64,O64,Q64,S64,U64,W64,Y64,AA64,AC64,AE64,AG64) -> 0 | AJ64: =SUM(J64,L64,N64,P64,R64,T64,V64,X64,Z64,AB64,AD64,AF64,AH64) -> 0 | AK64: ='WEEKLY FC'!F107 -> 0 | AL64: ='WEEKLY FC'!D107 -> 0 | AM64: =G64+AI64-AK64 -> 0 | AN64: =H64+AJ64-AL64 -> 0
B65: N | C65: 15 | D65: ='WEEKLY FC'!B108 -> BUAH FROZEN MANGGA | E65: 0 | F65: 0 | G65: 0 | H65: 0 | AI65: =SUM(I65,K65,M65,O65,Q65,S65,U65,W65,Y65,AA65,AC65,AE65,AG65) -> 0 | AJ65: =SUM(J65,L65,N65,P65,R65,T65,V65,X65,Z65,AB65,AD65,AF65,AH65) -> 0 | AK65: ='WEEKLY FC'!F108 -> 0 | AL65: ='WEEKLY FC'!D108 -> 0 | AM65: =G65+AI65-AK65 -> 0 | AN65: =H65+AJ65-AL65 -> 0
C66: 16 | D66: ='WEEKLY FC'!B109 -> BUAH FROZEN DURIAN | E66: 0 | F66: 0 | G66: 0 | H66: 0 | AI66: =SUM(I66,K66,M66,O66,Q66,S66,U66,W66,Y66,AA66,AC66,AE66,AG66) -> 0 | AJ66: =SUM(J66,L66,N66,P66,R66,T66,V66,X66,Z66,AB66,AD66,AF66,AH66) -> 0 | AK66: ='WEEKLY FC'!F109 -> 0 | AL66: ='WEEKLY FC'!D109 -> 0 | AM66: =G66+AI66-AK66 -> 0 | AN66: =H66+AJ66-AL66 -> 0
C67: 17 | D67: ='WEEKLY FC'!B110 -> TEH POCI KUNING / VANILA | E67: -10248.037 | F67: 11.5 | G67: 205422 | H67: 73 | AC67: =-'TO - TI'!I25-'TO - TI'!N12 -> -21304.518 | AI67: =SUM(I67,K67,M67,O67,Q67,S67,U67,W67,Y67,AA67,AC67,AE67,AG67) -> -21304.518 | AJ67: =SUM(J67,L67,N67,P67,R67,T67,V67,X67,Z67,AB67,AD67,AF67,AH67) -> 0 | AK67: ='WEEKLY FC'!F110 -> 180096 | AL67: ='WEEKLY FC'!D110 -> 64 | AM67: =G67+AI67-AK67 -> 4021.4815 | AN67: =H67+AJ67-AL67 -> 9
C68: 18 | D68: ='WEEKLY FC'!B111 -> MILK SHAKE COKLAT | E68: 0 | F68: 0 | G68: 64110 | H68: 15 | AI68: =SUM(I68,K68,M68,O68,Q68,S68,U68,W68,Y68,AA68,AC68,AE68,AG68) -> 0 | AJ68: =SUM(J68,L68,N68,P68,R68,T68,V68,X68,Z68,AB68,AD68,AF68,AH68) -> 0 | AK68: ='WEEKLY FC'!F111 -> 59836 | AL68: ='WEEKLY FC'!D111 -> 14 | AM68: =G68+AI68-AK68 -> 4274 | AN68: =H68+AJ68-AL68 -> 1
C69: 19 | D69: ='WEEKLY FC'!B112 -> MILK SHAKE CAPPUCINO | E69: 0 | F69: 0 | G69: 0 | H69: 0 | AI69: =SUM(I69,K69,M69,O69,Q69,S69,U69,W69,Y69,AA69,AC69,AE69,AG69) -> 0 | AJ69: =SUM(J69,L69,N69,P69,R69,T69,V69,X69,Z69,AB69,AD69,AF69,AH69) -> 0 | AK69: ='WEEKLY FC'!F112 -> 0 | AL69: ='WEEKLY FC'!D112 -> 0 | AM69: =G69+AI69-AK69 -> 0 | AN69: =H69+AJ69-AL69 -> 0
C70: 20 | D70: ='WEEKLY FC'!B113 -> MILK SHAKE MANGGA | E70: 0 | F70: 0 | G70: 0 | H70: 0 | AI70: =SUM(I70,K70,M70,O70,Q70,S70,U70,W70,Y70,AA70,AC70,AE70,AG70) -> 0 | AJ70: =SUM(J70,L70,N70,P70,R70,T70,V70,X70,Z70,AB70,AD70,AF70,AH70) -> 0 | AK70: ='WEEKLY FC'!F113 -> 0 | AL70: ='WEEKLY FC'!D113 -> 0 | AM70: =G70+AI70-AK70 -> 0 | AN70: =H70+AJ70-AL70 -> 0
C71: 21 | D71: ='WEEKLY FC'!B114 -> MILK SHAKE STRAWBERRY | E71: 0 | F71: 0 | G71: 0 | H71: 0 | AI71: =SUM(I71,K71,M71,O71,Q71,S71,U71,W71,Y71,AA71,AC71,AE71,AG71) -> 0 | AJ71: =SUM(J71,L71,N71,P71,R71,T71,V71,X71,Z71,AB71,AD71,AF71,AH71) -> 0 | AK71: ='WEEKLY FC'!F114 -> 0 | AL71: ='WEEKLY FC'!D114 -> 0 | AM71: =G71+AI71-AK71 -> 0 | AN71: =H71+AJ71-AL71 -> 0
C72: 22 | D72: ='WEEKLY FC'!B115 -> STEE | E72: 475191 | F72: 300 | G72: 177404.64 | H72: 112 | AC72: =-'TO - TI'!N13 -> 0 | AD72: =-'TO - TI'!L13 -> 0 | AG72: ='PEMBELIAN KREDIT'!G23 -> 380153 | AH72: ='PEMBELIAN KREDIT'!E23 -> 240 | AI72: =SUM(I72,K72,M72,O72,Q72,S72,U72,W72,Y72,AA72,AC72,AE72,AG72) -> 380153 | AJ72: =SUM(J72,L72,N72,P72,R72,T72,V72,X72,Z72,AB72,AD72,AF72,AH72) -> 240 | AK72: ='WEEKLY FC'!F115 -> 251851.23 | AL72: ='WEEKLY FC'!D115 -> 159 | AM72: =G72+AI72-AK72 -> 305706.41 | AN72: =H72+AJ72-AL72 -> 193
C73: 23 | D73: ='WEEKLY FC'!B116 -> THAI GREEN TEA | E73: 9706.95 | F73: 3 | G73: 3235.65 | H73: 1 | AI73: =SUM(I73,K73,M73,O73,Q73,S73,U73,W73,Y73,AA73,AC73,AE73,AG73) -> 0 | AJ73: =SUM(J73,L73,N73,P73,R73,T73,V73,X73,Z73,AB73,AD73,AF73,AH73) -> 0 | AK73: ='WEEKLY FC'!F116 -> 0 | AL73: ='WEEKLY FC'!D116 -> 0 | AM73: =G73+AI73-AK73 -> 3235.65 | AN73: =H73+AJ73-AL73 -> 1
C74: 24 | D74: ='WEEKLY FC'!B117 -> RED VALVET | E74: 0 | F74: 0 | G74: 40293 | H74: 11 | AI74: =SUM(I74,K74,M74,O74,Q74,S74,U74,W74,Y74,AA74,AC74,AE74,AG74) -> 0 | AJ74: =SUM(J74,L74,N74,P74,R74,T74,V74,X74,Z74,AB74,AD74,AF74,AH74) -> 0 | AK74: ='WEEKLY FC'!F117 -> 32967 | AL74: ='WEEKLY FC'!D117 -> 9 | AM74: =G74+AI74-AK74 -> 7326 | AN74: =H74+AJ74-AL74 -> 2
C75: 25 | D75: ='WEEKLY FC'!B118 -> MILKY MANGGO | E75: 8424.9 | F75: 3 | G75: 28083 | H75: 10 | AI75: =SUM(I75,K75,M75,O75,Q75,S75,U75,W75,Y75,AA75,AC75,AE75,AG75) -> 0 | AJ75: =SUM(J75,L75,N75,P75,R75,T75,V75,X75,Z75,AB75,AD75,AF75,AH75) -> 0 | AK75: ='WEEKLY FC'!F118 -> 28083 | AL75: ='WEEKLY FC'!D118 -> 10 | AM75: =G75+AI75-AK75 -> 0 | AN75: =H75+AJ75-AL75 -> 0
C76: 26 | D76: ='WEEKLY FC'!B119 -> AIR MINERAL BOTOL (AMB) 330 ML | E76: 0 | F76: 0 | G76: 0 | H76: 0 | AI76: =SUM(I76,K76,M76,O76,Q76,S76,U76,W76,Y76,AA76,AC76,AE76,AG76) -> 0 | AJ76: =SUM(J76,L76,N76,P76,R76,T76,V76,X76,Z76,AB76,AD76,AF76,AH76) -> 0 | AK76: ='WEEKLY FC'!F119 -> 0 | AL76: ='WEEKLY FC'!D119 -> 0 | AM76: =G76+AI76-AK76 -> 0 | AN76: =H76+AJ76-AL76 -> 0
C77: 27 | D77: ='WEEKLY FC'!B120 -> TEH RC | E77: 0 | F77: 0 | G77: 0 | H77: 0 | AI77: =SUM(I77,K77,M77,O77,Q77,S77,U77,W77,Y77,AA77,AC77,AE77,AG77) -> 0 | AJ77: =SUM(J77,L77,N77,P77,R77,T77,V77,X77,Z77,AB77,AD77,AF77,AH77) -> 0 | AK77: ='WEEKLY FC'!F120 -> 0 | AL77: ='WEEKLY FC'!D120 -> 0 | AM77: =G77+AI77-AK77 -> 0 | AN77: =H77+AJ77-AL77 -> 0
C78: 28 | D78: ='WEEKLY FC'!B121 -> TEH BOTOL 1 LITER | E78: 0 | F78: 0 | G78: 0 | H78: 0 | AG78: ='PEMBELIAN KREDIT'!G26 -> 283500 | AH78: ='PEMBELIAN KREDIT'!E26 -> 36 | AI78: =SUM(I78,K78,M78,O78,Q78,S78,U78,W78,Y78,AA78,AC78,AE78,AG78) -> 283500 | AJ78: =SUM(J78,L78,N78,P78,R78,T78,V78,X78,Z78,AB78,AD78,AF78,AH78) -> 36 | AK78: ='WEEKLY FC'!F121 -> 283500 | AL78: ='WEEKLY FC'!D121 -> 36 | AM78: =G78+AI78-AK78 -> 0 | AN78: =H78+AJ78-AL78 -> 0
C79: 29 | D79: ='WEEKLY FC'!B122 -> 0 | E79: 0 | F79: 0 | G79: 0 | H79: 0 | AI79: =SUM(I79,K79,M79,O79,Q79,S79,U79,W79,Y79,AA79,AC79,AE79,AG79) -> 0 | AJ79: =SUM(J79,L79,N79,P79,R79,T79,V79,X79,Z79,AB79,AD79,AF79,AH79) -> 0 | AK79: ='WEEKLY FC'!F122 -> 0 | AL79: ='WEEKLY FC'!D122 -> 0 | AM79: =G79+AI79-AK79 -> 0 | AN79: =H79+AJ79-AL79 -> 0
C80: 30 | D80: ='WEEKLY FC'!B123 -> 0 | E80: 0 | F80: 0 | G80: 0 | H80: 0 | AI80: =SUM(I80,K80,M80,O80,Q80,S80,U80,W80,Y80,AA80,AC80,AE80,AG80) -> 0 | AJ80: =SUM(J80,L80,N80,P80,R80,T80,V80,X80,Z80,AB80,AD80,AF80,AH80) -> 0 | AK80: ='WEEKLY FC'!F123 -> 0 | AL80: ='WEEKLY FC'!D123 -> 0 | AM80: =G80+AI80-AK80 -> 0 | AN80: =H80+AJ80-AL80 -> 0
C81: 31 | D81: ='WEEKLY FC'!B124 -> 0 | E81: 0 | F81: 0 | G81: 0 | H81: 0 | AI81: =SUM(I81,K81,M81,O81,Q81,S81,U81,W81,Y81,AA81,AC81,AE81,AG81) -> 0 | AJ81: =SUM(J81,L81,N81,P81,R81,T81,V81,X81,Z81,AB81,AD81,AF81,AH81) -> 0 | AK81: ='WEEKLY FC'!F124 -> 0 | AL81: ='WEEKLY FC'!D124 -> 0 | AM81: =G81+AI81-AK81 -> 0 | AN81: =H81+AJ81-AL81 -> 0
D82: TOTAL LEMBAR 1 | E82: =SUM(E10:E81) -> 14241567 | G82: =SUM(G10:G81) -> 10088305 | I82: =SUM(I10:I81) -> 21000 | K82: =SUM(K10:K81) -> 80900 | M82: =SUM(M10:M81) -> 91000 | O82: =SUM(O10:O81) -> 126300 | Q82: =SUM(Q10:Q81) -> 27000 | S82: =SUM(S10:S81) -> 84480 | U82: =SUM(U10:U81) -> 21000 | W82: =SUM(W10:W81) -> 0 | Y82: =SUM(Y10:Y81) -> 0 | AA82: =SUM(AA10:AA81) -> 0 | AC82: =SUM(AC10:AC81) -> 27655.984 | AE82: =SUM(AE10:AE81) -> 0 | AG82: =SUM(AG10:AG81) -> 9812503 | AI82: =SUM(I82,K82,M82,O82,Q82,S82,U82,W82,Y82,AA82,AC82,AE82,AG82) -> 10291839 | AK82: =SUM(AK10:AK81) -> 10366577 | AM82: =SUM(AM10:AM81) -> 10013567
B84: NB : PEMBELIAN AYAM CASH DIMASUKKAN MANUAL DAN PEMBELIAN AYAM KREDIT WAJIB DIISI DI KOLOM PEMBELIAN KREDIT KHUSUS AYAM DAN MARINADE
B85: NB : KREDIT BARANG GUDANG, PEMAKAIAN MINGGU LALU ATAU PERSEDIAAN AWAL SERTA KOLOM TO/TI DI ISI SECARA MANUAL. TO DIBERI TANDA (- )
B87: VENDOR REPORT
AI88: CABANG | AJ88: =AJ2 -> RC SAMATA GOWA
AI89: PERIODE | AJ89: =AJ3 -> 8-14 JANUARI 2025
B90: TGL FAKTUR | C90: NO | E90: PEMAKAIAN | G90: PERSEDIAAN | I90: =I5 -> 46030 | K90: =K5 -> 46031 | M90: =M5 -> 46032 | O90: =O5 -> 46033 | Q90: =Q5 -> 46034 | S90: =S5 -> 46035 | U90: =U5 -> 46036 | W90: =W5 -> 0 | Y90: =Y5 -> 0 | AA90: =AA5 -> 0 | AC90: KHUSUS TO/TI | AE90: KREDIT BARGUD | AG90: KREDIT BAHAN BAKU | AI90: TOTAL | AK90: PERSEDIAAN | AM90: PEMAKAIAN
D91: KETERANGAN BAHAN | E91: MINGGU LALU | G91: AWAL | AC91: C. PATTY / CATERING STAFF | AI91: PEMBELIAN | AK91: AKHIR | AM91: MINGGU INI
B92: HARI | E92: DLM SATUAN | G92: DLM SATUAN | I92: =I7 -> KAMIS | K92: =K7 -> JUMAT | M92: =M7 -> SABTU | O92: =O7 -> MINGGU | Q92: =Q7 -> SENIN | S92: =S7 -> SELASA | U92: =U7 -> RABU | W92: =W7 -> 0 | Y92: =Y7 -> 0 | AA92: =AA7 -> 0 | AC92: PERKEDEL / BARGUD | AG92: AYAM DLL | AI92: DLM SATUAN | AK92: DLM SATUAN | AM92: DLM SATUAN
E93: Rp | F93: Unit | G93: Rp | H93: Unit | I93: Rp | J93: Unit | K93: Rp | L93: Unit | M93: Rp | N93: Unit | O93: Rp | P93: Unit | Q93: Rp | R93: Unit | S93: Rp | T93: Unit | U93: Rp | V93: Unit | W93: Rp | X93: Unit | Y93: Rp | Z93: Unit | AA93: Rp | AB93: Unit | AC93: Rp | AD93: Unit | AE93: Rp | AF93: Unit | AG93: Rp | AH93: Unit | AI93: Rp | AJ93: Unit | AK93: Rp | AL93: Unit | AM93: Rp | AN93: Unit
C94: 1 | D94: ='WEEKLY FC'!B127 -> PLASTIK JAGUNG | E94: -9100 | F94: -1.3 | G94: 14000 | H94: 2 | AI94: =SUM(I94,K94,M94,O94,Q94,S94,U94,W94,Y94,AA94,AC94,AE94,AG94) -> 0 | AJ94: =SUM(J94,L94,N94,P94,R94,T94,V94,X94,Z94,AB94,AD94,AF94,AH94) -> 0 | AK94: ='WEEKLY FC'!F127 -> 0 | AL94: ='WEEKLY FC'!D127 -> 0 | AM94: =G94+AI94-AK94 -> 14000 | AN94: =H94+AJ94-AL94 -> 2
C95: 2 | D95: ='WEEKLY FC'!B128 -> PLASTIK SEDANG | E95: 108864 | F95: 567 | G95: 696960 | H95: 3630 | AI95: =SUM(I95,K95,M95,O95,Q95,S95,U95,W95,Y95,AA95,AC95,AE95,AG95) -> 0 | AJ95: =SUM(J95,L95,N95,P95,R95,T95,V95,X95,Z95,AB95,AD95,AF95,AH95) -> 0 | AK95: ='WEEKLY FC'!F128 -> 613056 | AL95: ='WEEKLY FC'!D128 -> 3193 | AM95: =G95+AI95-AK95 -> 83904 | AN95: =H95+AJ95-AL95 -> 437
C96: 3 | D96: ='WEEKLY FC'!B129 -> PLASTIK KECIL | E96: 39281.5 | F96: 251 | G96: 451659 | H96: 2886 | AI96: =SUM(I96,K96,M96,O96,Q96,S96,U96,W96,Y96,AA96,AC96,AE96,AG96) -> 0 | AJ96: =SUM(J96,L96,N96,P96,R96,T96,V96,X96,Z96,AB96,AD96,AF96,AH96) -> 0 | AK96: ='WEEKLY FC'!F129 -> 408778 | AL96: ='WEEKLY FC'!D129 -> 2612 | AM96: =G96+AI96-AK96 -> 42881 | AN96: =H96+AJ96-AL96 -> 274
C97: 4 | D97: ='WEEKLY FC'!B130 -> PLASTIK JUMBO | E97: 28638 | F97: 43 | G97: 266400 | H97: 400 | AI97: =SUM(I97,K97,M97,O97,Q97,S97,U97,W97,Y97,AA97,AC97,AE97,AG97) -> 0 | AJ97: =SUM(J97,L97,N97,P97,R97,T97,V97,X97,Z97,AB97,AD97,AF97,AH97) -> 0 | AK97: ='WEEKLY FC'!F130 -> 241092 | AL97: ='WEEKLY FC'!D130 -> 362 | AM97: =G97+AI97-AK97 -> 25308 | AN97: =H97+AJ97-AL97 -> 38
C98: 5 | D98: ='WEEKLY FC'!B131 -> SEDOTAN PLASTIK | E98: 11750 | F98: 0.5 | G98: 258500 | H98: 11 | AI98: =SUM(I98,K98,M98,O98,Q98,S98,U98,W98,Y98,AA98,AC98,AE98,AG98) -> 0 | AJ98: =SUM(J98,L98,N98,P98,R98,T98,V98,X98,Z98,AB98,AD98,AF98,AH98) -> 0 | AK98: ='WEEKLY FC'!F131 -> 235000 | AL98: ='WEEKLY FC'!D131 -> 10 | AM98: =G98+AI98-AK98 -> 23500 | AN98: =H98+AJ98-AL98 -> 1
C99: 6 | D99: ='WEEKLY FC'!B132 -> ALAS BOX NASI | E99: 23400 | F99: 600 | G99: 177060 | H99: 4540 | AI99: =SUM(I99,K99,M99,O99,Q99,S99,U99,W99,Y99,AA99,AC99,AE99,AG99) -> 0 | AJ99: =SUM(J99,L99,N99,P99,R99,T99,V99,X99,Z99,AB99,AD99,AF99,AH99) -> 0 | AK99: ='WEEKLY FC'!F132 -> 139230 | AL99: ='WEEKLY FC'!D132 -> 3570 | AM99: =G99+AI99-AK99 -> 37830 | AN99: =H99+AJ99-AL99 -> 970
C100: 7 | D100: ='WEEKLY FC'!B133 -> BOX NASI ROCKET | E100: 727849.2 | F100: 970 | G100: 4382102.4 | H100: 5840 | AI100: =SUM(I100,K100,M100,O100,Q100,S100,U100,W100,Y100,AA100,AC100,AE100,AG100) -> 0 | AJ100: =SUM(J100,L100,N100,P100,R100,T100,V100,X100,Z100,AB100,AD100,AF100,AH100) -> 0 | AK100: ='WEEKLY FC'!F133 -> 3804325.2 | AL100: ='WEEKLY FC'!D133 -> 5070 | AM100: =G100+AI100-AK100 -> 577777.2 | AN100: =H100+AJ100-AL100 -> 770
C101: 8 | D101: ='WEEKLY FC'!B134 -> BOX CATERING (KARDUS) | E101: 7104 | F101: 1 | G101: 99456 | H101: 14 | AI101: =SUM(I101,K101,M101,O101,Q101,S101,U101,W101,Y101,AA101,AC101,AE101,AG101) -> 0 | AJ101: =SUM(J101,L101,N101,P101,R101,T101,V101,X101,Z101,AB101,AD101,AF101,AH101) -> 0 | AK101: ='WEEKLY FC'!F134 -> 99456 | AL101: ='WEEKLY FC'!D134 -> 14 | AM101: =G101+AI101-AK101 -> 0 | AN101: =H101+AJ101-AL101 -> 0
B102: P | C102: 9 | D102: ='WEEKLY FC'!B135 -> BOX MIE | E102: 0 | F102: 0 | G102: 0 | H102: 0 | AI102: =SUM(I102,K102,M102,O102,Q102,S102,U102,W102,Y102,AA102,AC102,AE102,AG102) -> 0 | AJ102: =SUM(J102,L102,N102,P102,R102,T102,V102,X102,Z102,AB102,AD102,AF102,AH102) -> 0 | AK102: ='WEEKLY FC'!F135 -> 0 | AL102: ='WEEKLY FC'!D135 -> 0 | AM102: =G102+AI102-AK102 -> 0 | AN102: =H102+AJ102-AL102 -> 0
B103: E | C103: 10 | D103: ='WEEKLY FC'!B136 -> BOX STEAK / NASGOR | E103: 177045 | F103: 290 | G103: 259462.5 | H103: 425 | AI103: =SUM(I103,K103,M103,O103,Q103,S103,U103,W103,Y103,AA103,AC103,AE103,AG103) -> 0 | AJ103: =SUM(J103,L103,N103,P103,R103,T103,V103,X103,Z103,AB103,AD103,AF103,AH103) -> 0 | AK103: ='WEEKLY FC'!F136 -> 228937.5 | AL103: ='WEEKLY FC'!D136 -> 375 | AM103: =G103+AI103-AK103 -> 30525 | AN103: =H103+AJ103-AL103 -> 50
B104: M | C104: 11 | D104: ='WEEKLY FC'!B137 -> COVER NASI BRANDING | E104: 164626 | F104: 1069 | G104: 1067374 | H104: 6931 | AI104: =SUM(I104,K104,M104,O104,Q104,S104,U104,W104,Y104,AA104,AC104,AE104,AG104) -> 0 | AJ104: =SUM(J104,L104,N104,P104,R104,T104,V104,X104,Z104,AB104,AD104,AF104,AH104) -> 0 | AK104: ='WEEKLY FC'!F137 -> 998844 | AL104: ='WEEKLY FC'!D137 -> 6486 | AM104: =G104+AI104-AK104 -> 68530 | AN104: =H104+AJ104-AL104 -> 445
...

Sheet IKHTISAR FOOD COST
A2: LAPORAN IKHTISAR FOOD COST
C5: CABANG : | D5: =LPKK!O4 -> RC SAMATA GOWA
C6: PERIODE: | D6: =LPKK!O5 -> 8-14 JANUARI 2025
B8: FOOD & BEVERAGE | D8: PAPER
A10: PERSEDIAAN AWAL | B10: 17341888 | D10: 11725905
A12: TRANSFER IN (+) =
A13: C. PATTY | B13: ='TO - TI'!S21 -> 264706.31
A14: PERKEDEL MANUAL
A15: PERKEDEL | B15: ='TO - TI'!D20 -> 237571.91
A17: TOTAL TRANSFER IN | B17: =SUM(B12:B15) -> 502278.22 | D17: =SUM(D12:D15) -> 0
A19: PEMBELIAN
A20: PEMBELIAN KREDIT | B20: =VENDOR!AI177 -> 12234546 | D20: =VENDOR!AI178 -> 0
A21: PEMBELIAN KONTAN | B21: =VENDOR!AI179 -> 1105240 | D21: =VENDOR!AI180 -> 75900
A22: TOTAL PEMBELIAN | B22: =B20+B21 -> 13339786 | D22: =D20+D21 -> 75900
A24: JUMLAH YANG TERSEDIA | B24: =B10+B17+B22 -> 31183952 | D24: =D10+D17+D22 -> 11801805
A26: TRANSFER OUT (-) =
A27: TO CATERING STAFF / FREE | B27: ='TO - TI'!I27+'TO - TI'!N23 -> 203305.98
A28: C. PATTY | B28: =B13 -> 264706.31
A29: PERKEDEL | B29: =B15 -> 237571.91
A30: TO AMB MEETING | B30: 26627
A31: PERGANTIAN PRODUK
A33: TOTAL TRANSFER OUT | B33: =SUM(B27:B31) -> 732211.19 | D33: =SUM(D27:D31) -> 0
A35: PERSEDIAAN AKHIR | B35: ='WEEKLY FC'!F362 -> 17074709 | D35: ='WEEKLY FC'!F363 -> 10606588
A37: JUMLAH YANG DIPAKAI | B37: =B24-B33-B35 -> 13377033 | D37: =D24-D33-D35 -> 1195216.8
A38: (%) | B38: =(B37/B47) -> 0.5317753 | D38: =D37/B47 -> 0.047513284
A41: PENJUALAN KOTOR | B41: ='LAPORAN KAS PERIODE'!M8 -> 28127721
A42: KOREKSI (-) | B42: ='LAPORAN KAS PERIODE'!M12 -> 74750
A43: DISCOUNT (-) | B43: ='LAPORAN KAS PERIODE'!M14 -> 270500
A44: KOMISI PENJUALAN ONLINE (-) | B44: ='LAPORAN KAS PERIODE'!M9+'LAPORAN KAS PERIODE'!M10+'LAPORAN KAS PERIODE'!M11 -> 2627048
A45: TAX (-)
A47: PENJUALAN BERSIH | B47: =B41-B42-B43-B44-B45 -> 25155423
A50: JUMLAH BAHAN YANG DIPAKAI | B50: =B37+D37 -> 14572249 | D50: =B50/B51 -> 0.57928858
A51: JUMLAH PENJUALAN BERSIH | B51: =B47 -> 25155423
A54: CATATAN : PENJUALAN BERSIH DIDAPAT DARI PENJUALAN KOTOR - KOREKSI - DISCOUNT
A55: - PENJUALAN DILUAR PRODUK FOOD & BEVERAGES (KOIN KIDDY RIDE, ROCKET KIDS DLL)

Sheet TO - TI
A2: TO / TI PERKEDEL | F2: TO CATTERING STAFF | K2: TO FREE UNDIAN GELEGAR JANUARI | P2: TO / TI CHICKEN PATTY | U2: TO / TI PERKEDEL MANUAL | Z2: TO CATTERING KHUSUS
C3: CABANG : | D3: =LPKK!O4 -> RC SAMATA GOWA | H3: CABANG : | I3: =D3 -> RC SAMATA GOWA | M3: CABANG : | N3: =I3 -> RC SAMATA GOWA | R3: CABANG : | S3: =D3 -> RC SAMATA GOWA | W3: CABANG : | X3: =S3 -> RC SAMATA GOWA | AB3: CABANG :
C4: PERIODE / TGL : | D4: =LPKK!O5 -> 8-14 JANUARI 2025 | H4: PERIODE / TGL : | I4: =D4 -> 8-14 JANUARI 2025 | M4: PERIODE / TGL : | N4: =I4 -> 8-14 JANUARI 2025 | R4: PERIODE / TGL : | S4: =D4 -> 8-14 JANUARI 2025 | W4: PERIODE / TGL : | X4: =S4 -> 8-14 JANUARI 2025 | AB4: PERIODE / TGL :
A6: NAMA BAHAN | B6: QTY | C6: HARGA BELI | D6: TOTAL | F6: NAMA PRODUCT | G6: QTY | H6: HARGA JUAL | I6: TOTAL | K6: NAMA PRODUCT | L6: QTY | M6: HARGA JUAL | N6: TOTAL | P6: NAMA BAHAN | Q6: QTY | R6: HARGA BELI | S6: TOTAL | U6: NAMA BAHAN | V6: QTY | W6: HARGA BELI | X6: TOTAL | Z6: NAMA PRODUCT | AA6: QTY | AB6: HARGA JUAL | AC6: TOTAL
A7: PREMIK KENTANG | B7: =H41 -> 4000 | C7: ='WEEKLY FC'!E330 -> 38055.24 | D7: =B7/1000*C7 -> 152220.96 | F7: DADA | G7: 7 | H7: 13000 | I7: =H7*G7*G27 -> 55391.748 | K7: DADA | M7: 13000 | N7: =L7*M7*L23 -> 0 | P7: DAGING / MENTOK | Q7: 5 | R7: =C8 -> 6154.7692 | S7: =R7*Q7 -> 30773.846 | U7: KENTANG SAYUR | W7: 10000 | X7: =V7/1000*W7 -> 0 | Z7: CHICKEN STRIP | AB7: 10000 | AC7: =AB7*AA7*AA22 -> 0
A8: DAGING AYAM/MENTOK | C8: ='WEEKLY FC'!E11 -> 6154.7692 | D8: =B8*C8 -> 0 | F8: P. ATAS | I8: =H8*G8*G27 -> 0 | K8: P. ATAS | M8: 13000 | N8: =L8*M8*L23 -> 0 | P8: PAHA BAWAH | Q8: 50 | R8: ='WEEKLY FC'!E14 -> 3898.0192 | S8: =R8*Q8 -> 194900.96 | U8: DAGING AYAM/MENTOK | W8: ='WEEKLY FC'!E11 -> 6154.7692 | X8: =V8*W8 -> 0 | Z8: CHICKEN STEAK | AB8: 10000 | AC8: =AB8*AA8*AA22 -> 0
A9: AIR GALON | B9: =H43 -> 6000 | C9: ='WEEKLY FC'!E77 -> 5000 | D9: =B9/19000*C9 -> 1578.9474 | F9: DADA HOT SPICY | I9: =H9*G9*G27 -> 0 | K9: P. BAWAH | M9: 11000 | N9: =L9*M9*L23 -> 0 | P9: DAGING GILING | S9: =R9*Q9 -> 0 | X9: =V9/1000*W9 -> 0 | Z9: CHICKEN BURGER | AB9: 9000 | AC9: =AB9*AA9*AA22 -> 0
A10: BAWANG MERAH | B10: =H45 -> 200 | C10: ='WEEKLY FC'!E303 -> 52000 | D10: =B10/1000*C10 -> 10400 | F10: P. ATAS HOT SPICY | I10: =H10*G10*G27 -> 0 | K10: SAYAP | M10: 10000 | N10: =L10*M10*L23 -> 0 | P10: ROTI TAWAR | Q10: =R46 -> 16 | R10: ='WEEKLY FC'!E62 -> 933 | S10: =R10*Q10 -> 14928 | U10: BAWANG MERAH | W10: ='WEEKLY FC'!E303 -> 52000 | X10: =V10/1000*W10 -> 0 | Z10: NASI GORENG | AB10: 8000 | AC10: =AB10*AA10*AA22 -> 0
A11: BAWANG PUTIH | B11: =H46 -> 50 | C11: ='WEEKLY FC'!E302 -> 52000 | D11: =B11/1000*C11 -> 2600 | F11: DADA SAMBAL GEPREK | I11: =H11*G11*G27 -> 0 | K11: NASI | M11: 4000 | N11: =L11*M11*L23 -> 0 | P11: SUSU ULTRA | Q11: =R45 -> 50 | R11: ='WEEKLY FC'!E65 -> 4700 | S11: =Q11/250*R11 -> 940 | U11: BAWANG PUTIH | W11: ='WEEKLY FC'!E302 -> 52000 | X11: =V11/1000*W11 -> 0 | AB11: 4000 | AC11: =AB11*AA11*AA22 -> 0
A12: PREMIK PERKEDEL | B12: =H48 -> 4 | C12: ='WEEKLY FC'!E342 -> 3108 | D12: =B12*C12 -> 12432 | F12: P. ATAS SAMBAL GEPREK | I12: =H12*G12*G27 -> 0 | K12: ES TEH | M12: =H25 -> 5000 | N12: =L12*M12*L23 -> 0 | P12: BAWANG BOMBAY | Q12: =R41 -> 100 | R12: ='WEEKLY FC'!E58 -> 5000 | S12: =Q12/1000*R12 -> 500 | U12: GARAM | W12: ='WEEKLY FC'!E299 -> 35000 | AB12: 4000 | AC12: =AB12*AA12*AA22 -> 0
A13: BATANG SLEDRI | B13: =H50 -> 500 | C13: ='WEEKLY FC'!E301 -> 42000 | D13: =B13/1000*C13 -> 21000 | F13: DADA SAMBAL GEPREK | I13: =H13*G13*G27 -> 0 | K13: STEE | M13: 5000 | N13: =M13*L13*L23 -> 0 | P13: MARGARIN | Q13: =R43 -> 35 | R13: ='WEEKLY FC'!E60 -> 6100 | S13: =Q13/200*R13 -> 1067.5 | U13: LADA | W13: ='WEEKLY FC'!E300 -> 28100 | AB13: 4000 | AC13: =AB13*AA13*AA22 -> 0
A14: KUNING TELUR | B14: =H51 -> 20 | C14: ='WEEKLY FC'!E320 -> 1867 | D14: =C14*B14 -> 37340 | F14: P. ATAS SAMBAL GEPREK | I14: =H14*G14*G27 -> 0 | N14: =M14*L14*L23 -> 0 | P14: PREMIK C. PATTY | Q14: =R40 -> 1 | R14: ='WEEKLY FC'!E343 -> 6660 | S14: =Q14*R14 -> 6660 | U14: VETSIN | W14: ='WEEKLY FC'!E298 -> 0 | AB14: 4000 | AC14: =AB14*AA14*AA22 -> 0
F15: DADA SAMBAL GEPREK | I15: =H15*G15*G27 -> 0 | N15: =M15*L15*L23 -> 0 | P15: TELUR | Q15: =R44 -> 8 | R15: =C14 -> 1867 | S15: =Q15*R15 -> 14936 | U15: BATANG SLEDRI | W15: ='WEEKLY FC'!E301 -> 42000 | X15: =V15/1000*W15 -> 0 | AC15: =AB15*AA15*AA22 -> 0
F16: P. ATAS SAMBAL GEPREK | I16: =H16*G16*G27 -> 0 | N16: =M16*L16*L23 -> 0 | U16: KUNING TELUR | W16: ='WEEKLY FC'!E320 -> 1867 | X16: =V16*W16 -> 0 | AC16: =AB16*AA16*AA22 -> 0
F17: DADA CHEESE LEVEL | I17: =H17*G17*G27 -> 0 | N17: =M17*L17*L24 -> 0
F18: P. ATAS CHEESE LEVEL | I18: =H18*G18*G27 -> 0 | N18: =M18*L18*L25 -> 0
A19: PAHA BAWAH | C19: ='WEEKLY FC'!E14 -> 3898.0192 | D19: =C19*B19 -> 0 | F19: CHICKEN STRIP | I19: =H19*G19*G27 -> 0 | N19: =M19*L19*L23 -> 0 | AC19: =AB19*AA19*AA22 -> 0
C20: SUB TOTAL | D20: =SUM(D7:D19) -> 237571.91 | F20: CHICKEN STEAK | H20: ='LAP. PENJUALAN '!S207 -> 14000 | I20: =H20*G20*G27 -> 0 | N20: =M20*L20*L23 -> 0 | W20: SUB TOTAL | X20: =SUM(X7:X19) -> 0 | AC20: =AB20*AA20*AA22 -> 0
F21: CHICKEN BURGER | I21: =H21*G21*G27 -> 0 | N21: =M21*L21*L23 -> 0 | R21: SUB TOTAL | S21: =SUM(S7:S20) -> 264706.31 | AC21: =AB21*AA21*AA22 -> 0
A22: PERKEDEL JADI | B22: 144 | C22: HPP | D22: =D20/B22 -> 1649.8049 | F22: NASI GORENG | I22: =H22*G22*G27 -> 0 | U22: PERKEDEL JADI | W22: HPP | X22: =X20/V22 -> #DIV/0! | Z22: FOOD COST | AA22: =H36 -> 0.60870053 | AC22: =SUM(AC7:AC21) -> 0
F23: NASI | G23: 52 | H23: 4000 | I23: =H23*G23*G27 -> 126609.71 | K23: FOOD COST | L23: =H36 -> 0.60870053 | M23: TOTAL | N23: =SUM(N7:N22) -> 0 | P23: CHICKEN PATTY JADI | Q23: 69 | S23: =S21/Q23 -> 3836.3233
F24: LEMON TEA | I24: =H24*G24*G27 -> 0
F25: ES TEH | G25: 7 | H25: 5000 | I25: =H25*G25*G27 -> 21304.518
I26: =H26*G26*G26 -> 0
D27: PARAF | F27: FOOD COST | G27: =H36 -> 0.60870053 | I27: =SUM(I7:I26) -> 203305.98 | N27: PARAF | S27: PARAF | X27: PARAF | AC27: PARAF
I29: PARAF
D30: (..........................) | X30: (..........................)
N31: (.........................) | S31: (..........................) | U31: NB. DIKERJAKAN MANUAL TANPA RUMUS | AC31: (.........................)
I33: (.........................)
A34: BUAT BERAPA RESEP | B34: 4 | P34: BUAT BERAPA RESEP | Q34: 1
F36: FOOD COST PERIODE KEMARIN | H36: 0.60870053
A37: TOLONG DIBACA SEBELUM MENGISI TO/TI | P37: RUMUS C. PATTY
A39: CATATAN : | F39: RUMUS PERKEDEL
A40: 1. TO/TI PERKEDEL TINGGAL MENGISI MANUAL KOLOM | P40: PREMIK PATTY | Q40: 1 | R40: =Q40*Q34 -> 1
A41: BUAT BERPA RESEP DAN PERKEDEL JADI . | F41: PREMIK KENTANG | G41: 1000 | H41: =G41*B34 -> 4000 | P41: BAWANG BOMBAY | Q41: 100 | R41: =Q41*Q34 -> 100
A42: 2. TO/TI PERKEDEL KOLOM AYAM DI ISI MANUAL | F42: DAGING AYAM/MENTOK | H42: =G42*B34 -> 0
A43: 3. TO FREE DIISI MANUAL | F43: AIR GALON | G43: 1500 | H43: =G43*B34 -> 6000 | P43: MARGARIN | Q43: 35 | R43: =Q43*Q34 -> 35
A44: 4. FOOD COST PERIODE KEMARIN DIISI DAN DISESUAIKAN | P44: TELUR | Q44: 8 | R44: =Q44*Q34 -> 8
A45: 5. TO CATTERING STAFF DIISI MANUAL | F45: BAWANG MERAH | G45: 50 | H45: =G45*B34 -> 200 | P45: SUSU ULTRA | Q45: 50 | R45: =Q45*Q34 -> 50
A46: 6. TO/TI CHICKEN PATTY DIISI MANUAL PAHA BAWAH ATAU | F46: BAWANG PUTIH | G46: 12.5 | H46: =G46*B34 -> 50 | P46: ROTI TAWAR | Q46: 16 | R46: =Q46*Q34 -> 16
A47: MENTOK YG DIGUNAKAN DAN BERAPA RESEP | F47: PREMIK PERKEDEL
A48: 7. TO/TI JUAL BARANG GUDANG DAN TO/TI FREE DIMASUKAN | G48: 1 | H48: =G48*B34 -> 4
A49: MANUAL DI VENDOR
A50: 8. KALO TIDAK BIKIN TO/TI PERKEDEL DAN CHIKEN PATTY | F50: BATANG SLEDRI | G50: 125 | H50: =G50*B34 -> 500
A51: MAKA KOLOM BUAT BERAPA RESEP DI HAPUS SAJA | F51: KUNING TELUR | G51: 5 | H51: =G51*B34 -> 20
A52: 9. UNTUK TOTAL (RP) & UNIT (PCS) TO CATERING STAFF DADA/P. ATAS ORIGINAL & HOT SPICY DI VENDOR DIMASUKKAN DIKOLOM DADA/PAHA ATAS(PCS)
A53: 10. UNTUK TOTAL (RP) & UNIT (PCS) TO CATERING STAFF CHICKEN STEAK & CHICKEN STRIP DI VENDOR DIMASUKKAN DIKOLOM DADA MENTOK
A54: 11. UNTUK TOTAL (RP) TO CATERING STAFF CHICKEN BURGER DI VENDOR DIMASUKKAN KE KOLOM BAHAN ROTI & JUMLAH UNIT MASUK KE KOLOM CHICKEN PATTY (PCS) & ROTI BURGER (PCS)
A55: 12. UNTUK TOTAL (RP) TO CATERING STAFF NASI GORENG DI VENDOR MASUK KE KOLOM BAHAN NASGOR. JUMLAH MASING- MASING UNIT MASUK KE DALAM DADA MENTOK (PCS), PREMIX NASGOR (PCS), TELUR (PCS) & BERAS (kg)
A56: 13. UNTUK TOTAL (RP) TO CATERING STAFF DADA/ PAHA ATAS GEPREK/TERASI/MATAH DI VENDOR MASUK KE KOLOM AYAM. JUMLAH MASING- MASING UNIT MASUK KE DALAM DADA/P. ATAS (PCS), MINYAK (LITER), CABAI RAWIT MERAH & HIJAU (KG), PREMIX GEPREK (PACK), PREMIX MATAH (PACK), PREMIX TERASI (PACK)
A57: 14. UNTUK TOTAL (RP) TO CATERING STAFF DADA/ PAHA ATAS CHEESE LEVEL DI VENDOR MASUK KE KOLOM AYAM. JUMLAH MASING- MASING UNIT MASUK KE DADA/P. ATAS (PCS), LEVEL 1/2 (PACK), CHEESE MELT (PACK)
A58: 15. UNTUK LEMON TEA DAN ES TEH TOTAL ( RP ) & UNIT (PACK) MASUK KE MASING-MASING BAHAN MINUMAN
A59: 16. UNTUK ALL CATERING STAFF WAJIB DIPOSTING DENGAN HARGA 0
A60: 17. UNTUK ADMINISTRASI TELUR CATTRING STAFF DIPISAH ANTARA TELUR OPRASIONAL, DAN MASUK KE VENDOR DI LEMBAR KE 3, WAJIB MENGERJAKAN COST ANALIST TELUR CATTRING STAFF
A69: 0

Sheet HITUNGAN HPP PRODUK
L3: FOOD COST ITEM
Z7: PAKET GEPREK ES THE KELAS 3 & 4 SULAWESI | AS7: PAKET HOT CHESE STEE KELAS 2,3&4 SULAWESI | AZ7: PAKET HOT CHESE THE RC KELAS 2,3&4 SULAWESI
A8: AIR GALON | D8: DADA | G8: SAOS STEAK | J8: PAKET SEGAR KELAS 2,3&4 SULAWESI ES THE POCI | AR8: OKE | AY8: OKE | BF8: OKE
A9: 1 LITER | B9: ='WEEKLY FC'!E77/19 -> 263.15789 | D9: 1 PCS DADA | E9: ='WEEKLY FC'!E12 -> 7385.7231 | G9: 1 PACK PREMIX STEAK ( 200 GR ) | H9: ='WEEKLY FC'!E327 -> 17094 | X9: OKE
A10: ES BATU ( 1 GRAM ) | B10: ='WEEKLY FC'!E78/10000 -> 1.6 | D10: MARINADE | E10: ='WEEKLY FC'!E324/414 -> 198.94203 | G10: AIR (1200 ML) | H10: =B9*1.2 -> 315.78947 | AS10: PAKET | AU10: PAKET | AW10: PAKET | AZ10: PAKET | BB10: PAKET | BD10: PAKET
D11: TEPUNG CAKRA | E11: =('WEEKLY FC'!E331*7)/200 -> 327.705 | J11: PAKET | L11: PAKET | N11: PAKET | P11: PAKET | R11: PAKET | T11: PAKET | V11: PAKET | Z11: PAKET | AB11: PAKET | AD11: PAKET | AF11: PAKET | AH11: PAKET | AJ11: PAKET | AL11: PAKET | AN11: PAKET | AP11: PAKET | AS11: LEVEL 1 | AU11: LEVEL 2 | AW11: LEVEL 3 | AZ11: LEVEL 1 | BB11: LEVEL 2 | BD11: LEVEL 3
D12: TEPUNG BRIDER | E12: =(('WEEKLY FC'!E325*2)/200) -> 234.1 | G12: HPP 1 RESEP | H12: =H9+H10 -> 17409.789 | J12: SEGAR 1 | L12: SEGAR 2 | N12: SEGAR 3 | P12: SEGAR 4 | R12: SEGAR 5 | T12: SEGAR 6 | V12: SEGAR 7 | Z12: GEPREK 1 | AB12: GEPREK 2 | AD12: GEPREK 3 | AF12: MATAH 1 | AH12: MATAH 2 | AJ12: MATAH 3 | AL12: TERASI 1 | AN12: TERASI 2 | AP12: TERASI 3 | AS12: NASI | AT12: =W41 -> 1301.4354 | AU12: NASI | AV12: =Y41 -> 1301.4354 | AW12: NASI | AX12: =AA41 -> 1301.4354 | AZ12: NASI | BA12: =AT12 -> 1301.4354 | BB12: NASI | BC12: =AV12 -> 1301.4354 | BD12: NASI | BE12: =AX12 -> 1301.4354
A13: SIMPLE SIRUP | D13: MINYAK | E13: ='WEEKLY FC'!E168/33 -> 606.10227 | G13: HPP 1 PORSI | H13: =H12/12 -> 1450.8158 | J13: NASI | K13: =H63 -> 954.38596 | L13: NASI | M13: =K13 -> 954.38596 | N13: BURGER | O13: =H138 -> 8292.1367 | P13: NASI | Q13: =K13 -> 954.38596 | R13: PEMBUNGKUS | S13: =E186 -> 1450.5 | T13: NASI | U13: =K13 -> 954.38596 | V13: NASI | W13: =K13 -> 954.38596 | Z13: NASI | AA13: =W13 -> 954.38596 | AB13: NASI | AC13: =AA13 -> 954.38596 | AD13: NASI | AE13: =AC13 -> 954.38596 | AF13: NASI | AG13: =AE13 -> 954.38596 | AH13: NASI | AI13: =AG13 -> 954.38596 | AJ13: NASI | AK13: =AI13 -> 954.38596 | AL13: NASI | AM13: =AK13 -> 954.38596 | AN13: NASI | AO13: =AM13 -> 954.38596 | AP13: NASI | AQ13: =AO13 -> 954.38596 | AS13: SAYAP | AT13: =W42 -> 5698.4354 | AU13: P.BAWAH | AV13: =Y42 -> 5288.1162 | AW13: DADA/PA | AX13: =AA42 -> 8775.82 | AZ13: SAYAP | BA13: =AT13 -> 5698.4354 | BB13: P.BAWAH | BC13: =AV13 -> 5288.1162 | BD13: DADA/PA | BE13: =AX13 -> 8775.82
A14: 1 KG GULA | B14: ='WEEKLY FC'!E72 -> 17600 | D14: AIR | E14: =(B9*1.75)/200 -> 2.3026316 | J14: SAYAP | K14: =E56 -> 6105.4354 | L14: C.STEAK | M14: =E75 -> 8145.877 | N14: ES TEH | O14: =K15 -> 878.01535 | P14: P.BAWAH | Q14: =E43 -> 5695.1162 | R14: NASGOR | S14: =H90 -> 5769.6704 | T14: C.STRIP | U14: =E111 -> 5472.3985 | V14: DADA / PA | W14: =E17 -> 9182.82 | Z14: SAYAP | AA14: =E57 -> 5698.4354 | AB14: P.BAWAH | AC14: =E44 -> 5288.1162 | AD14: DADA | AE14: =E18 -> 8775.82 | AF14: SAYAP GPRK | AG14: =AA14 -> 5698.4354 | AH14: P.BAWAH | AI14: =AC14 -> 5288.1162 | AJ14: DADA/PA | AK14: =AE14 -> 8775.82 | AL14: SAYAP | AM14: =AG14 -> 5698.4354 | AN14: P.BAWAH | AO14: =AI14 -> 5288.1162 | AP14: DADA/PA | AQ14: =AK14 -> 8775.82 | AS14: STEE | AT14: =M95 -> 3500 | AU14: STEE | AV14: =AT14 -> 3500 | AW14: STEE | AX14: =AV14 -> 3500 | AZ14: THE RC | BA14: =B301 -> 219.21053 | BB14: THE RC | BC14: =BA14 -> 219.21053 | BD14: THE RC | BE14: =BC14 -> 219.21053
A15: 1 LITER AIR | B15: =B9 -> 263.15789 | D15: SAOS SASET | E15: ='WEEKLY FC'!E334+'WEEKLY FC'!E335 -> 407 | G15: CHESSEE MELT | J15: ES TEH | K15: =B128 -> 878.01535 | L15: ES TEH | M15: =K15 -> 878.01535 | N15: PEMBUNGKUS | O15: =E177 -> 1130 | P15: ES TEH | Q15: =K15 -> 878.01535 | R15: ES TEH | S15: =K15 -> 878.01535 | T15: ES TEH | U15: =S15 -> 878.01535 | V15: ES TEH | W15: =U15 -> 878.01535 | Z15: ES TEH | AA15: =K15 -> 878.01535 | AB15: ES TEH | AC15: =AA15 -> 878.01535 | AD15: ES TEH | AE15: =AC15 -> 878.01535 | AF15: ES TEH | AG15: =AC15 -> 878.01535 | AH15: ES TEH | AI15: =AG15 -> 878.01535 | AJ15: ES TEH | AK15: =AI15 -> 878.01535 | AL15: ES TEH | AM15: =AG15 -> 878.01535 | AN15: ES TEH | AO15: =AM15 -> 878.01535 | AP15: ES TEH | AQ15: =AO15 -> 878.01535 | AS15: C LEVEL + CM | AT15: =W44 -> 1282.2658 | AU15: C LEVEL + CM | AV15: =AT15 -> 1282.2658 | AW15: C LEVEL + CM | AX15: =AV15 -> 1282.2658 | AZ15: C LEVEL + CM | BA15: =AT15 -> 1282.2658 | BB15: C LEVEL + CM | BC15: =AV15 -> 1282.2658 | BD15: C LEVEL + CM | BE15: =BC15 -> 1282.2658
D16: BIANG BRIDER | E16: =('WEEKLY FC'!E344*1)/200 -> 20.945 | G16: 1 PACK CHESSE MELT ( 100 GR ) | H16: ='WEEKLY FC'!E338 -> 12937 | J16: PEMBUNGKUS | K16: =E204 -> 1555.36 | L16: PEMBUNGKUS | M16: =K16 -> 1555.36 | P16: PEMBUNGKUS | Q16: =M16 -> 1555.36 | R16: HPP NON CVR | S16: =S14+S15 -> 6647.6857 | T16: PEMBUNGKUS | U16: =K16 -> 1555.36 | V16: PEMBUNGKUS | W16: =K16 -> 1555.36 | Z16: GPRK | AA16: =H51 -> 897.4976 | AB16: GPRK | AC16: =AA16 -> 897.4976 | AD16: GPRK | AE16: =AC16 -> 897.4976 | AF16: MATAH | AG16: =E135 -> 1686.4853 | AH16: MATAH | AI16: =AG16 -> 1686.4853 | AJ16: MATAH | AK16: =AI16 -> 1686.4853 | AL16: TRASI | AM16: =E150 -> 1473.3767 | AN16: TRASI | AO16: =AM16 -> 1473.3767 | AP16: TRASI | AQ16: =AO16 -> 1473.3767 | AS16: PEMBUNGKUS | AT16: =W45 -> 2003.36 | AU16: PEMBUNGKUS | AV16: =AT16 -> 2003.36 | AW16: PEMBUNGKUS | AX16: =AV16 -> 2003.36 | AZ16: PEMBUNGKUS | BA16: =AT16 -> 2003.36 | BB16: PEMBUNGKUS | BC16: =AV16 -> 2003.36 | BD16: PEMBUNGKUS | BE16: =BC16 -> 2003.36
A17: HPP 1 RESEP ( 1500 ML ) | B17: =SUM(B13:B15) -> 17863.158 | D17: HPP DADA | E17: =SUM(E9:E16) -> 9182.82 | G17: AIR (400 ML ) | H17: =B9*0.4 -> 105.26316 | J17: HPP NON CVR | K17: =SUM(K13:K15) -> 7937.8367 | L17: HPP NON CVR | M17: =SUM(M13:M15) -> 9978.2783 | N17: HPP NON CVR | O17: =O13+O14 -> 9170.152 | P17: HPP NON CVR | Q17: =SUM(Q13:Q15) -> 7527.5175 | R17: HPP + COVER | S17: =S16+S13 -> 8098.1857 | T17: HPP NON CVR | U17: =SUM(U13:U16) -> 8860.1598 | V17: HPP NON CVR | W17: =SUM(W13:W15) -> 11015.221 | Z17: PEMBUNGKUS | AA17: =E168 -> 1555.36 | AB17: PEMBUNGKUS | AC17: =AA17 -> 1555.36 | AD17: PEMBUNGKUS | AE17: =AC17 -> 1555.36 | AF17: PEMBUNGKUS | AG17: =AE17 -> 1555.36 | AH17: PEMBUNGKUS | AI17: =AG17 -> 1555.36 | AJ17: PEMBUNGKUS | AK17: =AI17 -> 1555.36 | AL17: PEMBUNGKUS | AM17: =AK17 -> 1555.36 | AN17: PEMBUNGKUS | AO17: =AM17 -> 1555.36 | AP17: PEMBUNGKUS | AQ17: =AO17 -> 1555.36 | AS17: HPP NON CVR | AT17: =SUM(AT12:AT15) -> 11782.137 | AU17: HPP NON CVR | AV17: =SUM(AV12:AV15) -> 11371.817 | AW17: HPP NON CVR | AX17: =SUM(AX12:AX15) -> 14859.521 | AZ17: HPP NON CVR | BA17: =SUM(BA12:BA15) -> 8501.3471 | BB17: HPP NON CVR | BC17: =SUM(BC12:BC15) -> 8091.0279 | BD17: HPP NON CVR | BE17: =SUM(BE12:BE15) -> 11578.732
A18: HPP 1 LITER | B18: =(B17/1.5) -> 11908.772 | D18: HPP DADA U/GPRK & LVL | E18: =E17-E15 -> 8775.82 | J18: HPP + COVER | K18: =K17+K16 -> 9493.1967 | L18: HPP + COVER | M18: =M17+M16 -> 11533.638 | N18: HPP + COVER | O18: =O17+O15 -> 10300.152 | P18: HPP + COVER | Q18: =Q17+Q16 -> 9082.8775 | T18: HPP + COVER | V18: HPP + COVER | W18: =W17+W16 -> 12570.581 | Z18: HPP NON CVR | AA18: =SUM(AA13:AA16) -> 8428.3343 | AB18: HPP NON CVR | AC18: =SUM(AC13:AC17) -> 9573.3751 | AD18: HPP NON CVR | AE18: =SUM(AE13:AE16) -> 11505.719 | AF18: HPP NON CVR | AG18: =SUM(AG13:AG16) -> 9217.322 | AH18: HPP NON CVR | AI18: =SUM(AI13:AI16) -> 8807.0028 | AJ18: HPP NON CVR | AK18: =SUM(AK13:AK16) -> 12294.707 | AL18: HPP NON CVR | AM18: =SUM(AM13:AM16) -> 9004.2134 | AN18: HPP NON CVR | AO18: =SUM(AO13:AO16) -> 8593.8942 | AP18: HPP NON CVR | AQ18: =SUM(AQ13:AQ16) -> 12081.598 | AS18: HPP + COVER | AT18: =AT17+AT16 -> 13785.497 | AU18: HPP + COVER | AV18: =AV17+AV16 -> 13375.177 | AW18: HPP + COVER | AX18: =AX17+AX16 -> 16862.881 | AZ18: HPP + COVER | BA18: =BA17+BA16 -> 10504.707 | BB18: HPP + COVER | BC18: =BC17+BC16 -> 10094.388 | BD18: HPP + COVER | BE18: =BE17+BE16 -> 13582.092
Z19: HPP + COVER | AA19: =AA18+AA17 -> 9983.6943 | AB19: HPP + COVER | AC19: =AC18+AC17 -> 11128.735 | AD19: HPP + COVER | AE19: =AE18+AE17 -> 13061.079 | AF19: HPP + COVER | AG19: =AG18+AG17 -> 10772.682 | AH19: HPP + COVER | AI19: =AI18+AI17 -> 10362.363 | AJ19: HPP + COVER | AK19: =AK18+AK17 -> 13850.067 | AL19: HPP + COVER | AM19: =AM18+AM17 -> 10559.573 | AN19: HPP + COVER | AO19: =AO18+AO17 -> 10149.254 | AP19: HPP + COVER | AQ19: =AQ18+AQ17 -> 13636.958
G20: HPP 1 RESEP | H20: =SUM(H16:H18) -> 13042.263
A21: BIANG TEH POCI KUNING | D21: P.ATAS | G21: HPP 1 PORSI | H21: =H20/20 -> 652.11316
A22: 40 GR POCI KUNING | B22: ='WEEKLY FC'!E110 -> 2814 | D22: 1 PCS P.ATAS | E22: ='WEEKLY FC'!E13 -> 5949.6103 | J22: PAKET ROCKET KELAS 3 & 2 KALBAR | Z22: PAKET SEHAT KELAS 3 & 2 KALBAR | AJ22: PAKET CATT KELAS 2,3&4 SULAWESI | AS22: PAKET SEGAR KELAS 2,3&4 SULAWESI STEE
A23: 4 LITER AIR | B23: =B9*4 -> 1052.6316 | D23: MARINADE | E23: =E10 -> 198.94203 | G23: SAOS LEVEL 1 & 2 | X23: OKE | AH23: OKE | AR23: OKE | BG23: OKE
D24: TEPUNG CAKRA | E24: =E11 -> 327.705 | G24: LEVEL(500 GR ) | H24: ='WEEKLY FC'!E336 -> 37296
A25: HPP 1 RESEP | B25: =SUM(B22:B24) -> 3866.6316 | D25: TEPUNG BRIDER | E25: =E12 -> 234.1 | G25: AIR (1.900 ML ) | H25: =B9*1.95 -> 513.15789 | J25: PAKET | L25: PAKET | N25: PAKET | P25: PAKET | R25: PAKET | T25: PAKET | V25: PAKET | Z25: PAKET | AB25: PAKET | AD25: PAKET | AF25: PAKET | AJ25: PAKET | AL25: PAKET | AN25: PAKET | AP25: PAKET | AS25: PAKET | AU25: PAKET | AW25: PAKET | AY25: PAKET | BA25: PAKET | BC25: PAKET | BE25: PAKET
A26: HPP 1 PORSI | B26: =B25/16 -> 241.66447 | D26: MINYAK | E26: =E13 -> 606.10227 | J26: ROCKET 1 | L26: ROCKET 2 | N26: ROCKET 3 | P26: ROCKET 4 | R26: ROCKET 5 | T26: ROCKET 6 | V26: ROCKET 7 | Z26: SEHAT 1 | AB26: SEHAT 2 | AD26: SEHAT 3 | AF26: SEHAT 4 | AJ26: CATT 1 | AL26: CATT 2 | AN26: CATT 3 | AP26: CATT 4 | AS26: SEGAR 1 | AU26: SEGAR 2 | AW26: SEGAR 3 | AY26: SEGAR 4 | BA26: SEGAR 5 | BC26: SEGAR 6 | BE26: SEGAR 7
D27: AIR | E27: =E14 -> 2.3026316 | G27: HPP 1 RESEP | H27: =SUM(H24:H26) -> 37809.158 | J27: NASI | K27: =H61 -> 1301.4354 | L27: NASI | M27: =K27 -> 1301.4354 | N27: BURGER | O27: =H151 -> 8484.1367 | P27: NASI | Q27: =K27 -> 1301.4354 | R27: PEMBUNGKUS | S27: =S13 -> 1450.5 | T27: NASI | U27: =K27 -> 1301.4354 | V27: NASI | W27: =K27 -> 1301.4354 | Z27: NASI | AA27: =W27 -> 1301.4354 | AD27: NASI | AE27: =AA27 -> 1301.4354 | AF27: NASI | AG27: =AA27 -> 1301.4354 | AJ27: NASI | AK27: =AG27 -> 1301.4354 | AL27: NASI | AM27: =AK27 -> 1301.4354 | AN27: NASI | AO27: =AM27 -> 1301.4354 | AP27: NASI | AQ27: =AK27 -> 1301.4354 | AS27: NASI | AT27: =K13 -> 954.38596 | AU27: NASI | AV27: =M13 -> 954.38596 | AW27: BURGER | AX27: =O13 -> 8292.1367 | AY27: NASI | AZ27: =Q13 -> 954.38596 | BA27: PEMBUNGKUS | BB27: =S13 -> 1450.5 | BC27: NASI | BD27: =U13 -> 954.38596 | BE27: NASI | BF27: =W13 -> 954.38596
A28: BIANG TEH POCI VANILA | D28: SAOS SASET | E28: =E15 -> 407 | G28: HPP 1 PORSI | H28: =H27/60 -> 630.15263 | J28: SAYAP | K28: =E56 -> 6105.4354 | L28: C.STEAK | M28: =M14 -> 8145.877 | N28: NESTLE | O28: =K29 -> 1657.4478 | P28: P.BAWAH | Q28: =Q14 -> 5695.1162 | R28: NASGOR | S28: =S14 -> 5769.6704 | T28: C.STRIP | U28: =U14 -> 5472.3985 | V28: DADA / PA | W28: =E30 -> 7746.7072 | Z28: SAYAP | AA28: =K28 -> 6105.4354 | AB28: BURGER | AC28: =O27 -> 8484.1367 | AD28: DADA | AE28: =W28 -> 7746.7072 | AF28: C.STRIP | AG28: =U28 -> 5472.3985 | AJ28: SAYAP/PB | AK28: =AA28 -> 6105.4354 | AL28: DADA/PA | AM28: =AE28 -> 7746.7072 | AN28: SAYAP/PB | AO28: =AK28 -> 6105.4354 | AP28: DADA/PA | AQ28: =AM28 -> 7746.7072 | AS28: SAYAP | AT28: =K14 -> 6105.4354 | AU28: C.STEAK | AV28: =M14 -> 8145.877 | AW28: STEE | AX28: =AV29 -> 3500 | AY28: P.BAWAH | AZ28: =Q14 -> 5695.1162 | BA28: NASGOR | BB28: =S14 -> 5769.6704 | BC28: C.STRIP | BD28: =U14 -> 5472.3985 | BE28: DADA / PA | BF28: =W14 -> 9182.82
D29: BIANG BRIDER | E29: =E16 -> 20.945 | J29: NESTLE | K29: =B45 -> 1657.4478 | L29: NESTLE | M29: =K29 -> 1657.4478 | N29: PEMBUNGKUS | O29: =O15 -> 1130 | P29: NESTLE | Q29: =K29 -> 1657.4478 | R29: NESTLE | S29: =Q29 -> 1657.4478 | T29: NESTEA | U29: =K29 -> 1657.4478 | V29: NESTEA | W29: =U29 -> 1657.4478 | Z29: MILO | AA29: =B70 -> 3136.7994 | AB29: MILO | AC29: =AA29 -> 3136.7994 | AD29: MILO | AE29: =AC29 -> 3136.7994 | AF29: MILO | AG29: =AA29 -> 3136.7994 | AN29: AMB | AO29: ='WEEKLY FC'!E119 -> 3500 | AP29: AMB | AQ29: =AO29 -> 3500 | AS29: STEE | AT29: =AT14 -> 3500 | AU29: STEE | AV29: =AT29 -> 3500 | AW29: PEMBUNGKUS | AX29: =O15 -> 1130 | AY29: STEE | AZ29: =AX28 -> 3500 | BA29: STEE | BB29: =AZ29 -> 3500 | BC29: STEE | BD29: =BB29 -> 3500 | BE29: STEE | BF29: =BD29 -> 3500
A30: 50 GR POCI VANILA | B30: ='WEEKLY FC'!E110 -> 2814 | D30: HPP P.ATAS | E30: =SUM(E22:E29) -> 7746.7072 | J30: PEMBUNGKUS | K30: =E204 -> 1555.36 | L30: PEMBUNGKUS | M30: =K30 -> 1555.36 | P30: PEMBUNGKUS | Q30: =K30 -> 1555.36 | T30: PEMBUNGKUS | U30: =K30 -> 1555.36 | V30: PEMBUNGKUS | W30: =U30 -> 1555.36 | Z30: PEMBUNGKUS | AA30: =W31 -> 10705.59 | AB30: PEMBUNGKUS | AC30: =O29 -> 1130 | AD30: PEMBUNGKUS | AE30: =AA30 -> 10705.59 | AF30: PEMBUNGKUS | AG30: =AA30 -> 10705.59 | AJ30: PEMBUNGKUS | AK30: =SUM(E198:E199)+E203 -> 1135.36 | AL30: PEMBUNGKUS | AM30: =AK30 -> 1135.36 | AN30: PEMBUNGKUS | AO30: =AM30 -> 1135.36 | AP30: PEMBUNGKUS | AQ30: =AO30 -> 1135.36 | AS30: PEMBUNGKUS | AT30: =K16 -> 1555.36 | AU30: PEMBUNGKUS | AV30: =M16 -> 1555.36 | AY30: PEMBUNGKUS | AZ30: =Q16 -> 1555.36 | BA30: HPP NON CVR | BB30: =BB27+BB28 -> 7220.1704 | BC30: PEMBUNGKUS | BD30: =U16 -> 1555.36 | BE30: PEMBUNGKUS | BF30: =W16 -> 1555.36
A31: 8000 ML AIR | B31: =B9*8 -> 2105.2632 | G31: BUTTER MIX | J31: HPP NON CVR | K31: =SUM(K27:K30) -> 10619.679 | L31: HPP NON CVR | M31: =SUM(M27:M29) -> 11104.76 | N31: HPP NON CVR | O31: =O27+O28 -> 10141.584 | P31: HPP NON CVR | Q31: =SUM(Q27:Q29) -> 8653.9994 | R31: HPP NON CVR | S31: =S28+S29 -> 7427.1181 | T31: HPP NON CVR | U31: =SUM(U27:U29) -> 8431.2817 | V31: HPP NON CVR | W31: =SUM(W27:W29) -> 10705.59 | Z31: HPP NON CVR | AA31: =SUM(AA27:AA29) -> 10543.67 | AB31: HPP NON CVR | AC31: =AC28+AC29 -> 11620.936 | AD31: HPP NON CVR | AE31: =SUM(AE27:AE29) -> 12184.942 | AF31: HPP NON CVR | AG31: =SUM(AG27:AG29) -> 9910.6333 | AJ31: HPP NON CVR | AK31: =AK27+AK28 -> 7406.8708 | AL31: HPP NON CVR | AM31: =AM27+AM28 -> 9048.1426 | AN31: HPP NON CVR | AO31: =AO27+AO28+AO29 -> 10906.871 | AP31: HPP NON CVR | AQ31: =AQ27+AQ28+AQ29 -> 12548.143 | AS31: HPP NON CVR | AT31: =SUM(AT27:AT29) -> 10559.821 | AU31: HPP NON CVR | AV31: =SUM(AV27:AV29) -> 12600.263 | AW31: HPP NON CVR | AX31: =AX27+AX28 -> 11792.137 | AY31: HPP NON CVR | AZ31: =SUM(AZ27:AZ29) -> 10149.502 | BA31: HPP + COVER | BB31: =BB30+BB29 -> 10720.17 | BC31: HPP NON CVR | BD31: =SUM(BD27:BD29) -> 9926.7844 | BE31: HPP NON CVR | BF31: =SUM(BF27:BF29) -> 13637.206
G32: 1 PCK BUTTER MIX ( 125 GR ) | H32: ='WEEKLY FC'!E326 -> 8547 | J32: HPP + COVER | K32: =K30+K31 -> 12175.039 | L32: HPP + COVER | M32: =M31+M30 -> 12660.12 | N32: HPP + COVER | O32: =O31+O29 -> 11271.584 | P32: HPP + COVER | Q32: =Q31+Q30 -> 10209.359 | R32: HPP + COVER | S32: =S31+S27 -> 8877.6181 | T32: HPP + COVER | U32: =U31+U30 -> 9986.6417 | V32: HPP + COVER | W32: =W31+W30 -> 12260.95 | Z32: HPP + COVER | AA32: =AA31+AA30 -> 21249.261 | AB32: HPP + COVER | AC32: =AC31+AC30 -> 12750.936 | AD32: HPP + COVER | AE32: =AE31+AE30 -> 22890.532 | AF32: HPP + COVER | AG32: =AG31+AG30 -> 20616.224 | AJ32: HPP + COVER | AK32: =AK31+AK30 -> 8542.2308 | AL32: HPP + COVER | AM32: =AM31+AM30 -> 10183.503 | AN32: HPP + COVER | AO32: =AO31+AO30 -> 12042.231 | AP32: HPP + COVER | AQ32: =AQ31+AQ30 -> 13683.503 | AS32: HPP + COVER | AT32: =AT30+AT31 -> 12115.181 | AU32: HPP + COVER | AV32: =AV31+AV30 -> 14155.623 | AW32: HPP + COVER | AX32: =AX31+AX29 -> 12922.137 | AY32: HPP + COVER | AZ32: =AZ31+AZ30 -> 11704.862 | BC32: HPP + COVER | BD32: =BD31+BD30 -> 11482.144 | BE32: HPP + COVER | BF32: =BF31+BF30 -> 15192.566
A33: HPP 1 RESEP | B33: =SUM(B30:B32) -> 4919.2632 | G33: TEPUNG CAKRA ( 375 GR ) | H33: ='WEEKLY FC'!E331*0.375 -> 3511.125
A34: HPP 1 PORSI | B34: =B33/36 -> 136.6462 | D34: P.BAWAH | G34: AIR (750 ML ) | H34: =B9*0.75 -> 197.36842
D35: 1 PCS P. BAWAH | E35: ='WEEKLY FC'!E14 -> 3898.0192 | G35: KUNING TELUR (4 BUTIR) | H35: ='WEEKLY FC'!E320*4 -> 7468
A36: NESTEA | D36: MARINADE | E36: =E23 -> 198.94203 | H36: =H32+H33+H34+H35 -> 19723.493 | J36: PAKET ROMA KELAS 2,3&4 SULAWESI | V36: PAKET HOT CHESE ES THE KELAS 2,3&4 SULAWESI | AD36: PAKET AYAM UTUH KELAS 2,3&4 SULAWESI | AL36: PAKET BUCKET KELAS 2,3&4 SULAWESI | AU36: PAKET GEPREK STEE KELAS 3 & 4 SULAWESI
A37: 1 PACK / 1KG NESTEA | B37: ='WEEKLY FC'!E102 -> 54570 | D37: TEPUNG CAKRA | E37: =E24 -> 327.705 | G37: HPP 15 PORSI | H37: =SUM(H32:H35)/15 -> 1314.8996 | T37: OKE | AB37: OKE | AJ37: OKE | AT37: OKE | BM37: OKE
A38: 9LITER AIR | B38: =B9*9 -> 2368.4211 | D38: TEPUNG BRIDER | E38: =E25 -> 234.1 | G38: HPP 20 PORSI | H38: =SUM(H32:H35)/20 -> 986.17467
A39: 500 ML SIMPLE SIRUP | B39: =B18*0.5 -> 5954.386 | D39: MINYAK | E39: =E26 -> 606.10227 | G39: HPP 30 PORSI | H39: =SUM(H32:H35)/30 -> 657.44978 | J39: PAKET | L39: PAKET | N39: PAKET | P39: PAKET | R39: PAKET | V39: PAKET | X39: PAKET | Z39: PAKET | AD39: PAKET | AF39: PAKET | AH39: PAKET | AL39: PAKET | AN39: PAKET | AP39: PAKET | AR39: PAKET
D40: AIR | E40: =E27 -> 2.3026316 | J40: ROMA 1 | L40: ROMA 2 | N40: ROMA 3 | P40: ROMA 4 | R40: ROMA 5 | V40: LEVEL 1 | X40: LEVEL 2 | Z40: LEVEL 3 | AD40: AYAM UTUH ORI | AF40: AYAM UTUH GEPREK | AH40: AYAM UTUH LEVEL | AL40: BUCKET 1 | AN40: BUCKET 2 | AP40: BUCKET 3 | AR40: BUCKET 4 | AU40: PAKET | AW40: PAKET | AY40: PAKET | BA40: PAKET | BC40: PAKET | BE40: PAKET | BG40: PAKET | BI40: PAKET | BK40: PAKET
D41: SAOS SASET | E41: =E28 -> 407 | J41: NASGOR | K41: =H90 -> 5769.6704 | L41: NASI | M41: =H61 -> 1301.4354 | N41: NASI | O41: =K41 -> 5769.6704 | P41: NASI | Q41: =O41 -> 5769.6704 | R41: NASI | S41: =Q41 -> 5769.6704 | V41: NASI | W41: =W27 -> 1301.4354 | X41: NASI | Y41: =W41 -> 1301.4354 | Z41: NASI | AA41: =Y41 -> 1301.4354 | AD41: AYAM UTUH | AE41: =B250 -> 41186.464 | AF41: AYAM UTUH | AG41: =AE41 -> 41186.464 | AH41: AYAM UTUH | AI41: =AG41 -> 41186.464 | AL41: 4 PCS DADA/ P ATAS | AM41: =E17*4 -> 36731.28 | AN41: 4 PCS DADA/ P ATAS | AO41: =AM41 -> 36731.28 | AP41: AYAM UTUH | AQ41: =AE41+AE43+AE44 -> 44442.464 | AR41: AYAM UTUH | AS41: =AE41 -> 41186.464 | AU41: GEPREK 1 | AW41: GEPREK 2 | AY41: GEPREK 3 | BA41: MATAH 1 | BC41: MATAH 2 | BE41: MATAH 3 | BG41: TERASI 1 | BI41: TERASI 2 | BK41: TERASI 3
A42: HPP 1 RESEP | B42: =SUM(B37:B40) -> 62892.807 | D42: BIANG BRIDER | E42: =E16 -> 20.945 | G42: SAMBAL KOSEK | J42: TEH BOTOL | K42: ='WEEKLY FC'!E94 -> 2167 | L42: P.BAWAH | M42: =E43 -> 5695.1162 | N42: C.STEAK | O42: =E75 -> 8145.877 | P42: DADA/ PA | Q42: =E17 -> 9182.82 | R42: C.STRIP | S42: =E111 -> 5472.3985 | V42: SAYAP | W42: =E57 -> 5698.4354 | X42: P.BAWAH | Y42: =E44 -> 5288.1162 | Z42: DADA/PA | AA42: =E18 -> 8775.82 | AD42: NASI | AE42: =AA41*4 -> 5205.7416 | AF42: NASI | AG42: =AE42 -> 5205.7416 | AH42: NASI | AI42: =AG42 -> 5205.7416 | AL42: 4 PCS SAYAP/ P BAWAH | AM42: =E43*4 -> 22780.465 | AN42: 4 PCS SAYAP/ P BAWAH | AO42: =AM42 -> 22780.465 | AR42: SAMBAL KOSEK | AS42: =AG44 -> 4487.488 | AU42: NASI | AV42: =AA13 -> 954.38596 | AW42: NASI | AX42: =AC13 -> 954.38596 | AY42: NASI | AZ42: =AE13 -> 954.38596 | BA42: NASI | BB42: =AG13 -> 954.38596 | BC42: NASI | BD42: =AI13 -> 954.38596 | BE42: NASI | BF42: =AK13 -> 954.38596 | BG42: NASI | BH42: =AM13 -> 954.38596 | BI42: NASI | BJ42: =AO13 -> 954.38596 | BK42: NASI | BL42: =AQ13 -> 954.38596
A43: HPP 1 PORSI | B43: =B42/42 -> 1497.4478 | D43: HPP P.BAWAH | E43: =SUM(E35:E42) -> 5695.1162 | J43: PEMBUNGKUS | K43: =E186 -> 1450.5 | L43: TEH BOTOL | M43: =K42 -> 2167 | N43: TEH BOTOL | O43: =M43 -> 2167 | P43: TEH BOTOL | Q43: =O43 -> 2167 | R43: TEH BOTOL | S43: =Q43 -> 2167 | V43: ES THE | W43: =K15 -> 878.01535 | X43: ES THE | Y43: =W43 -> 878.01535 | Z43: ES THE | AA43: =Y43 -> 878.01535 | AD43: SAMBAL SASET | AE43: ='WEEKLY FC'!E334*8 -> 1608 | AF43: NESTEA | AG43: =AE45 -> 6629.7911 | AN43: 9 PCS STRIP | AO43: =E111*3 -> 16417.195 | AR43: LEVEL | AS43: =AI46 -> 6411.3289 | AU43: SAYAP | AV43: =AA14 -> 5698.4354 | AW43: P.BAWAH | AX43: =AC14 -> 5288.1162 | AY43: DADA | AZ43: =AE14 -> 8775.82 | BA43: SAYAP GPRK | BB43: =AG14 -> 5698.4354 | BC43: P.BAWAH | BD43: =AI14 -> 5288.1162 | BE43: DADA/PA | BF43: =AK14 -> 8775.82 | BG43: SAYAP | BH43: =AM14 -> 5698.4354 | BI43: P.BAWAH | BJ43: =AO14 -> 5288.1162 | BK43: DADA/PA | BL43: =AQ14 -> 8775.82
A44: ES BATU | B44: =('WEEKLY FC'!E78/10)*0.1 -> 160 | D44: HPP P.BAWAH U/GPRK & LVL | E44: =E43-E41 -> 5288.1162 | G44: RAWIT HIJAU ( 500 GR ) | H44: ='WEEKLY FC'!E322*0.5 -> 0 | L44: PEMBUNGKUS | M44: =K30 -> 1555.36 | N44: PEMBUNGKUS | O44: =E204 -> 1555.36 | P44: PEMBUNGKUS | Q44: =M44 -> 1555.36 | R44: PEMBUNGKUS | S44: =Q44 -> 1555.36 | V44: C LEVEL + CM | W44: =E210 -> 1282.2658 | X44: C LEVEL + CM | Y44: =W44 -> 1282.2658 | Z44: C LEVEL + CM | AA44: =Y44 -> 1282.2658 | AD44: SAMBAL TOMAT | AE44: ='WEEKLY FC'!E335*8 -> 1648 | AF44: SAMBAL KOSEK | AG44: =H51*5 -> 4487.488 | AN44: 12 PCS STRIP | AO44: =E94 -> 7032.0772 | AU44: STEE | AV44: =AT29 -> 3500 | AW44: STEE | AX44: =AV44 -> 3500 | AY44: STEE | AZ44: =AX44 -> 3500 | BA44: STEE | BB44: =AZ44 -> 3500 | BC44: STEE | BD44: =BB44 -> 3500 | BE44: STEE | BF44: =BD44 -> 3500 | BG44: STEE | BH44: =BF44 -> 3500 | BI44: STEE | BJ44: =BH44 -> 3500 | BK44: STEE | BL44: =BJ44 -> 3500
A45: HPP 1 PORSI LEMON TEA | B45: =SUM(B43:B44) -> 1657.4478 | G45: RAWIT MERAH( 500 GR ) | H45: ='WEEKLY FC'!E321*0.5 -> 30000 | L45: HPP NON CVR | M45: =SUM(M41:M43) -> 9163.5516 | N45: HPP NON CVR | O45: =SUM(O41:O43) -> 16082.547 | P45: HPP NON CVR | Q45: =SUM(Q41:Q43) -> 17119.49 | R45: HPP NON CVR | S45: =SUM(S41:S43) -> 13409.069 | V45: PEMBUNGKUS | W45: =E159 -> 2003.36 | X45: PEMBUNGKUS | Y45: =W45 -> 2003.36 | Z45: PEMBUNGKUS | AA45: =Y45 -> 2003.36 | AD45: NESTEA | AE45: =B45*4 -> 6629.7911 | AF45: SAMBAL MATAH | AG45: =E135*5 -> 8432.4266 | AH45: NESTEA | AI45: =AG43 -> 6629.7911 | AL45: PEMBUNGKUS | AM45: ='WEEKLY FC'!E159 -> 100 | AN45: PEMBUNGKUS | AO45: =AM45 -> 100 | AP45: PEMBUNGKUS | AQ45: =AO45 -> 100 | AR45: PEMBUNGKUS | AS45: =AQ45 -> 100 | AU45: GPRK | AV45: =AA16 -> 897.4976 | AW45: GPRK | AX45: =AC16 -> 897.4976 | AY45: GPRK | AZ45: =AE16 -> 897.4976 | BA45: MATAH | BB45: =AG16 -> 1686.4853 | BC45: MATAH | BD45: =AI16 -> 1686.4853 | BE45: MATAH | BF45: =BD45 -> 1686.4853 | BG45: TRASI | BH45: =AM16 -> 1473.3767 | BI45: TRASI | BJ45: =AO16 -> 1473.3767 | BK45: TRASI | BL45: =AQ16 -> 1473.3767
G46: BAWANG PUTIH (100 GR ) | H46: ='WEEKLY FC'!E302*0.1 -> 5200 | J46: HPP NON CVR | K46: =SUM(K41:K42) -> 7936.6704 | L46: HPP + COVER | M46: =M45+M44 -> 10718.912 | N46: HPP + COVER | O46: =O45+O44 -> 17637.907 | P46: HPP + COVER | Q46: =Q45+Q44 -> 18674.85 | R46: HPP + COVER | S46: =S45+S44 -> 14964.429 | V46: HPP NON CVR | W46: =SUM(W41:W44) -> 9160.1519 | X46: HPP NON CVR | Y46: =SUM(Y41:Y44) -> 8749.8327 | Z46: HPP NON CVR | AA46: =SUM(AA41:AA44) -> 12237.537 | AH46: LEVEL | AI46: =E210*5 -> 6411.3289 | AL46: HPP NON CVR | AM46: =SUM(AM41:AM44) -> 59511.745 | AN46: HPP NON CVR 3 | AO46: =SUM(AO41:AO43) -> 75928.94 | AP46: HPP NON CVR | AQ46: =AQ41 -> 44442.464 | AR46: HPP NON CVR GPRK | AS46: =SUM(AS41:AS44) -> 52085.28 | AU46: PEMBUNGKUS | AV46: =AA17 -> 1555.36 | AW46: PEMBUNGKUS | AX46: =AC17 -> 1555.36 | AY46: PEMBUNGKUS | AZ46: =AE17 -> 1555.36 | BA46: PEMBUNGKUS | BB46: =AG17 -> 1555.36 | BC46: PEMBUNGKUS | BD46: =AI17 -> 1555.36 | BE46: PEMBUNGKUS | BF46: =BD46 -> 1555.36 | BG46: PEMBUNGKUS | BH46: =AM17 -> 1555.36 | BI46: PEMBUNGKUS | BJ46: =AO17 -> 1555.36 | BK46: PEMBUNGKUS | BL46: =AQ17 -> 1555.36
D47: SAYAP | G47: 1 PACK PREMIX KOSEK ( 60 GR ) | H47: ='WEEKLY FC'!E340 -> 1887 | J47: HPP + COVER | K47: =K46+K43 -> 9387.1704 | V47: HPP + COVER | W47: =W46+W45 -> 11163.512 | X47: HPP + COVER | Y47: =Y46+Y45 -> 10753.193 | Z47: HPP + COVER | AA47: =AA46+AA45 -> 14240.897 | AD47: PEMBUNGKUS | AE47: =E195-E191 -> 6442 | AF47: HPP NON CVR GPRK | AG47: =SUM(AG41:AG44) -> 57509.484 | AH47: HPP NON CVR | AI47: =SUM(AI41:AI46) -> 59433.325 | AL47: HPP + COVER | AM47: =AM46+AM45 -> 59611.745 | AN47: HPP NON CVR 2 | AO47: =AO41+AO42+AO44 -> 66543.822 | AP47: HPP + COVER | AQ47: =AQ46+AQ45 -> 44542.464 | AR47: HPP NON LEVEL | AS47: =AS41+AS43 -> 47597.793 | AU47: HPP NON CVR | AV47: =SUM(AV42:AV45) -> 11050.319 | AW47: HPP NON CVR | AX47: =SUM(AX42:AX45) -> 10640 | AY47: HPP NON CVR | AZ47: =SUM(AZ42:AZ45) -> 14127.704 | BA47: HPP NON CVR | BB47: =SUM(BB42:BB45) -> 11839.307 | BC47: HPP NON CVR | BD47: =SUM(BD42:BD45) -> 11428.987 | BE47: HPP NON CVR | BF47: =SUM(BF42:BF45) -> 14916.691 | BG47: HPP NON CVR | BH47: =SUM(BH42:BH45) -> 11626.198 | BI47: HPP NON CVR | BJ47: =SUM(BJ42:BJ45) -> 11215.879 | BK47: HPP NON CVR | BL47: =SUM(BL42:BL45) -> 14703.583
D48: 1 PCS SAYAP | E48: ='WEEKLY FC'!E15 -> 4308.3385 | G48: MINYAK (250 ML ) | H48: ='WEEKLY FC'!E168*0.25 -> 5000.3438 | AD48: HPP NON CVR | AE48: =SUM(AE41:AE45) -> 56277.996 | AF48: HPP NON CVR MTH | AG48: =SUM(AG41:AG43)+AG45 -> 61454.423 | AH48: HPP + COVER | AI48: =AI47+E195 -> 66415.325 | AN48: HPP + COVER | AO48: =AO46+AO45 -> 76028.94 | AR48: HPP + COVER | AS48: =AS47+AS45 -> 47697.793 | AU48: HPP + COVER | AV48: =AV47+AV46 -> 12605.679 | AW48: HPP + COVER | AX48: =AX47+AX46 -> 12195.36 | AY48: HPP + COVER | AZ48: =+AZ47+AZ46 -> 15683.064 | BA48: HPP + COVER | BB48: =BB47+BB46 -> 13394.667 | BC48: HPP + COVER | BD48: =BD47+BD46 -> 12984.347 | BE48: HPP + COVER | BF48: =BF46+BF47 -> 16472.051 | BG48: HPP + COVER | BH48: =BH47+BH46 -> 13181.558 | BI48: HPP + COVER | BJ48: =BJ47+BJ46 -> 12771.239 | BK48: HPP + COVER | BL48: =BL47+BL46 -> 16258.943
A49: TAKE AWAY | D49: MARINADE | E49: =E36 -> 198.94203 | AD49: HPP + COVER | AE49: =AE48+AE47 -> 62719.996 | AF49: HPP + COVER | AG49: =AG48+E195 -> 68436.423
A50: NESTEA | B50: =B45 -> 1657.4478 | D50: TEPUNG CAKRA | E50: =E37 -> 327.705 | G50: HPP 1 RESEP | H50: =SUM(H44:H48) -> 42087.344 | J50: PAKET GREEN CRISPY KELAS 2,3&4 SULAWESI
A51: CUP MINUMAN | B51: ='WEEKLY FC'!E144 -> 373 | D51: TEPUNG BRIDER | E51: =E38 -> 234.1 | G51: HPP 1 PORSI+TIMUN | H51: =H50/65+250 -> 897.4976 | V51: OKE
A52: SEALER | B52: ='WEEKLY FC'!E140/1000 -> 72.15 | D52: MINYAK | E52: =E39 -> 606.10227
A53: SEDOTAN | B53: ='WEEKLY FC'!E131/500 -> 47 | D53: AIR | E53: =E40 -> 2.3026316 | X53: PAKET ROCKET KELAS 2 & 4 SULAWESI | AS53: PAKET SEGAR KELAS 2,3&4 SULAWESI TEEH RC
D54: SAOS SASET | E54: =E41 -> 407 | J54: PAKET | L54: PAKET | N54: PAKET | P54: PAKET | R54: PAKET | T54: PAKET | AR54: OKE | BG54: OKE
D55: BIANG BRIDER | E55: =E16 -> 20.945 | G55: NASI PUTIH | J55: LEVEL 1 | L55: LEVEL 2 | N55: LEVEL 3 | P55: HOT SPICY 1 | R55: HOT SPICY 2 | T55: HOT SPICY 3
A56: HPP LEMON TEA TAKE AWAY | B56: =SUM(B50:B55) -> 2149.5978 | D56: HPP SAYAP | E56: =SUM(E48:E55) -> 6105.4354 | G56: BERAS ( 1 KG ) | H56: ='WEEKLY FC'!E34 -> 14000 | J56: NASI | K56: =M41 -> 1301.4354 | L56: NASI | M56: =K56 -> 1301.4354 | N56: NASI | O56: =M56 -> 1301.4354 | P56: NASI | Q56: =O56 -> 1301.4354 | R56: NASI | S56: =Q56 -> 1301.4354 | T56: NASI | U56: =S56 -> 1301.4354 | X56: PAKET | Z56: PAKET | AB56: PAKET | AD56: PAKET | AF56: PAKET | AH56: PAKET | AJ56: PAKET | AL56: PAKET | AN56: PAKET | AP56: PAKET | AS56: PAKET | AU56: PAKET | AW56: PAKET | AY56: PAKET | BA56: PAKET | BC56: PAKET | BE56: PAKET
D57: HPP SAYAP U/GPRK & LVL | E57: =E56-E54 -> 5698.4354 | G57: AIR (1200 ML) | H57: =B9*1.2 -> 315.78947 | J57: SAYAP | K57: =E57 -> 5698.4354 | L57: P.BAWAH | M57: =E44 -> 5288.1162 | N57: DADA/ PA | O57: =E18 -> 8775.82 | P57: SAYAP SPICY | Q57: =B275 -> 6913.9612 | R57: P.BAWAH SPICY | S57: =B274 -> 6503.6419 | T57: DADA/ PA SPICY | U57: =B272 -> 10031.679 | X57: ROCKET 1 | Z57: ROCKET 2 | AB57: ROCKET 3 | AD57: ROCKET 4 | AF57: ROCKET 5 | AH57: ROCKET 6 | AJ57: ROCKET 7 | AL57: ROCKET 8 | AN57: ROCKET 9 | AP57: ROCKET 10 | AS57: SEGAR 1 | AU57: SEGAR 2 | AW57: SEGAR 3 | AY57: SEGAR 4 | BA57: SEGAR 5 | BC57: SEGAR 6 | BE57: SEGAR 7
G58: HPP 1 RESEP | H58: =SUM(H56:H57) -> 14315.789 | J58: ES THE/STEE | K58: ='WEEKLY FC'!E115 -> 1583.97 | L58: ES THE/STEE | M58: =K58 -> 1583.97 | N58: ES THE/STEE | O58: =M58 -> 1583.97 | P58: ES THE/STEE | Q58: =O58 -> 1583.97 | R58: ES THE/STEE | S58: =Q58 -> 1583.97 | T58: ES THE/STEE | U58: =S58 -> 1583.97 | X58: NASI | Y58: =U56 -> 1301.4354 | Z58: NASI | AA58: =Y58 -> 1301.4354 | AB58: DADA / PA | AC58: =E30 -> 7746.7072 | AD58: NASGOR | AE58: =K41 -> 5769.6704 | AF58: PEMBUNGKUS | AG58: =Y61 -> 1555.36 | AH58: BURGER | AI58: =O27 -> 8484.1367 | AJ58: NASI | AK58: =Y58 -> 1301.4354 | AL58: PEMBUNGKUS | AM58: =O44 -> 1555.36 | AN58: NASI | AO58: =AM60 -> 1301.4354 | AP58: C.STRIP | AQ58: =AG59 -> 7032.0772 | AS58: NASI | AT58: =AT27 -> 954.38596 | AU58: NASI | AV58: =AV27 -> 954.38596 | AW58: BURGER | AX58: =AX27 -> 8292.1367 | AY58: NASI | AZ58: =AZ27 -> 954.38596 | BA58: PEMBUNGKUS | BB58: =BB27 -> 1450.5 | BC58: NASI | BD58: =BD27 -> 954.38596 | BE58: NASI | BF58: =BF27 -> 954.38596
J59: C LEVEL + CM | K59: =E210 -> 1282.2658 | L59: C LEVEL + CM | M59: =K59 -> 1282.2658 | N59: C LEVEL + CM | O59: =M59 -> 1282.2658 | P59: GREEN CRISPY | Q59: =O59 -> 1282.2658 | R59: GREEN CRISPY | S59: =Q59 -> 1282.2658 | T59: GREEN CRISPY | U59: =S59 -> 1282.2658 | X59: SAYAP | Y59: =E56 -> 6105.4354 | Z59: C.STEAK | AA59: =E43 -> 5695.1162 | AB59: NESTLE | AC59: =AA60 -> 1657.4478 | AF59: C.STRIP | AG59: =E94 -> 7032.0772 | AH59: MILO | AI59: =B70 -> 3136.7994 | AJ59: P.BAWAH | AK59: =Q28 -> 5695.1162 | AL59: C.STEAK | AM59: =M28 -> 8145.877 | AN59: DADA / PA | AO59: =AC58 -> 7746.7072 | AP59: FF | AQ59: =H72 -> 3872.1023 | AS59: SAYAP | AT59: =AT28 -> 6105.4354 | AU59: C.STEAK | AV59: =AV28 -> 8145.877 | AW59: TEEH RC | AX59: =AV60 -> 219.21053 | AY59: P.BAWAH | AZ59: =AZ28 -> 5695.1162 | BA59: NASGOR | BB59: =BB28 -> 5769.6704 | BC59: C.STRIP | BD59: =BD28 -> 5472.3985 | BE59: DADA / PA | BF59: =BF28 -> 9182.82
J60: GREEN CRISPY | K60: =B286 -> 250.01719 | L60: GREEN CRISPY | M60: =K60 -> 250.01719 | N60: GREEN CRISPY | O60: =M60 -> 250.01719 | R60: PEMBUNGKUS | S60: =Q61 -> 1555.36 | X60: NESTLE | Y60: =B45 -> 1657.4478 | Z60: NESTLE | AA60: =Y60 -> 1657.4478 | AB60: PEMBUNGKUS | AC60: =AA61 -> 1555.36 | AD60: NESTLE | AE60: =AC59 -> 1657.4478 | AF60: NESTLE | AG60: =AE60 -> 1657.4478 | AJ60: MILO | AK60: =AI59 -> 3136.7994 | AL60: NASI | AM60: =AK58 -> 1301.4354 | AN60: MILO | AO60: =AM61 -> 3136.7994 | AP60: MILO | AQ60: =AO60 -> 3136.7994 | AS60: TEEH RC | AT60: =B301 -> 219.21053 | AU60: TEEH RC | AV60: =AT60 -> 219.21053 | AW60: PEMBUNGKUS | AX60: =AX29 -> 1130 | AY60: TEEH RC | AZ60: =AX59 -> 219.21053 | BA60: TEEH RC | BB60: =AZ60 -> 219.21053 | BC60: TEEH RC | BD60: =BB60 -> 219.21053 | BE60: TEEH RC | BF60: =BD60 -> 219.21053
A61: MILO | G61: HPP 1 PORSI | H61: =H58/11 -> 1301.4354 | J61: PEMBUNGKUS | K61: =E159 -> 2003.36 | L61: PEMBUNGKUS | M61: =K61 -> 2003.36 | N61: PEMBUNGKUS | O61: =M61 -> 2003.36 | P61: PEMBUNGKUS | Q61: =E204 -> 1555.36 | R61: HPP NON CVR | S61: =SUM(S56:S59) -> 10671.313 | T61: PEMBUNGKUS | U61: =S60 -> 1555.36 | X61: PEMBUNGKUS | Y61: =E204 -> 1555.36 | Z61: PEMBUNGKUS | AA61: =Y61 -> 1555.36 | AB61: NASI | AC61: =AA58 -> 1301.4354 | AD61: PEMBUNGKUS | AE61: =K43 -> 1450.5 | AF61: NASI | AG61: =AC61 -> 1301.4354 | AH61: PEMBUNGKUS | AI61: =O29 -> 1130 | AJ61: PEMBUNGKUS | AK61: =AG58 -> 1555.36 | AL61: MILO | AM61: =AK60 -> 3136.7994 | AN61: PEMBUNGKUS | AO61: =AK61 -> 1555.36 | AP61: PEMBUNGKUS | AQ61: =SUM(E172:E176) -> 871 | AS61: PEMBUNGKUS | AT61: =AT30 -> 1555.36 | AU61: PEMBUNGKUS | AV61: =AV30 -> 1555.36 | AY61: PEMBUNGKUS | AZ61: =AZ30 -> 1555.36 | BA61: HPP NON CVR | BB61: =BB58+BB59 -> 7220.1704 | BC61: PEMBUNGKUS | BD61: =BD30 -> 1555.36 | BE61: PEMBUNGKUS | BF61: =BF30 -> 1555.36
A62: 1 PACK MILO ( 960 GR) | B62: ='WEEKLY FC'!E101 -> 97450 | D62: CHICKEN STEAK | J62: HPP NON CVR | K62: =SUM(K56:K60) -> 10116.124 | L62: HPP NON CVR | M62: =SUM(M56:M60) -> 9705.8045 | N62: HPP NON CVR | O62: =SUM(O56:O60) -> 13193.508 | P62: HPP NON CVR | Q62: =SUM(Q56:Q60) -> 11081.632 | R62: HPP + COVER | S62: =S61+S60 -> 12226.673 | T62: HPP NON CVR | U62: =SUM(U56:U60) -> 14199.35 | X62: HPP NON CVR | Y62: =SUM(Y58:Y60) -> 9064.3186 | Z62: HPP NON CVR | AA62: =SUM(AA58:AA60) -> 8653.9994 | AB62: HPP NON CVR | AC62: =AC58+AC59+AC61 -> 10705.59 | AD62: HPP NON CVR | AE62: =SUM(AE58:AE60) -> 7427.1181 | AF62: HPP NON CVR | AG62: =SUM(AG59:AG61) -> 9990.9604 | AH62: HPP NON CVR | AI62: =SUM(AI58:AI60) -> 11620.936 | AJ62: HPP NON CVR | AK62: =SUM(AK58:AK60) -> 10133.351 | AL62: HPP NON CVR | AM62: =SUM(AM59:AM61) -> 12584.112 | AN62: HPP NON CVR | AO62: =SUM(AO58:AO60) -> 12184.942 | AP62: HPP NON CVR | AQ62: =SUM(AQ58:AQ60) -> 14040.979 | AS62: HPP NON CVR | AT62: =SUM(AT58:AT60) -> 7279.0319 | AU62: HPP NON CVR | AV62: =SUM(AV58:AV60) -> 9319.4735 | AW62: HPP NON CVR | AX62: =AX58+AX59 -> 8511.3472 | AY62: HPP NON CVR | AZ62: =SUM(AZ58:AZ60) -> 6868.7127 | BA62: HPP + COVER | BB62: =BB61+BB58 -> 8670.6704 | BC62: HPP NON CVR | BD62: =SUM(BD58:BD60) -> 6645.995 | BE62: HPP NON CVR | BF62: =SUM(BF58:BF60) -> 10356.417
A63: AIR PANAS ( 1 LTR) | B63: =B9 -> 263.15789 | D63: MENTOK ( FILET 55 GR ) | E63: ='WEEKLY FC'!E11/2 -> 3077.3846 | G63: HPP 1 PORSI 150GR | H63: =H58/15 -> 954.38596 | J63: HPP + COVER | K63: =K62+K61 -> 12119.484 | L63: HPP + COVER | M63: =M62+M61 -> 11709.165 | N63: HPP + COVER | O63: =O62+O61 -> 15196.868 | P63: HPP + COVER | Q63: =Q62+Q61 -> 12636.992 | T63: HPP + COVER | U63: =U62+U61 -> 15754.71 | X63: HPP + COVER | Y63: =Y62+Y61 -> 10619.679 | Z63: HPP + COVER | AA63: =AA62+AA61 -> 10209.359 | AB63: HPP + COVER | AC63: =AC62+AC60 -> 12260.95 | AD63: HPP + COVER | AE63: =AE62+AE61 -> 8877.6181 | AF63: HPP + COVER | AG63: =AG62+AG58 -> 11546.32 | AH63: HPP + COVER | AI63: =AI62+AI61 -> 12750.936 | AJ63: HPP + COVER | AK63: =AK62+AK61 -> 11688.711 | AL63: HPP + COVER | AM63: =AM62+AM58 -> 14139.472 | AN63: HPP + COVER | AO63: =AO62+AO61 -> 13740.302 | AP63: HPP + COVER | AQ63: =AQ62+AQ61 -> 14911.979 | AS63: HPP + COVER | AT63: =AT62+AT61 -> 8834.3919 | AU63: HPP + COVER | AV63: =AV62+AV61 -> 10874.834 | AW63: HPP + COVER | AX63: =AX62+AX60 -> 9641.3472 | AY63: HPP + COVER | AZ63: =AZ62+AZ61 -> 8424.0727 | BC63: HPP + COVER | BD63: =BD62+BD61 -> 8201.355 | BE63: HPP + COVER | BF63: =BF62+BF61 -> 11911.777
A64: AIR DINGIN ( 6,5 LITER) | B64: =B9*6.5 -> 1710.5263 | D64: MARINADE | E64: =E10/2 -> 99.471014
A65: SIMPLE SIRUP ( 900 ML) | B65: =B18*0.9 -> 10717.895 | D65: TELOR | E65: ='WEEKLY FC'!E320/4 -> 466.75
D66: MINYAK | E66: =E52 -> 606.10227
A67: HPP 1 RESEP MILO | B67: =SUM(B62:B66) -> 110141.58 | D67: TEPUNG CAKRA (40 gr) | E67: ='WEEKLY FC'!E331/1000*40 -> 374.52 | G67: FRENCH FRIES
A68: HPP 1 PORSI | B68: =B67/37 -> 2976.7994 | G68: FRENCH FREIS( 100 GR ) | H68: ='WEEKLY FC'!E35*0.1 -> 2600 | J68: PAKET GEPREK KELAS 2 | AD68: MANRE 1 | AU68: PAKET GEPREK TEEH RC KELAS 3 & 4 SULAWESI
A69: ES BATU | B69: =B44 -> 160 | D69: 1 PCS CHICKEN STEAK | E69: =SUM(E63:E67) -> 4624.2279 | G69: MINYAK | H69: =E66 -> 606.10227 | AB69: OKE | AD69: NASI | AE69: =H63 -> 954.38596 | BM69: OKE
A70: HPP 1 PORSI ES MILO | B70: =SUM(B68:B69) -> 3136.7994 | D70: CRINKLE ( 4PCS / 35 GR ) | E70: =('WEEKLY FC'!E39/1000)*35 -> 1120 | G70: KERTAS FF | H70: ='WEEKLY FC'!E143 -> 259 | AD70: SAYAP/PB | AE70: =E330 -> 5067.0229
D71: MIX VEGETABLE( 30 gram ) | E71: ='WEEKLY FC'!E33*0.03 -> 900 | G71: SAOS SASET | H71: =E54 -> 407 | AD71: AMC | AE71: ='WEEKLY FC'!E100 -> 458
D72: 1 PORSI SAOS STEAK | E72: =H13 -> 1450.8158 | G72: HPP 1 PORSI | H72: =SUM(H68:H71) -> 3872.1023 | J72: PAKET | L72: PAKET | N72: PAKET | P72: PAKET | R72: PAKET | T72: PAKET | V72: PAKET | X72: PAKET | Z72: PAKET | AD72: PEMBUNGKUS | AE72: 943 | AU72: PAKET | AW72: PAKET | AY72: PAKET | BA72: PAKET | BC72: PAKET | BE72: PAKET | BG72: PAKET | BI72: PAKET | BK72: PAKET
D73: MARGARIN ( 5 gram ) | E73: ='WEEKLY FC'!E60/600*5 -> 50.833333 | J73: GEPREK 1 | L73: GEPREK 2 | N73: GEPREK 3 | P73: MATAH 1 | R73: MATAH 2 | T73: MATAH 3 | V73: TERASI 1 | X73: TERASI 2 | Z73: TERASI 3 | AE73: =SUM(AE69:AE72) -> 7422.4088 | AU73: GEPREK 1 | AW73: GEPREK 2 | AY73: GEPREK 3 | BA73: MATAH 1 | BC73: MATAH 2 | BE73: MATAH 3 | BG73: TERASI 1 | BI73: TERASI 2 | BK73: TERASI 3
J74: NASI | K74: =K56 -> 1301.4354 | L74: NASI | M74: =K74 -> 1301.4354 | N74: NASI | O74: =M74 -> 1301.4354 | P74: NASI | Q74: =O74 -> 1301.4354 | R74: NASI | S74: =Q74 -> 1301.4354 | T74: NASI | U74: =S74 -> 1301.4354 | V74: NASI | W74: =U74 -> 1301.4354 | X74: NASI | Y74: =W74 -> 1301.4354 | Z74: NASI | AA74: =Y74 -> 1301.4354 | AE74: =AE73/9000 -> 0.82471209 | AU74: NASI | AV74: =AV42 -> 954.38596 | AW74: NASI | AX74: =AX42 -> 954.38596 | AY74: NASI | AZ74: =AZ42 -> 954.38596 | BA74: NASI | BB74: =BB42 -> 954.38596 | BC74: NASI | BD74: =BD42 -> 954.38596 | BE74: NASI | BF74: =BF42 -> 954.38596 | BG74: NASI | BH74: =BH42 -> 954.38596 | BI74: NASI | BJ74: =BJ42 -> 954.38596 | BK74: NASI | BL74: =BL42 -> 954.38596
A75: TAKE AWAY | D75: HPP CHICKEN STEAK 1 PORSI | E75: =SUM(E68:E73) -> 8145.877 | J75: SAYAP | K75: =K57 -> 5698.4354 | L75: P.BAWAH | M75: =M57 -> 5288.1162 | N75: DADA | O75: =O57 -> 8775.82 | P75: SAYAP GPRK | Q75: =K75 -> 5698.4354 | R75: P.BAWAH | S75: =M75 -> 5288.1162 | T75: DADA/PA | U75: =O75 -> 8775.82 | V75: SAYAP | W75: =Q75 -> 5698.4354 | X75: P.BAWAH | Y75: =S75 -> 5288.1162 | Z75: DADA/PA | AA75: =U75 -> 8775.82 | AU75: SAYAP | AV75: =AV43 -> 5698.4354 | AW75: P.BAWAH | AX75: =AX43 -> 5288.1162 | AY75: DADA | AZ75: =AZ43 -> 8775.82 | BA75: SAYAP GPRK | BB75: =BB43 -> 5698.4354 | BC75: P.BAWAH | BD75: =BD43 -> 5288.1162 | BE75: DADA/PA | BF75: =BF43 -> 8775.82 | BG75: SAYAP | BH75: =BH43 -> 5698.4354 | BI75: P.BAWAH | BJ75: =BJ43 -> 5288.1162 | BK75: DADA/PA | BL75: =BL43 -> 8775.82
A76: MILO | B76: =B70 -> 3136.7994 | G76: NASI GORENG | J76: NESTLE | K76: =Y60 -> 1657.4478 | L76: NESTLE | M76: =K76 -> 1657.4478 | N76: NESTLE | O76: =M76 -> 1657.4478 | P76: NESTLE | Q76: =O76 -> 1657.4478 | R76: NESTLE | S76: =Q76 -> 1657.4478 | T76: NESTLE | U76: =S76 -> 1657.4478 | V76: NESTLE | W76: =U76 -> 1657.4478 | X76: NESTLE | Y76: =W76 -> 1657.4478 | Z76: NESTLE | AA76: =Y76 -> 1657.4478 | AU76: TEEH RC | AV76: =AV60 -> 219.21053 | AW76: TEEH RC | AX76: =AV76 -> 219.21053 | AY76: TEEH RC | AZ76: =AX76 -> 219.21053 | BA76: TEEH RC | BB76: =AZ76 -> 219.21053 | BC76: TEEH RC | BD76: =BB76 -> 219.21053 | BE76: TEEH RC | BF76: =BD76 -> 219.21053 | BG76: TEEH RC | BH76: =BF76 -> 219.21053 | BI76: TEEH RC | BJ76: =BH76 -> 219.21053 | BK76: TEEH RC | BL76: =BJ76 -> 219.21053
A77: CUP MINUMAN | B77: =B51 -> 373 | G77: NASI PUTIH ( 200 GR ) | H77: =H58/11 -> 1301.4354 | J77: GPRK | K77: =AA16 -> 897.4976 | L77: GPRK | M77: =K77 -> 897.4976 | N77: GPRK | O77: =M77 -> 897.4976 | P77: MATAH | Q77: =E135 -> 1686.4853 | R77: MATAH | S77: =Q77 -> 1686.4853 | T77: MATAH | U77: =S77 -> 1686.4853 | V77: TRASI | W77: =E150 -> 1473.3767 | X77: TRASI | Y77: =W77 -> 1473.3767 | Z77: TRASI | AA77: =Y77 -> 1473.3767 | AU77: GPRK | AV77: =AV45 -> 897.4976 | AW77: GPRK | AX77: =AX45 -> 897.4976 | AY77: GPRK | AZ77: =AZ45 -> 897.4976 | BA77: MATAH | BB77: =BB45 -> 1686.4853 | BC77: MATAH | BD77: =BD45 -> 1686.4853 | BE77: MATAH | BF77: =BF45 -> 1686.4853 | BG77: TRASI | BH77: =BH45 -> 1473.3767 | BI77: TRASI | BJ77: =BJ45 -> 1473.3767 | BK77: TRASI | BL77: =BL45 -> 1473.3767
A78: SEALER | B78: =B52 -> 72.15 | G78: 1 PCS FILET MENTOK | H78: ='WEEKLY FC'!E11/5 -> 1230.9538 | J78: PEMBUNGKUS | K78: =AA17 -> 1555.36 | L78: PEMBUNGKUS | M78: =K78 -> 1555.36 | N78: PEMBUNGKUS | O78: =M78 -> 1555.36 | P78: PEMBUNGKUS | Q78: =O78 -> 1555.36 | R78: PEMBUNGKUS | S78: =Q78 -> 1555.36 | T78: PEMBUNGKUS | U78: =S78 -> 1555.36 | V78: PEMBUNGKUS | W78: =U78 -> 1555.36 | X78: PEMBUNGKUS | Y78: =W78 -> 1555.36 | Z78: PEMBUNGKUS | AA78: =Y78 -> 1555.36 | AU78: PEMBUNGKUS | AV78: =AV46 -> 1555.36 | AW78: PEMBUNGKUS | AX78: =AX46 -> 1555.36 | AY78: PEMBUNGKUS | AZ78: =AZ46 -> 1555.36 | BA78: PEMBUNGKUS | BB78: =BB46 -> 1555.36 | BC78: PEMBUNGKUS | BD78: =BD46 -> 1555.36 | BE78: PEMBUNGKUS | BF78: =BF46 -> 1555.36 | BG78: PEMBUNGKUS | BH78: =BH46 -> 1555.36 | BI78: PEMBUNGKUS | BJ78: =BJ46 -> 1555.36 | BK78: PEMBUNGKUS | BL78: =BL46 -> 1555.36
A79: SEDOTAN | B79: =B53 -> 47 | D79: TAKE AWAY | G79: TELOR ( 0,5 ) | H79: ='WEEKLY FC'!E320*0.5 -> 933.5 | J79: HPP NON CVR | K79: =SUM(K74:K77) -> 9554.8162 | L79: HPP NON CVR | M79: =SUM(M74:M77) -> 9144.497 | N79: HPP NON CVR | O79: =SUM(O74:O77) -> 12632.201 | P79: HPP NON CVR | Q79: =SUM(Q74:Q77) -> 10343.804 | R79: HPP NON CVR | S79: =SUM(S74:S77) -> 9933.4847 | T79: HPP NON CVR | U79: =SUM(U74:U77) -> 13421.189 | V79: HPP NON CVR | W79: =SUM(W74:W77) -> 10130.695 | X79: HPP NON CVR | Y79: =SUM(Y74:Y77) -> 9720.3761 | Z79: HPP NON CVR | AA79: =SUM(AA74:AA77) -> 13208.08 | AU79: HPP NON CVR | AV79: =SUM(AV74:AV77) -> 7769.5295 | AW79: HPP NON CVR | AX79: =SUM(AX74:AX77) -> 7359.2103 | AY79: HPP NON CVR | AZ79: =SUM(AZ74:AZ77) -> 10846.914 | BA79: HPP NON CVR | BB79: =SUM(BB74:BB77) -> 8558.5172 | BC79: HPP NON CVR | BD79: =SUM(BD74:BD77) -> 8148.198 | BE79: HPP NON CVR | BF79: =SUM(BF74:BF77) -> 11635.902 | BG79: HPP NON CVR | BH79: =SUM(BH74:BH77) -> 8345.4086 | BI79: HPP NON CVR | BJ79: =SUM(BJ74:BJ77) -> 7935.0894 | BK79: HPP NON CVR | BL79: =SUM(BL74:BL77) -> 11422.793
D80: BOX STEAK | E80: ='WEEKLY FC'!E137 -> 154 | G80: CABE MERAH | J80: HPP + COVER | K80: =K79+K78 -> 11110.176 | L80: HPP + COVER | M80: =M79+M78 -> 10699.857 | N80: HPP + COVER | O80: =O79+O78 -> 14187.561 | P80: HPP + COVER | Q80: =Q79+Q78 -> 11899.164 | R80: HPP + COVER | S80: =S79+S78 -> 11488.845 | T80: HPP + COVER | U80: =U79+U78 -> 14976.549 | V80: HPP + COVER | W80: =W79+W78 -> 11686.055 | X80: HPP + COVER | Y80: =Y79+Y78 -> 11275.736 | Z80: HPP + COVER | AA80: =AA79+AA78 -> 14763.44 | AU80: HPP + COVER | AV80: =AV79+AV78 -> 9324.8895 | AW80: HPP + COVER | AX80: =AX79+AX78 -> 8914.5703 | AY80: HPP + COVER | AZ80: =+AZ79+AZ78 -> 12402.274 | BA80: HPP + COVER | BB80: =BB79+BB78 -> 10113.877 | BC80: HPP + COVER | BD80: =BD79+BD78 -> 9703.558 | BE80: HPP + COVER | BF80: =BF78+BF79 -> 13191.262 | BG80: HPP + COVER | BH80: =BH79+BH78 -> 9900.7686 | BI80: HPP + COVER | BJ80: =BJ79+BJ78 -> 9490.4494 | BK80: HPP + COVER | BL80: =BL79+BL78 -> 12978.153
A81: 1 PORSI MILO TAKE AWAY | B81: =SUM(B75:B79) -> 3628.9494 | D81: SAOS SACHET | E81: =E54 -> 407 | G81: DAUN BAWANG (10 GR) | H81: =('WEEKLY FC'!E306/1000)*10 -> 150
D82: PLASTIK SEDANG | E82: ='WEEKLY FC'!E128 -> 192 | G82: BAWANG PUTIH ( 2,5 GR ) | H82: =('WEEKLY FC'!E302/1000)*2.5 -> 130
D83: 1 PORSI CHICKEN STEAK | E83: =E75 -> 8145.877 | G83: 1 PACK PREMIX NASGOR ( 10 GR ) | H83: ='WEEKLY FC'!E328 -> 1832
A84: NESTLE ORANGE | G84: MINYAK ( 10 GR ) | H84: ='WEEKLY FC'!E168/1000*10 -> 200.01375
A85: 1 PACK NESTLE ORANGE( 560 GR ) | B85: ='WEEKLY FC'!E103 -> 54100 | D85: HPP STEAK TAKE AWAY | E85: =SUM(E79:E84) -> 8898.877 | K85: MINUMAN
A86: AIR (8 LITER ) | B86: =B9*8 -> 2105.2632 | G86: 10 GR KECAP BANGAU | H86: ='WEEKLY FC'!E309/700*5 -> 247.14286
A87: SIMPLE (200 ML ) | G87: TELOR CEPLOK | H87: =H162 -> 2067.0138 | K87: NO | L87: PRODUK | M87: HPP | O87: NO | P87: PRODUK | Q87: HPP | S87: NO | T87: PRODUK | V87: HPP
D88: CHICKEN STRIP 4 PCS | G88: TIMUN | H88: ='WEEKLY FC'!E308/1000*30 -> 60 | K88: 1 | L88: ='LAP. PENJUALAN '!C216 -> Air Mineral Botol (600 ML) | M88: ='WEEKLY FC'!E99 -> 1667 | O88: 21 | P88: ='LAP. PENJUALAN '!C236 -> Juice Sirsak Float | Q88: =H276+Q98 -> 218.31579 | S88: 41 | T88: ='LAP TAMBAHAN '!C281 -> 0 | V88: =H309 -> 4882.0185
A89: HPP 1 RESEP | B89: =SUM(B85:B86) -> 56205.263 | D89: 4 PCS FILET MENTOK | E89: =('WEEKLY FC'!E11/5)*4 -> 4923.8154 | G89: TOMAT | H89: ='WEEKLY FC'!E61/1000*15 -> 150 | K89: 2 | L89: ='LAP. PENJUALAN '!C217 -> Air Mineral Botol (330 ML) | M89: ='WEEKLY FC'!E119 -> 3500 | O89: 22 | P89: ='LAP. PENJUALAN '!C237 -> Juice Sirsak | Q89: =H276 -> 218.31579 | S89: 42 | T89: ='LAP TAMBAHAN '!C282 -> 0
A90: HPP 1 PORSI | B90: =B89/35 -> 1605.8647 | D90: BUTTER MIX | E90: =H37 -> 1314.8996 | G90: HPP NASI GORENG | H90: =SUM(H79:H89) -> 5769.6704 | K90: 3 | L90: ='LAP. PENJUALAN '!C218 -> Air Mineral Cup | M90: ='WEEKLY FC'!E100 -> 458 | O90: 23
A91: ES BATU | B91: =B69 -> 160 | D91: MINYAK | E91: =E66 -> 606.10227 | K91: 4 | L91: ='LAP. PENJUALAN '!C219 -> Teh Botol | M91: ='WEEKLY FC'!E94 -> 2167 | O91: 24 | P91: ='LAP. PENJUALAN '!C239 -> Milkshake Coklat | Q91: =B165 -> 4566.6316
A92: HPP 1 PORSI ES ORANGE | B92: =SUM(B90:B91) -> 1765.8647 | D92: TEPUNG CAKRA | E92: =E109 -> 187.26 | G92: TAKE AWAY | K92: 5 | L92: ='LAP. PENJUALAN '!C220 -> Teh Sosro Genggam | M92: ='WEEKLY FC'!E95 -> 2271 | O92: 25 | P92: ='LAP. PENJUALAN '!C240 -> Milkshake Coklat Float | Q92: =B165+Q98 -> 4566.6316
G93: NASI GORENG | H93: =H90 -> 5769.6704 | K93: 6 | L93: ='LAP. PENJUALAN '!C221 -> Fruit Tea Botol | M93: ='WEEKLY FC'!E96 -> 3500 | O93: 26 | P93: ='LAP. PENJUALAN '!C241 -> Milkshake Strawberry | Q93: =B215 -> 3100.6316
D94: HPP 1 PORSI ( 4 PCS ) | E94: =SUM(E89:E93) -> 7032.0772 | G94: BOX NASGOR | H94: =E80 -> 154 | K94: 7 | L94: ='LAP. PENJUALAN '!C222 -> Fuit Tea Genggam | M94: ='WEEKLY FC'!E97 -> 0 | O94: 27 | P94: ='LAP. PENJUALAN '!C242 -> Milkshake Strawberry Float | Q94: =B215+Q98 -> 3100.6316
G95: SAOS SASET | H95: =E81 -> 407 | K95: 8 | L95: ='LAP. PENJUALAN '!C223 -> Tebs | M95: ='WEEKLY FC'!E98 -> 3500 | O95: 28
A96: TAKE AWAY | G96: PLASTIK SEDANG | H96: ='WEEKLY FC'!E128 -> 192 | K96: 9 | L96: ='LAP. PENJUALAN '!C224 -> S-tee | M96: ='WEEKLY FC'!E115 -> 1583.97 | O96: 29 | P96: ='LAP. PENJUALAN '!C244 -> Nestle Lemon Tea | Q96: =B45 -> 1657.4478
A97: ORANGE | B97: =B92 -> 1765.8647 | D97: TAKE AWAY | G97: COVER NASGOR | H97: ='WEEKLY FC'!E139 -> 189 | K97: 10 | O97: 30 | P97: ='LAP. PENJUALAN '!C245 -> Milo | Q97: =B70 -> 3136.7994
A98: CUP MINUMAN | B98: =B77 -> 373 | D98: CHICKEN STRIP | E98: =E94 -> 7032.0772 | K98: 11 | L98: ='LAP. PENJUALAN '!C226 -> Juice Durian Float | M98: =E269+'WEEKLY FC'!E73 -> 253.15789 | O98: 31 | P98: ='LAP. PENJUALAN '!C246 -> Ice Cream | Q98: ='WEEKLY FC'!E73 -> 0
A99: SEALER | B99: =B78 -> 72.15 | D99: KANTONG KERTAS | E99: ='WEEKLY FC'!E143 -> 259 | G99: HPP NASI GORENG | H99: =SUM(H93:H97) -> 6711.6704 | K99: 12 | L99: ='LAP. PENJUALAN '!C227 -> Juice Durian | M99: =E269 -> 253.15789 | O99: 32
A100: SEDOTAN | B100: =B79 -> 47 | D100: SAOS SACHET | E100: =E81 -> 407 | K100: 13 | L100: ='LAP. PENJUALAN '!C228 -> Juice Melon Float | M100: =H204+Q98 -> 26.315789 | O100: 33 | P100: ='LAP. PENJUALAN '!C248 -> Es Teh | Q100: =B128 -> 878.01535
D101: PLASTIK KECIL | E101: ='WEEKLY FC'!E133 -> 750.36 | K101: 14 | L101: ='LAP. PENJUALAN '!C229 -> Juice Melon | M101: =H204 -> 26.315789 | O101: 34 | P101: ='LAP. PENJUALAN '!C249 -> Es Teh RC | Q101: =B301 -> 219.21053
A102: 1 PORSI ORANGE TAKE AWAY | B102: =SUM(B96:B100) -> 2258.0147 | D102: CHICKEN STRIP TAKE AWAY | E102: =SUM(E98:E101) -> 8448.4372 | G102: DRESSING BURGER | K102: 15 | L102: ='LAP. PENJUALAN '!C230 -> Juice Strawberry Float | M102: =E219+Q98 -> 253.15789 | O102: 35
G103: MAYONESE ( 1LTR) | H103: ='WEEKLY FC'!E329 -> 31280 | K103: 16 | L103: ='LAP. PENJUALAN '!C231 -> Juice Strawberry | M103: =E219 -> 253.15789 | O103: 36 | P103: ='LAP. PENJUALAN '!C251 -> Thai Green Tea | Q103: =H287 -> 4454.6685
G104: SAOS TOMAT (300 GR) | H104: ='WEEKLY FC'!E333/5000*300 -> 3958.08 | K104: 17 | L104: ='LAP. PENJUALAN '!C232 -> Juice Mangga Float | M104: =E235+Q98 -> 433.33158 | O104: 37 | P104: ='LAP. PENJUALAN '!C252 -> Milky Mango | Q104: =H298 -> 4027.3185
A105: LHYCHEE TEA | D105: CHICKEN STRIP 3 PCS | G105: CREAM CHESSE ( 100 GR) | H105: ='WEEKLY FC'!E55/180*100 -> 8833.3333 | K105: 18 | L105: ='LAP. PENJUALAN '!C233 -> Juice Mangga | M105: =E235 -> 433.33158 | O105: 38 | P105: ='LAP. PENJUALAN '!C253 -> Red Velvet | Q105: =H309 -> 4882.0185
...

Sheet LEFT OVER
A2: LEFT OVER AND SPOILAGE PRODUK
N3: STORE | O3: =LPKK!O4 -> RC SAMATA GOWA
N4: =[3]LP!K3 -> PERIODE | O4: =LPKK!O5 -> 8-14 JANUARI 2025
A7: ITEM | B7: PERSEDIAAN | C7: TANGGAL | D7: TANGGAL | E7: TANGGAL | F7: TANGGAL | G7: TANGGAL | H7: TANGGAL | I7: TANGGAL | J7: TANGGAL | K7: TANGGAL | L7: TANGGAL | M7: TOTAL | N7: PERSEDIAAN | O7: PEMAKAIAN | P7: SELISIH
B8: AWAL | C8: 46030 | D8: 46031 | E8: 46032 | F8: 46033 | G8: 46034 | H8: 46035 | I8: 46036 | N8: AKHIR
A9: MENTOK | D9: 1 | M9: =SUM(B9:L9) -> 1 | O9: 1 | P9: =M9-N9-O9 -> 0
A10: DADA | B10: 2 | M10: =SUM(C10:L10) -> 0 | P10: =M10-N10-O10 -> 0
A11: PAHA ATAS | B11: 2 | H11: 1 | M11: =SUM(C11:L11) -> 1 | O11: 1 | P11: =M11-N11-O11 -> 0
A12: PAHA BAWAH | B12: 4 | C12: 4 | E12: 1 | G12: 1 | M12: =SUM(C12:L12) -> 6 | O12: 6 | P12: =M12-N12-O12 -> 0
A13: SAYAP | B13: 7 | E13: 1 | M13: =SUM(C13:L13) -> 1 | O13: 1 | P13: =M13-N13-O13 -> 0
A14: DADA SPICY | M14: =SUM(C14:L14) -> 0 | P14: =M14-N14-O14 -> 0
A15: PAHA ATAS SPICY | M15: =SUM(C15:L15) -> 0 | P15: =M15-N15-O15 -> 0
A16: PAHA BAWAH SPICY | M16: =SUM(C16:L16) -> 0 | P16: =M16-N16-O16 -> 0
A17: SAYAP SPICY | M17: =SUM(C17:L17) -> 0 | P17: =M17-N17-O17 -> 0
A18: CHICKEN STRIPS | M18: =SUM(C18:L18) -> 0 | P18: =M18-N18-O18 -> 0
A19: CHICKEN STEAK | M19: =SUM(C19:L19) -> 0 | P19: =M19-N19-O19 -> 0
A20: CHICKEN PATTY | M20: =SUM(C20:L20) -> 0 | P20: =M20-N20-O20 -> 0
A21: PERKEDEL | M21: =SUM(C21:L21) -> 0 | P21: =M21-N21-O21 -> 0
A22: FRENCH FRIES | M22: =SUM(C22:L22) -> 0 | P22: =M22-N22-O22 -> 0
A23: NASI | M23: =SUM(C23:L23) -> 0 | P23: =M23-N23-O23 -> 0
A24: ROTI BURGER | M24: =SUM(C24:L24) -> 0 | P24: =M24-N24-O24 -> 0
A25: LEMON TEA | M25: =SUM(C25:L25) -> 0 | P25: =M25-N25-O25 -> 0
A26: MILO | C26: 0.21 | D26: 0.02 | E26: 0.04 | H26: 0.02 | I26: 0.07 | M26: =SUM(C26:L26) -> 0.36 | P26: =M26-N26-O26 -> 0.36
A27: NESTLE ORANGE | M27: =SUM(C27:L27) -> 0 | P27: =M27-N27-O27 -> 0
A28: TEH POCI / TEH RC | M28: =SUM(C28:L28) -> 0 | P28: =M28-N28-O28 -> 0
A29: ICE CREAM | M29: =SUM(C29:L29) -> 0 | P29: =M29-N29-O29 -> 0
A30: JUS | M30: =SUM(C30:L30) -> 0 | P30: =M30-N30-O30 -> 0
A31: MILK SHAKE | M31: =SUM(C31:L31) -> 0 | P31: =M31-N31-O31 -> 0
A32: GREEN CRISPY | M32: =SUM(C32:L32) -> 0 | P32: =M32-N32-O32 -> 0
A33: MINYAK | E33: 2.15 | M33: =SUM(C33:L33) -> 2.15 | P33: =M33-N33-O33 -> 2.15
A34: AYAM UTUH | M34: =SUM(C34:L34) -> 0 | O34: 1 | P34: =M34-N34-O34 -> -1
A35: CHESEMELT | F35: 0.4 | M35: =SUM(C35:L35) -> 0.4 | P35: =M35-N35-O35 -> 0.4
M36: =SUM(C36:L36) -> 0 | P36: =M36-N36-O36 -> 0
M37: =SUM(C37:L37) -> 0 | P37: =M37-N37-O37 -> 0
M38: =SUM(C38:L38) -> 0 | P38: =M38-N38-O38 -> 0
M39: =SUM(C39:L39) -> 0 | P39: =M39-N39-O39 -> 0
M40: =SUM(C40:L40) -> 0 | P40: =M40-N40-O40 -> 0
C41: PARAF CREW | N41: PARAF MANAGER
C45: ( ) | N45: ( )
A47: CATATAN :
A48: 1. FORM LO TERBARU DIGUNAKAN UNTUK PENCATATAN SELAMA 1 PERIODE
A49: 2. UNTUK LO CHICKEN STRIP DIHITUNG PER PCS BUKAN PER PORSI
A50: 3. KOLOM PERSEDIAAN AWAL DIDAPAT DARI PERSEDIAAN AKHIR PERIODE SEBELUMNYA (KHUSUS LO AYAM)
A51: 4. KOLOM PERSEDIAAN AKHIR DIDAPAT DARI PENGHITUNGAN AKTUAL STOK AYAM LO YANG ADA DI FREZER
A52: 5. TO PEMBUATAN PERKEDEL DAN PEMUSNAHAN AYAM LO DIMASUKKAN KE DALAM KOLOM PEMAKAIAN
A53: 6. PEMUSNAHAN AYAM LO HARUS DISERTAI DENGAN BERITA ACARA YANG SUDAH DITANDATANGANI OLEH MANAGEMENT (RM/AM/TC/AUDIT/HR/TO)
A54: 7. LO NASI BISA DIKONFERSI MENJADI BERAS DENGAN CARA LO NASI (KG) : 2.200 =

Sheet LAP. CF
C4: LAPORAN CASH FLOW
J6: CABANG : | K6: =LPKK!O4 -> RC SAMATA GOWA
J7: PERIODE : | K7: =LPKK!O5 -> 8-14 JANUARI 2025
C10: SALDO AWAL PER | F10: =F14 -> 46030 | L10: Rp. | M10: 8049367
C13: Penerimaan :
D14: Sales tanggal, | F14: ='LAPORAN KAS PERIODE'!C6 -> 46030 | I14: Rp | J14: ='LAPORAN KAS PERIODE'!C16 -> 2978332
D15: Sales tanggal, | F15: ='LAPORAN KAS PERIODE'!D6 -> 46031 | I15: Rp | J15: ='LAPORAN KAS PERIODE'!D16 -> 3887301
D16: Sales tanggal, | F16: ='LAPORAN KAS PERIODE'!E6 -> 46032 | I16: Rp | J16: ='LAPORAN KAS PERIODE'!E16 -> 3654747
D17: Sales tanggal, | F17: ='LAPORAN KAS PERIODE'!F6 -> 46033 | I17: Rp | J17: ='LAPORAN KAS PERIODE'!F16 -> 4004039
D18: Sales tanggal, | F18: ='LAPORAN KAS PERIODE'!G6 -> 46034 | I18: Rp | J18: ='LAPORAN KAS PERIODE'!G16 -> 3624209
D19: Sales tanggal, | F19: ='LAPORAN KAS PERIODE'!H6 -> 46035 | I19: Rp | J19: ='LAPORAN KAS PERIODE'!H16 -> 3031252
D20: Sales tanggal, | F20: ='LAPORAN KAS PERIODE'!I6 -> 46036 | I20: Rp | J20: ='LAPORAN KAS PERIODE'!I16 -> 3975543
D21: Sales tanggal, | F21: ='LAPORAN KAS PERIODE'!J6 -> 0 | I21: Rp | J21: ='LAPORAN KAS PERIODE'!J16 -> 0
D22: Sales tanggal, | F22: ='LAPORAN KAS PERIODE'!K6 -> 0 | I22: Rp | J22: ='LAPORAN KAS PERIODE'!K16 -> 0
D23: Sales tanggal, | F23: ='LAPORAN KAS PERIODE'!L6 -> 0 | I23: Rp | J23: ='LAPORAN KAS PERIODE'!L16 -> 0
F26: Total Penerimaan Sales | J26: ….................................. | L26: Rp. | M26: =SUM(J14:K23) -> 25155423
C28: Penerimaan lain - lain :
A30: R | D30: TO AMB MEETING AREA | I30: Rp | J30: 26672
I31: Rp
I32: Rp
I33: RP
J35: ….................................... | L35: Rp. | M35: =SUM(J29:K33) -> 26672
F37: Total Uang Yang Ada | J37: …................................... | L37: Rp. | M37: =M10+M26+M35 -> 33231462
C38: Pengeluaran :
D40: Belanja tanggal, | F40: =F14 -> 46030 | I40: Rp | J40: =VENDOR!I249 -> 7349237
D41: Belanja tanggal, | F41: =F15 -> 46031 | I41: Rp | J41: =VENDOR!K249 -> 2970401
D42: Belanja tanggal, | F42: =F16 -> 46032 | I42: Rp | J42: =VENDOR!M249 -> 2875247
D43: Belanja tanggal, | F43: =F17 -> 46033 | I43: Rp | J43: =VENDOR!O249 -> 3546485
D44: Belanja tanggal, | F44: =F18 -> 46034 | I44: Rp | J44: =VENDOR!Q249 -> 2482710
D45: Belanja tanggal, | F45: =F19 -> 46035 | I45: Rp | J45: =VENDOR!S249 -> 4372444
D46: Belanja tanggal, | F46: =F20 -> 46036 | I46: Rp | J46: =VENDOR!U249 -> 8216838
D47: Belanja tanggal, | F47: =F21 -> 0 | I47: Rp | J47: =VENDOR!W249 -> 0
D48: Belanja tanggal, | F48: =F22 -> 0 | I48: Rp | J48: =VENDOR!Y249 -> 0
D49: Belanja tanggal, | F49: =F23 -> 0 | I49: Rp | J49: =VENDOR!AA249 -> 0
F53: Total Pengeluaran | J53: …................................... | L53: Rp. | M53: =SUM(J40:K49) -> 31813362
C55: SALDO AKHIR PER | J55: …................................... | L55: Rp. | M55: =M37-M53 -> 1418100
D58: Paraf Supervisor
D61: (DIO BAGUS SETIAWAN)
C63: NB. UNTUK SALDO AKHIR PERIODE BISA DIKETIK MANUAL

Sheet SALES CONTROL
A2: ROCKET CHICKEN
A7: SALES CONTROL
L8: CABANG : | M8: =LPKK!O4 -> RC SAMATA GOWA
L9: BULAN : | M9: DESEMBER
A11: TGL | B11: NET SALES | C11: CU | D11: DAYA BELI | E11: MONTH TO DATE | G11: TARGET | H11: % | I11: AVERAGE | J11: MTD | K11: PENJUALAN PAKET ROCKET KIDS
E12: SALES | F12: CU | I12: NET SALES | J12: LAST MONTH | K12: TERJUAL HARI INI (PAKET 1,2,3) | L12: MTD PAKET | M12: HARGA MAINAN | N12: NOMINAL
A13: 1 | B13: 6536645 | C13: 170 | D13: =B13/C13 -> 38450.853 | E13: =B13 -> 6536645 | F13: =C13 -> 170 | G13: 5500000 | H13: =E13/G13 -> 1.1884809 | I13: =E13/A13 -> 6536645 | J13: 4332790 | K13: 38 | L13: =K13 -> 38 | M13: 2 | N13: =L13*M13 -> 76 | O13: =E13-J13 -> 2203855 | P13: =B13*1.3% -> 84976.385
A14: =+A13+1 -> 2 | B14: 5541514 | C14: 163 | D14: =B14/C14 -> 33997.018 | E14: =E13+B14 -> 12078159 | F14: =F13+C14 -> 333 | G14: 11000000 | H14: =E14/G14 -> 1.0980145 | I14: =E14/A14 -> 6039079.5 | J14: 8146157 | K14: 32 | L14: =L13+K14 -> 70 | M14: 3 | N14: =L14*M14 -> 210 | O14: =E14-J14 -> 3932002 | P14: =B14*1.3% -> 72039.682
A15: =+A14+1 -> 3 | B15: 5079513 | C15: 127 | D15: =B15/C15 -> 39996.165 | E15: =E14+B15 -> 17157672 | F15: =F14+C15 -> 460 | G15: =G14+G13 -> 16500000 | H15: =E15/G15 -> 1.0398589 | I15: =E15/A15 -> 5719224 | J15: 12230311 | L15: =L14+K15 -> 70 | N15: =L15*M15 -> 0 | O15: =E15-J15 -> 4927361 | P15: =B15*1.3% -> 66033.669
A16: =+A15+1 -> 4 | B16: 5991915 | C16: 178 | D16: =B16/C16 -> 33662.444 | E16: =E15+B16 -> 23149587 | F16: =F15+C16 -> 638 | G16: =G15+G13 -> 22000000 | H16: =E16/G16 -> 1.052254 | I16: =E16/A16 -> 5787396.8 | J16: 17824934 | K16: 25 | L16: =L15+K16 -> 95 | M16: 5 | N16: =L16*M16 -> 475 | O16: =E16-J16 -> 5324653 | P16: =B16*1.3% -> 77894.895
A17: =+A16+1 -> 5 | B17: 4231255 | C17: 130 | D17: =B17/C17 -> 32548.115 | E17: =E16+B17 -> 27380842 | F17: =F16+C17 -> 768 | G17: =G16+G13 -> 27500000 | H17: =E17/G17 -> 0.99566698 | I17: =E17/A17 -> 5476168.4 | J17: 21774055 | K17: 22 | L17: =L16+K17 -> 117 | M17: 5 | N17: =L17*M17 -> 585 | O17: =E17-J17 -> 5606787 | P17: =B17*1.3% -> 55006.315
A18: =+A17+1 -> 6 | B18: 3279995 | C18: 98 | D18: =B18/C18 -> 33469.337 | E18: =E17+B18 -> 30660837 | F18: =F17+C18 -> 866 | G18: =G17+G13 -> 33000000 | H18: =E18/G18 -> 0.92911627 | I18: =E18/A18 -> 5110139.5 | J18: 25885802 | L18: =L17+K18 -> 117 | N18: =L18*M18 -> 0 | O18: =E18-J18 -> 4775035 | P18: =B18*1.3% -> 42639.935
A19: =+A18+1 -> 7 | B19: 4000430 | C19: 107 | D19: =B19/C19 -> 37387.196 | E19: =E18+B19 -> 34661267 | F19: =F18+C19 -> 973 | G19: =G18+G13 -> 38500000 | H19: =E19/G19 -> 0.90029265 | I19: =E19/A19 -> 4951609.6 | J19: 30016480 | L19: =L18+K19 -> 117 | M19: 3 | N19: =L19*M19 -> 351 | O19: =E19-J19 -> 4644787 | P19: =B19*1.3% -> 52005.59
A20: =+A19+1 -> 8 | B20: 2978322 | C20: 101 | D20: =B20/C20 -> 29488.337 | E20: =E19+B20 -> 37639589 | F20: =F19+C20 -> 1074 | G20: =G19+G13 -> 44000000 | H20: =E20/G20 -> 0.8554452 | I20: =E20/A20 -> 4704948.6 | J20: 34508078 | K20: 8 | L20: =L19+K20 -> 125 | M20: 4 | N20: =L20*M20 -> 500 | O20: =E20-J20 -> 3131511 | P20: =B20*1.3% -> 38718.186
A21: =+A20+1 -> 9 | B21: 3887301 | C21: 110 | D21: =B21/C21 -> 35339.1 | E21: =E20+B21 -> 41526890 | F21: =F20+C21 -> 1184 | G21: =G20+G13 -> 49500000 | H21: =E21/G21 -> 0.83892707 | I21: =E21/A21 -> 4614098.9 | J21: 39520736 | K21: 18 | L21: =L20+K21 -> 143 | M21: 5 | N21: =L21*M21 -> 715 | O21: =E21-J21 -> 2006154 | P21: =B21*1.3% -> 50534.913 | T21: 3624209
A22: =+A21+1 -> 10 | B22: 3654747 | C22: 105 | D22: =B22/C22 -> 34807.114 | E22: =E21+B22 -> 45181637 | F22: =F21+C22 -> 1289 | G22: =G21+G13 -> 55000000 | H22: =E22/G22 -> 0.82148431 | I22: =E22/A22 -> 4518163.7 | J22: 43164696 | L22: =L21+K22 -> 143 | N22: =L22*M22 -> 0 | O22: =E22-J22 -> 2016941 | P22: =B22*1.3% -> 47511.711
A23: =+A22+1 -> 11 | B23: 4004039 | C23: 125 | D23: =B23/C23 -> 32032.312 | E23: =E22+B23 -> 49185676 | F23: =F22+C23 -> 1414 | G23: =G22+G13 -> 60500000 | H23: =E23/G23 -> 0.81298638 | I23: =E23/A23 -> 4471425.1 | J23: 47867685 | L23: =L22+K23 -> 143 | N23: =L23*M23 -> 0 | O23: =E23-J23 -> 1317991 | P23: =B23*1.3% -> 52052.507 | Q23: =E21-J21 -> 2006154
A24: =+A23+1 -> 12 | B24: 3624209 | C24: 116 | D24: =B24/C24 -> 31243.181 | E24: =E23+B24 -> 52809885 | F24: =F23+C24 -> 1530 | G24: =G23+G13 -> 66000000 | H24: =E24/G24 -> 0.80014977 | I24: =E24/A24 -> 4400823.8 | J24: 51732349 | L24: =L23+K24 -> 143 | N24: =L24*M24 -> 0 | O24: =E24-J24 -> 1077536 | P24: =B24*1.3% -> 47114.717
A25: =+A24+1 -> 13 | B25: 3031252 | C25: 104 | D25: =B25/C25 -> 29146.654 | E25: =E24+B25 -> 55841137 | F25: =F24+C25 -> 1634 | G25: =G24+G13 -> 71500000 | H25: =E25/G25 -> 0.78099492 | I25: =E25/A25 -> 4295472.1 | J25: 55794830 | L25: =L24+K25 -> 143 | N25: =L25*M25 -> 0 | O25: =E25-J25 -> 46307 | P25: =B25*1.3% -> 39406.276
A26: =+A25+1 -> 14 | B26: 3975543 | C26: 118 | D26: =B26/C26 -> 33691.042 | E26: =E25+B26 -> 59816680 | F26: =F25+C26 -> 1752 | G26: =G25+G13 -> 77000000 | H26: =E26/G26 -> 0.77684 | I26: =E26/A26 -> 4272620 | J26: 61012310 | K26: 13 | L26: =L25+K26 -> 156 | N26: =L26*M26 -> 0 | O26: =E26-J26 -> -1195630 | P26: =B26*1.3% -> 51682.059 | S26: 4004039
A27: =+A26+1 -> 15 | D27: =B27/C27 -> #DIV/0! | E27: =E26+B27 -> 59816680 | F27: =F26+C27 -> 1752 | G27: =G26+G13 -> 82500000 | H27: =E27/G27 -> 0.72505067 | I27: =E27/A27 -> 3987778.7 | J27: 65158654 | L27: =L26+K27 -> 156 | N27: =L27*M27 -> 0 | O27: =E27-J27 -> -5341974 | P27: =B27*1.3% -> 0
A28: =+A27+1 -> 16 | D28: =B28/C28 -> #DIV/0! | E28: =E27+B28 -> 59816680 | F28: =F27+C28 -> 1752 | G28: =G27+G13 -> 88000000 | H28: =E28/G28 -> 0.679735 | I28: =E28/A28 -> 3738542.5 | J28: 69464312 | L28: =L27+K28 -> 156 | N28: =L28*M28 -> 0 | O28: =E28-J28 -> -9647632 | P28: =B28*1.3% -> 0
A29: =+A28+1 -> 17 | D29: =B29/C29 -> #DIV/0! | E29: =E28+B29 -> 59816680 | F29: =F28+C29 -> 1752 | G29: =G28+G13 -> 93500000 | H29: =E29/G29 -> 0.63975059 | I29: =E29/A29 -> 3518628.2 | J29: 75161776 | L29: =L28+K29 -> 156 | N29: =L29*M29 -> 0 | O29: =E29-J29 -> -15345096 | P29: =B29*1.3% -> 0
A30: =+A29+1 -> 18 | D30: =B30/C30 -> #DIV/0! | E30: =E29+B30 -> 59816680 | F30: =F29+C30 -> 1752 | G30: =G29+G13 -> 99000000 | H30: =E30/G30 -> 0.60420889 | I30: =E30/A30 -> 3323148.9 | J30: 79300766 | L30: =L29+K30 -> 156 | N30: =L30*M30 -> 0 | O30: =E30-J30 -> -19484086 | P30: =B30*1.3% -> 0
A31: =+A30+1 -> 19 | D31: =B31/C31 -> #DIV/0! | E31: =E30+B31 -> 59816680 | F31: =F30+C31 -> 1752 | G31: =G30+G13 -> 104500000 | H31: =E31/G31 -> 0.57240842 | I31: =E31/A31 -> 3148246.3 | J31: 84271649 | L31: =L30+K31 -> 156 | N31: =L31*M31 -> 0 | O31: =E31-J31 -> -24454969 | P31: =B31*1.3% -> 0
A32: =+A31+1 -> 20 | D32: =B32/C32 -> #DIV/0! | E32: =E31+B32 -> 59816680 | F32: =F31+C32 -> 1752 | G32: =G31+G13 -> 110000000 | H32: =E32/G32 -> 0.543788 | I32: =E32/A32 -> 2990834 | J32: 87227067 | L32: =L31+K32 -> 156 | N32: =L32*M32 -> 0 | O32: =E32-J32 -> -27410387 | P32: =B32*1.3% -> 0
A33: =+A32+1 -> 21 | D33: =B33/C33 -> #DIV/0! | E33: =E32+B33 -> 59816680 | F33: =F32+C33 -> 1752 | G33: =G32+G13 -> 115500000 | H33: =E33/G33 -> 0.51789333 | I33: =E33/A33 -> 2848413.3 | J33: 92842414 | L33: =L32+K33 -> 156 | N33: =L33*M33 -> 0 | O33: =E33-J33 -> -33025734 | P33: =B33*1.3% -> 0
A34: =+A33+1 -> 22 | D34: =B34/C34 -> #DIV/0! | E34: =E33+B34 -> 59816680 | F34: =F33+C34 -> 1752 | G34: =G33+G13 -> 121000000 | H34: =E34/G34 -> 0.49435273 | I34: =E34/A34 -> 2718940 | J34: 97742968 | L34: =L33+K34 -> 156 | N34: =L34*M34 -> 0 | O34: =E34-J34 -> -37926288 | P34: =B34*1.3% -> 0
A35: =+A34+1 -> 23 | D35: =B35/C35 -> #DIV/0! | E35: =E34+B35 -> 59816680 | F35: =F34+C35 -> 1752 | G35: =G34+G13 -> 126500000 | H35: =E35/G35 -> 0.47285913 | I35: =E35/A35 -> 2600725.2 | J35: 102201945 | L35: =L34+K35 -> 156 | N35: =L35*M35 -> 0 | O35: =E35-J35 -> -42385265 | P35: =B35*1.3% -> 0
A36: =+A35+1 -> 24 | D36: =B36/C36 -> #DIV/0! | E36: =E35+B36 -> 59816680 | F36: =F35+C36 -> 1752 | G36: =G35+G13 -> 132000000 | H36: =E36/G36 -> 0.45315667 | I36: =E36/A36 -> 2492361.7 | J36: 108013339 | L36: =L35+K36 -> 156 | N36: =L36*M36 -> 0 | O36: =E36-J36 -> -48196659 | P36: =B36*1.3% -> 0
A37: =+A36+1 -> 25 | D37: =B37/C37 -> #DIV/0! | E37: =E36+B37 -> 59816680 | F37: =F36+C37 -> 1752 | G37: =G36+G13 -> 137500000 | H37: =E37/G37 -> 0.4350304 | I37: =E37/A37 -> 2392667.2 | J37: 111890580 | L37: =L36+K37 -> 156 | N37: =L37*M37 -> 0 | O37: =E37-J37 -> -52073900 | P37: =B37*1.3% -> 0
A38: =+A37+1 -> 26 | D38: =B38/C38 -> #DIV/0! | E38: =E37+B38 -> 59816680 | F38: =F37+C38 -> 1752 | G38: =G37+G13 -> 143000000 | H38: =E38/G38 -> 0.41829846 | I38: =E38/A38 -> 2300641.5 | J38: 116663606 | L38: =L37+K38 -> 156 | N38: =L38*M38 -> 0 | O38: =E38-J38 -> -56846926 | P38: =B38*1.3% -> 0
A39: =+A38+1 -> 27 | D39: =B39/C39 -> #DIV/0! | E39: =E38+B39 -> 59816680 | F39: =F38+C39 -> 1752 | G39: =G38+G13 -> 148500000 | H39: =E39/G39 -> 0.40280593 | I39: =E39/A39 -> 2215432.6 | J39: 120629521 | L39: =L38+K39 -> 156 | N39: =L39*M39 -> 0 | O39: =E39-J39 -> -60812841 | P39: =B39*1.3% -> 0
A40: =+A39+1 -> 28 | D40: =B40/C40 -> #DIV/0! | E40: =E39+B40 -> 59816680 | F40: =F39+C40 -> 1752 | G40: =G39+G13 -> 154000000 | H40: =E40/G40 -> 0.38842 | I40: =E40/A40 -> 2136310 | J40: 124672879 | L40: =L39+K40 -> 156 | N40: =L40*M40 -> 0 | O40: =E40-J40 -> -64856199 | P40: =B40*1.3% -> 0
A41: =+A40+1 -> 29 | D41: =B41/C41 -> #DIV/0! | E41: =E40+B41 -> 59816680 | F41: =F40+C41 -> 1752 | G41: =G40+G13 -> 159500000 | H41: =E41/G41 -> 0.37502621 | I41: =E41/A41 -> 2062644.1 | J41: 128247761 | L41: =L40+K41 -> 156 | N41: =L41*M41 -> 0 | O41: =E41-J41 -> -68431081 | P41: =B41*1.3% -> 0
A42: =+A41+1 -> 30 | D42: =B42/C42 -> #DIV/0! | E42: =E41+B42 -> 59816680 | F42: =F41+C42 -> 1752 | G42: =G41+G13 -> 165000000 | H42: =E42/G42 -> 0.36252533 | I42: =E42/A42 -> 1993889.3 | J42: 132322166 | L42: =L41+K42 -> 156 | N42: =L42*M42 -> 0 | O42: =E42-J42 -> -72505486 | P42: =B42*1.3% -> 0
A43: =+A42+1 -> 31 | D43: =B43/C43 -> #DIV/0! | E43: =E42+B43 -> 59816680 | F43: =F42+C43 -> 1752 | G43: =G42+G13 -> 170500000 | H43: =E43/G43 -> 0.35083097 | I43: =E43/A43 -> 1929570.3 | J43: 137886696 | L43: =L42+K43 -> 156 | N43: =L43*M43 -> 0 | O43: =E43-J43 -> -78070016 | P43: =B43*1.3% -> 0 | Q43: =SUM(P13:P43) -> 777616.84
L45: DIBUAT OLEH
B46: RUMUS PENGISIAN SALES CONTROL
D47: 1. | E47: NET SALES | F47: : | G47: PENJUALAN BERSIH HARI INI
D48: 2. | E48: CU | F48: : | G48: CUSTOMER HARI INI | L48: (DIO BAGUS SETIAWAN)
D49: 3. | E49: SALES MTD | F49: : | G49: SALES HARI INI + SALES MTD | O49: =E26-J26 -> -1195630
D50: 4. | E50: MTD CU | F50: : | G50: CUSTOMER HARI INI + CUSTOMER MTD
D51: 5. | E51: % | F51: : | G51: SALES MTD | I51: ......%
G52: TARGET
D53: 6. | E53: AVERAGE SALES | F53: : | G53: SALES MTD : TANGGAL HARI INI
D54: 7. | E54: DAYA BELI | F54: : | G54: SALES HARI INI : CU HARI INI
J57: -2076105
J58: -1918005
J59: =E38-J38 -> -56846926
J60: =E39-J39 -> -60812841

Sheet COST ANALYSIS
B2: COST ANALYSIS
H4: CABANG : | I4: =LPKK!O4 -> RC SAMATA GOWA
H5: PERIODE : | I5: =LPKK!O5 -> 8-14 JANUARI 2025
A7: No | B7: Item | C7: Stock Awal | D7: Pembelian | E7: Stock Akhir | F7: Pemakaian | G7: Penjualan | H7: ( + / - ) | I7: LO | J7: Keterangan
A9: 1 | B9: =VENDOR!D10 -> DADA MENTOK | C9: =VENDOR!H10 -> 133 | D9: =VENDOR!AJ10 -> 118 | E9: =VENDOR!AL10 -> 112.3 | F9: =C9+D9-E9 -> 138.7 | G9: =Q10 -> 49.1 | H9: =G9-(F9-I9) -> -89.6 | J9: =SUM(H9:H11) -> -0.6 | L9: ITEM | M9: LP | N9: GRAB | O9: GOJEK | P9: SHOPEE | Q9: TOTAL
A10: 2 | B10: =VENDOR!D11 -> DADA | C10: =VENDOR!H11 -> 247 | D10: =VENDOR!AJ11 -> 253 | E10: =VENDOR!AL11 -> 208 | F10: =C10+D10-E10 -> 292 | G10: =Q11 -> 680 | H10: =G10-((F10+F11)-I10) -> 89 | I10: ='LEFT OVER'!M9+'LEFT OVER'!M10+'LEFT OVER'!M11 -> 2 | K10: =SUM(J9:J22) -> 0.4 | L10: DADA MENTOK | Q10: =V14 -> 49.1 | S10: MENTOK | T10: STRIP 2 | U10: ='LAP. PENJUALAN '!N185+'LAP. PENJUALAN '!N186 -> 14 | V10: =U10*2/5 -> 5.6 | W10: BT MIX | X10: =U10/30 -> 0.46666667 | Y10: =X10+X11 -> 1.1166667
A11: 3 | B11: =VENDOR!D12 -> PAHA ATAS | C11: =VENDOR!H12 -> 249 | D11: =VENDOR!AJ12 -> 260 | E11: =VENDOR!AL12 -> 208 | F11: =C11+D11-E11 -> 301 | L11: DADA | M11: ='LAP. PENJUALAN '!J293 -> 565 | N11: ='LAP. PENJUALAN GRAB FOOD'!J259 -> 71 | O11: ='LAP. PENJUALAN GO FOOD'!J258 -> 31 | P11: ='LAP. PENJUALAN SHOPEE FOOD'!M254 -> 13 | Q11: =SUM(M11:P12) -> 680 | T11: STRIP 4 | U11: ='LAP. PENJUALAN '!N12+'LAP. PENJUALAN '!N49+'LAP. PENJUALAN GRAB FOOD'!N12+'LAP. PENJUALAN GRAB FOOD'!N39+'LAP. PENJUALAN GO FOOD'!N39+'LAP. PENJUALAN GO FOOD'!N12+'LAP. PENJUALAN SHOPEE FOOD'!N39+'LAP. PENJUALAN SHOPEE FOOD'!N12+'LAP. PENJUALAN GRAB FOOD'!N169+'LAP. PENJUALAN GRAB FOOD'!N230+'LAP. PENJUALAN '!N196+'LAP. PENJUALAN '!N199+'LAP. PENJUALAN '!N208+'LAP. PENJUALAN '!N201+'LAP. PENJUALAN '!N30+'LAP. PENJUALAN '!N38+'LAP. PENJUALAN '!N43+'LAP. PENJUALAN '!N48 -> 13 | V11: =U11*4/5 -> 10.4 | X11: =U11/20 -> 0.65
A12: 4 | B12: =VENDOR!D13 -> PAHA BAWAH | C12: =VENDOR!H13 -> 273 | D12: =VENDOR!AJ13 -> 210 | E12: =VENDOR!AL13 -> 240 | F12: =C12+D12-E12 -> 243 | G12: =Q13 -> 240 | H12: =G12-(F12-I12) -> 3 | I12: ='LEFT OVER'!M12 -> 6 | J12: {=H12:H13} -> 3 | L12: PAHA ATAS | T12: STEAK | U12: ='LAP. PENJUALAN '!N13+'LAP. PENJUALAN '!N35+'LAP. PENJUALAN '!N47+'LAP. PENJUALAN '!N168+'LAP. PENJUALAN '!N168+'LAP. PENJUALAN GRAB FOOD'!N13+'LAP. PENJUALAN GRAB FOOD'!N35+'LAP. PENJUALAN GRAB FOOD'!N42+'LAP. PENJUALAN GRAB FOOD'!N47+'LAP. PENJUALAN GO FOOD'!N13+'LAP. PENJUALAN GO FOOD'!N35+'LAP. PENJUALAN GO FOOD'!N42+'LAP. PENJUALAN GO FOOD'!N47+'LAP. PENJUALAN SHOPEE FOOD'!N13+'LAP. PENJUALAN SHOPEE FOOD'!N35+'LAP. PENJUALAN SHOPEE FOOD'!N42+'LAP. PENJUALAN SHOPEE FOOD'!N47+'LAP. PENJUALAN GRAB FOOD'!N155+'LAP. PENJUALAN GRAB FOOD'!N163+'LAP. PENJUALAN '!N194+'LAP. PENJUALAN '!N197+'LAP. PENJUALAN '!N195+'LAP. PENJUALAN '!N198+'LAP. PENJUALAN '!N207+'LAP. PENJUALAN '!N209+'LAP. PENJUALAN '!N41+'LAP. PENJUALAN '!N26 -> 49 | V12: =U12/2 -> 24.5 | W12: P STEAK | X12: =U12/12 -> 4.0833333
A13: 5 | B13: =VENDOR!D14 -> SAYAP | C13: =VENDOR!H14 -> 252 | D13: =VENDOR!AJ14 -> 260 | E13: =VENDOR!AL14 -> 210 | F13: =C13+D13-E13 -> 302 | G13: =Q14 -> 299 | H13: =G13-(F13-I13) -> -2 | I13: ='LEFT OVER'!M13 -> 1 | J13: -2 | L13: PAHA BAWAH | M13: ='LAP. PENJUALAN '!J294 -> 192 | N13: ='LAP. PENJUALAN GRAB FOOD'!J260 -> 30 | O13: ='LAP. PENJUALAN GO FOOD'!J259 -> 8 | P13: ='LAP. PENJUALAN SHOPEE FOOD'!M255 -> 10 | Q13: =SUM(M13:P13) -> 240 | T13: NASGOR | U13: ='LAP. PENJUALAN '!N22+'LAP. PENJUALAN '!N38+'LAP. PENJUALAN '!N45+'LAP. PENJUALAN '!N165+'LAP. PENJUALAN GRAB FOOD'!N22+'LAP. PENJUALAN GRAB FOOD'!N38+'LAP. PENJUALAN GRAB FOOD'!N45+'LAP. PENJUALAN GO FOOD'!N22+'LAP. PENJUALAN GO FOOD'!N38+'LAP. PENJUALAN GO FOOD'!N45+'LAP. PENJUALAN SHOPEE FOOD'!N22+'LAP. PENJUALAN SHOPEE FOOD'!N38+'LAP. PENJUALAN SHOPEE FOOD'!N45 -> 43 | V13: =U13/5 -> 8.6
A14: 6 | B14: =VENDOR!D15 -> CHICKEN PATTY | C14: =VENDOR!H15 -> 6 | D14: =VENDOR!AJ15 -> 69 | E14: =VENDOR!AL15 -> 11 | F14: =C14+D14-E14 -> 64 | G14: =M28 -> 66 | H14: =G14-(F14-I14) -> 2 | L14: SAYAP | M14: ='LAP. PENJUALAN '!J295 -> 236 | N14: ='LAP. PENJUALAN GRAB FOOD'!J261 -> 42 | O14: ='LAP. PENJUALAN GO FOOD'!J260 -> 10 | P14: ='LAP. PENJUALAN SHOPEE FOOD'!M256 -> 11 | Q14: =SUM(M14:P14) -> 299 | V14: =SUM(V10:V13) -> 49.1
A15: 7 | B15: =VENDOR!D16 -> SAYAP TANPA KOLAR | C15: =VENDOR!H16 -> 0 | D15: =VENDOR!AJ16 -> 0 | E15: =VENDOR!AL16 -> 0 | F15: =C15+D15-E15 -> 0 | H15: =G15-(F15-I15) -> 0 | L15: CHICKEN PATTY | Q15: =SUM(M15:P15) -> 0
A16: 8 | B16: =VENDOR!D17 -> PATTY BEEF | C16: =VENDOR!H17 -> 0 | D16: =VENDOR!AJ17 -> 0 | E16: =VENDOR!AL17 -> 0 | F16: =C16+D16-E16 -> 0 | H16: =G16-(F16-I16) -> 0 | L16: SAYAP TANPA KOLARR | Q16: =SUM(M16:P16) -> 0 | S16: BERAS | T16: LP | U16: GRAB | V16: GOJEK | W16: SHOPEE
A17: 9 | B17: =VENDOR!D18 -> BEEF STEAK | C17: =VENDOR!H18 -> 0 | D17: =VENDOR!AJ18 -> 0 | E17: =VENDOR!AL18 -> 0 | F17: =C17+D17-E17 -> 0 | H17: =G17-(F17-I17) -> 0 | L17: PATTY BEEF | Q17: =SUM(M17:P17) -> 0 | S17: REGULER | T17: ='LAP. PENJUALAN '!N16+'LAP. PENJUALAN '!N34+'LAP. PENJUALAN '!N35+'LAP. PENJUALAN '!N37+'LAP. PENJUALAN '!N39+'LAP. PENJUALAN '!N40+'LAP. PENJUALAN '!N41+'LAP. PENJUALAN '!N42+'LAP. PENJUALAN '!N46+'LAP. PENJUALAN '!N47+'LAP. PENJUALAN '!N48+'LAP. PENJUALAN '!N51+'LAP. PENJUALAN '!N52+'LAP. PENJUALAN '!N53+'LAP. PENJUALAN '!N59+'LAP. PENJUALAN '!N60+'LAP. PENJUALAN '!N61+'LAP. PENJUALAN '!N67+'LAP. PENJUALAN '!N68+'LAP. PENJUALAN '!N69+'LAP. PENJUALAN '!N75+'LAP. PENJUALAN '!N76+'LAP. PENJUALAN '!N77+'LAP. PENJUALAN '!N83+'LAP. PENJUALAN '!N84+'LAP. PENJUALAN '!N85+'LAP. PENJUALAN '!N86+'LAP. PENJUALAN '!N89+'LAP. PENJUALAN '!N90+'LAP. PENJUALAN '!N124+'LAP. PENJUALAN '!N125+'LAP. PENJUALAN '!N126+'LAP. PENJUALAN '!N127+'LAP. PENJUALAN '!N174+'LAP. PENJUALAN '!N175+'LAP. PENJUALAN '!N176+'LAP. PENJUALAN '!N177+'LAP. PENJUALAN '!N178+'LAP. PENJUALAN '!N186+'LAP. PENJUALAN '!N181+45+'LAP. PENJUALAN '!N194+'LAP. PENJUALAN '!N195+'LAP. PENJUALAN '!N196+'LAP. PENJUALAN '!N197+'LAP. PENJUALAN '!N198+'LAP. PENJUALAN '!N199+'LAP. PENJUALAN '!N201+'LAP. PENJUALAN '!N201+'LAP. PENJUALAN '!N201+'LAP. PENJUALAN '!N201+'LAP. PENJUALAN '!N202+'LAP. PENJUALAN '!N202+'LAP. PENJUALAN '!N202+'LAP. PENJUALAN '!N202+'LAP. PENJUALAN '!N210+'LAP. PENJUALAN '!N201+'LAP. PENJUALAN '!N201+'LAP. PENJUALAN '!N201+'LAP. PENJUALAN '!N201+'LAP. PENJUALAN '!N202+'LAP. PENJUALAN '!N202+'LAP. PENJUALAN '!N202+'LAP. PENJUALAN '!N202+'LAP. PENJUALAN '!N203+'LAP. PENJUALAN '!N203+'LAP. PENJUALAN '!N203+'LAP. PENJUALAN '!N25+'LAP. PENJUALAN '!N26+'LAP. PENJUALAN '!N28+'LAP. PENJUALAN '!N29+'LAP. PENJUALAN '!N30+'LAP. PENJUALAN '!N31 -> 676 | U17: ='LAP. PENJUALAN GRAB FOOD'!N16+'LAP. PENJUALAN GRAB FOOD'!N34+'LAP. PENJUALAN GRAB FOOD'!N35+'LAP. PENJUALAN GRAB FOOD'!N37+'LAP. PENJUALAN GRAB FOOD'!N39+'LAP. PENJUALAN GRAB FOOD'!N40+'LAP. PENJUALAN GRAB FOOD'!N41+'LAP. PENJUALAN GRAB FOOD'!N43+'LAP. PENJUALAN GRAB FOOD'!N45+'LAP. PENJUALAN GRAB FOOD'!N46+'LAP. PENJUALAN GRAB FOOD'!N47+'LAP. PENJUALAN GRAB FOOD'!N48+'LAP. PENJUALAN GRAB FOOD'!N49+'LAP. PENJUALAN GRAB FOOD'!N51+'LAP. PENJUALAN GRAB FOOD'!N52+'LAP. PENJUALAN GRAB FOOD'!N53+'LAP. PENJUALAN GRAB FOOD'!N59+'LAP. PENJUALAN GRAB FOOD'!N60+'LAP. PENJUALAN GRAB FOOD'!N61+'LAP. PENJUALAN GRAB FOOD'!N67+'LAP. PENJUALAN GRAB FOOD'!N68+'LAP. PENJUALAN GRAB FOOD'!N69+'LAP. PENJUALAN GRAB FOOD'!N75+'LAP. PENJUALAN GRAB FOOD'!N76+'LAP. PENJUALAN GRAB FOOD'!N77+'LAP. PENJUALAN GRAB FOOD'!N122+'LAP. PENJUALAN GRAB FOOD'!N123+'LAP. PENJUALAN GRAB FOOD'!N124+'LAP. PENJUALAN GRAB FOOD'!N151+'LAP. PENJUALAN GRAB FOOD'!N154+'LAP. PENJUALAN GRAB FOOD'!N155+'LAP. PENJUALAN GRAB FOOD'!N156+'LAP. PENJUALAN GRAB FOOD'!N157+'LAP. PENJUALAN GRAB FOOD'!N158+'LAP. PENJUALAN GRAB FOOD'!N167+'LAP. PENJUALAN GRAB FOOD'!N173+'LAP. PENJUALAN GRAB FOOD'!N175+'LAP. PENJUALAN GRAB FOOD'!N179+'LAP. PENJUALAN GRAB FOOD'!N183+'LAP. PENJUALAN GRAB FOOD'!N229+'LAP. PENJUALAN GRAB FOOD'!N230+'LAP. PENJUALAN GRAB FOOD'!N231+'LAP. PENJUALAN GRAB FOOD'!N234+'LAP. PENJUALAN GRAB FOOD'!N235+'LAP. PENJUALAN GRAB FOOD'!N237+'LAP. PENJUALAN GRAB FOOD'!N238 -> 90 | V17: ='LAP. PENJUALAN GO FOOD'!N16+'LAP. PENJUALAN GO FOOD'!N34+'LAP. PENJUALAN GO FOOD'!N35+'LAP. PENJUALAN GO FOOD'!N37+'LAP. PENJUALAN GO FOOD'!N39+'LAP. PENJUALAN GO FOOD'!N40+'LAP. PENJUALAN GO FOOD'!N41+'LAP. PENJUALAN GO FOOD'!N42+'LAP. PENJUALAN GO FOOD'!N43+'LAP. PENJUALAN GO FOOD'!N46+'LAP. PENJUALAN GO FOOD'!N47+'LAP. PENJUALAN GO FOOD'!N48+'LAP. PENJUALAN GO FOOD'!N49+'LAP. PENJUALAN GO FOOD'!N51+'LAP. PENJUALAN GO FOOD'!N52+'LAP. PENJUALAN GO FOOD'!N53+'LAP. PENJUALAN GO FOOD'!N59+'LAP. PENJUALAN GO FOOD'!N60+'LAP. PENJUALAN GO FOOD'!N61+'LAP. PENJUALAN GO FOOD'!N67+'LAP. PENJUALAN GO FOOD'!N68+'LAP. PENJUALAN GO FOOD'!N69+'LAP. PENJUALAN GO FOOD'!N75+'LAP. PENJUALAN GO FOOD'!N76+'LAP. PENJUALAN GO FOOD'!N77+'LAP. PENJUALAN GO FOOD'!N83+'LAP. PENJUALAN GO FOOD'!N85+'LAP. PENJUALAN GO FOOD'!N86+'LAP. PENJUALAN GO FOOD'!N129+'LAP. PENJUALAN GO FOOD'!N130+'LAP. PENJUALAN GO FOOD'!N131 -> 27 | W17: ='LAP. PENJUALAN SHOPEE FOOD'!N16+'LAP. PENJUALAN SHOPEE FOOD'!N34+'LAP. PENJUALAN SHOPEE FOOD'!N35+'LAP. PENJUALAN SHOPEE FOOD'!N37+'LAP. PENJUALAN SHOPEE FOOD'!N39+'LAP. PENJUALAN SHOPEE FOOD'!N40+'LAP. PENJUALAN SHOPEE FOOD'!N41+'LAP. PENJUALAN SHOPEE FOOD'!N42+'LAP. PENJUALAN SHOPEE FOOD'!N43+'LAP. PENJUALAN SHOPEE FOOD'!N46+'LAP. PENJUALAN SHOPEE FOOD'!N47+'LAP. PENJUALAN SHOPEE FOOD'!N48+'LAP. PENJUALAN SHOPEE FOOD'!N49+'LAP. PENJUALAN SHOPEE FOOD'!N51+'LAP. PENJUALAN SHOPEE FOOD'!N52+'LAP. PENJUALAN SHOPEE FOOD'!N53+'LAP. PENJUALAN SHOPEE FOOD'!N59+'LAP. PENJUALAN SHOPEE FOOD'!N60+'LAP. PENJUALAN SHOPEE FOOD'!N61+'LAP. PENJUALAN SHOPEE FOOD'!N67+'LAP. PENJUALAN SHOPEE FOOD'!N68+'LAP. PENJUALAN SHOPEE FOOD'!N69+'LAP. PENJUALAN SHOPEE FOOD'!N75+'LAP. PENJUALAN SHOPEE FOOD'!N76+'LAP. PENJUALAN SHOPEE FOOD'!N77+'LAP. PENJUALAN SHOPEE FOOD'!N83+'LAP. PENJUALAN SHOPEE FOOD'!N85+'LAP. PENJUALAN SHOPEE FOOD'!N86+'LAP. PENJUALAN SHOPEE FOOD'!N122+'LAP. PENJUALAN SHOPEE FOOD'!N123+'LAP. PENJUALAN SHOPEE FOOD'!N124 -> 23 | X17: *200GR
A18: 10 | B18: =VENDOR!D19 -> DADA MENTOK TAKJIL | C18: =VENDOR!H19 -> 0 | D18: =VENDOR!AJ19 -> 0 | E18: =VENDOR!AL19 -> 0 | F18: =C18+D18-E18 -> 0 | G18: =M19 -> 0 | H18: =G18-(F18-I18) -> 0 | J18: =SUM(H18:H20) -> 0 | L18: BEEF STEAK | Q18: =SUM(M18:P18) -> 0 | S18: PROMO | T18: ='LAP. PENJUALAN '!N155+'LAP. PENJUALAN '!N156+'LAP. PENJUALAN '!N157+'LAP. PENJUALAN '!N158+'LAP. PENJUALAN '!N159+'LAP. PENJUALAN '!N160+'LAP. PENJUALAN '!N161+'LAP. PENJUALAN '!N162+'LAP. PENJUALAN '!N163+'LAP. PENJUALAN '!N164+'LAP. PENJUALAN '!N166+'LAP. PENJUALAN '!N167+'LAP. PENJUALAN '!N168+'LAP. PENJUALAN '!N169+'LAP. PENJUALAN '!N179 -> 0 | X18: *150GR
A19: 11 | B19: =VENDOR!D20 -> DADA TAKJIL | C19: =VENDOR!H20 -> 0 | D19: =VENDOR!AJ20 -> 0 | E19: =VENDOR!AL20 -> 0 | F19: =C19+D19-E19 -> 0 | H19: =G19-(F19-I19) -> 0 | L19: DADA MENTOK TAKJIL | M19: ='LAP. PENJUALAN '!N156+'LAP. PENJUALAN '!N158+'LAP. PENJUALAN '!N160+'LAP. PENJUALAN '!N162+'LAP. PENJUALAN '!N164+'LAP. PENJUALAN '!N166 -> 0 | Q19: =SUM(M19:P19) -> 0 | S19: NASGOR ALL | T19: =U13 -> 43 | X19: *200GR
A20: 12 | B20: =VENDOR!D21 -> PAHA ATAS TAKJIL | C20: =VENDOR!H21 -> 0 | D20: =VENDOR!AJ21 -> 0 | E20: =VENDOR!AL21 -> 0 | F20: =C20+D20-E20 -> 0 | H20: =G20-(F20-I20) -> 0 | L20: DADA TAKJIL | S20: P AYM UTUH | T20: ='LAP. PENJUALAN '!N105+'LAP. PENJUALAN '!N105+'LAP. PENJUALAN '!N105+'LAP. PENJUALAN '!N105+'LAP. PENJUALAN '!N106+'LAP. PENJUALAN '!N106+'LAP. PENJUALAN '!N106+'LAP. PENJUALAN '!N106+'LAP. PENJUALAN '!N107+'LAP. PENJUALAN '!N107+'LAP. PENJUALAN '!N107+'LAP. PENJUALAN '!N107 -> 4 | U20: =T20*4 -> 16 | W20: =(SUM(T17:W17)/11)+(SUM(T18:W18)/15)+(SUM(T19:W19)/11)+(U20/11) -> 79.545455 | AB20: =B9 -> DADA MENTOK | AE20: 3 | AF20: ='WEEKLY FC'!E11 -> 6154.7692 | AG20: =AF20*AE20 -> 18464.308
A21: 13 | B21: =VENDOR!D22 -> PAHA BAWAH TAKJIL | C21: =VENDOR!H22 -> 0 | D21: =VENDOR!AJ22 -> 0 | E21: =VENDOR!AL22 -> 0 | F21: =C21+D21-E21 -> 0 | G21: =M22 -> 0 | H21: =G21-(F21-I21) -> 0 | J21: =SUM(H21:H22) -> 0 | L21: PAHA ATAS TAKJIL | AB21: =B49 -> AIR MINERAL BOTOL (AMB) | AE21: 9 | AF21: ='WEEKLY FC'!E99 -> 1667 | AG21: =AF21*AE21 -> 15003
A22: 14 | B22: =VENDOR!D23 -> SAYAP TAKJIL | C22: =VENDOR!H23 -> 0 | D22: =VENDOR!AJ23 -> 0 | E22: =VENDOR!AL23 -> 0 | F22: =C22+D22-E22 -> 0 | H22: =G22-(F22-I22) -> 0 | L22: PAHA BAWAH TAKJIL | M22: ='LAP. PENJUALAN '!N155+'LAP. PENJUALAN '!N157+'LAP. PENJUALAN '!N159+'LAP. PENJUALAN '!N161+'LAP. PENJUALAN '!N163+'LAP. PENJUALAN '!N179+'LAP. PENJUALAN '!N166 -> 0 | Q22: =SUM(M22:P22) -> 0 | V22: GOJEK | W22: SHOPEE | X22: GULA | AG22: =AG20+AG21 -> 33467.308
A23: 15 | B23: =VENDOR!D24 -> AYAM UTUH | C23: =VENDOR!H24 -> 9 | D23: =VENDOR!AJ24 -> 30 | E23: =VENDOR!AL24 -> 30 | F23: =C23+D23-E23 -> 9 | G23: =Q24 -> 9 | H23: =G23-(F23-I23) -> 0 | L23: SAYAP TAKJIL | S23: NESTEA (42) | T23: =N44 -> 199 | X23: =SUM(T23:W23)/42*0.5 -> 2.3690476 | Y23: *500ML
L24: AYAM UTUH | M24: ='LAP. PENJUALAN '!N102+'LAP. PENJUALAN '!N103+'LAP. PENJUALAN '!N104+'LAP. PENJUALAN '!N105+'LAP. PENJUALAN '!N106+'LAP. PENJUALAN '!N107+'LAP. PENJUALAN '!N108+'LAP. PENJUALAN '!N109 -> 3 | N24: ='LAP. PENJUALAN GRAB FOOD'!N102+'LAP. PENJUALAN GRAB FOOD'!N103+'LAP. PENJUALAN GRAB FOOD'!N104+'LAP. PENJUALAN GRAB FOOD'!N105+'LAP. PENJUALAN GRAB FOOD'!N106+'LAP. PENJUALAN GRAB FOOD'!N107+'LAP. PENJUALAN GRAB FOOD'!N181+'LAP. PENJUALAN GRAB FOOD'!N182 -> 2 | O24: ='LAP. PENJUALAN GO FOOD'!N102+'LAP. PENJUALAN GO FOOD'!N103+'LAP. PENJUALAN GO FOOD'!N104+'LAP. PENJUALAN GO FOOD'!N105+'LAP. PENJUALAN GO FOOD'!N106+'LAP. PENJUALAN GO FOOD'!N107+'LAP. PENJUALAN GO FOOD'!N108 -> 1 | P24: ='LAP. PENJUALAN SHOPEE FOOD'!N102+'LAP. PENJUALAN SHOPEE FOOD'!N103+'LAP. PENJUALAN SHOPEE FOOD'!N104+'LAP. PENJUALAN SHOPEE FOOD'!N105+'LAP. PENJUALAN SHOPEE FOOD'!N106+'LAP. PENJUALAN SHOPEE FOOD'!N107+'LAP. PENJUALAN SHOPEE FOOD'!N108 -> 3 | Q24: =SUM(M24:P24) -> 9 | S24: MILO (37) | X24: =SUM(T24:W24)/37*0.9 -> 0 | Y24: *900ML | Z24: =SUM(T24:W24) -> 0
A25: 16 | B25: =VENDOR!D26 -> VEGETABLE MIX | C25: =VENDOR!H26 -> 3.25 | D25: =VENDOR!AJ26 -> 0 | E25: =VENDOR!AL26 -> 2.5 | F25: =C25+D25-E25 -> 0.75 | G25: =M25 -> 0.98 | H25: =G25-(F25-I25) -> 0.23 | L25: MIX VEG | M25: =U12*20/1000 -> 0.98 | Q25: =SUM(M25:P25) -> 0.98 | S25: TEHPOCIV (24) | X25: =SUM(T25:W25)/36*1.44 -> 0 | Y25: *1440
A26: 17 | B26: =VENDOR!D27 -> BERAS | C26: =VENDOR!H27 -> 59 | D26: =VENDOR!AJ27 -> 95.272727 | E26: =VENDOR!AL27 -> 78 | F26: =C26+D26-E26 -> 76.272727 | G26: =W20 -> 79.545455 | H26: =G26-(F26-I26) -> 3.2727273 | L26: BERAS | S26: MILKSHAKE | X26: =SUM(T26:W26)*0.02 -> 0 | Y26: *20ML
A27: 18 | B27: =VENDOR!D28 -> FRENCH FRIES | C27: =VENDOR!H28 -> 5 | D27: =VENDOR!AJ28 -> 0 | E27: =VENDOR!AL28 -> 2.3 | F27: =C27+D27-E27 -> 2.7 | G27: =Q27 -> 3 | H27: =G27-(F27-I27) -> 0.3 | L27: FRENCH FRIES | M27: ='LAP. PENJUALAN '!N15+'LAP. PENJUALAN GRAB FOOD'!N15+'LAP. PENJUALAN GO FOOD'!N15+'LAP. PENJUALAN SHOPEE FOOD'!N15+'LAP. PENJUALAN GRAB FOOD'!N153+'LAP. PENJUALAN '!N202+'LAP. PENJUALAN '!N203 -> 30 | Q27: =SUM(M27:P27)/10 -> 3 | X27: =SUM(X23:X26)/1.5 -> 1.5793651
A28: 19 | B28: =VENDOR!D29 -> ROTI BURGER | C28: =VENDOR!H29 -> 128 | D28: =VENDOR!AJ29 -> 0 | E28: =VENDOR!AL29 -> 69 | F28: =C28+D28-E28 -> 59 | G28: =M28 -> 66 | H28: =G28-(F28-I28) -> 7 | L28: ROTI BURGER | M28: ='LAP. PENJUALAN '!N18+'LAP. PENJUALAN '!N19+'LAP. PENJUALAN '!N84+'LAP. PENJUALAN GRAB FOOD'!N84+'LAP. PENJUALAN GRAB FOOD'!N36+'LAP. PENJUALAN GRAB FOOD'!N18+'LAP. PENJUALAN GRAB FOOD'!N19+'LAP. PENJUALAN GO FOOD'!N84+'LAP. PENJUALAN GO FOOD'!N36+'LAP. PENJUALAN GO FOOD'!N18+'LAP. PENJUALAN GO FOOD'!N19+'LAP. PENJUALAN SHOPEE FOOD'!N84+'LAP. PENJUALAN SHOPEE FOOD'!N36+'LAP. PENJUALAN SHOPEE FOOD'!N19+'LAP. PENJUALAN SHOPEE FOOD'!N18+'LAP. PENJUALAN GRAB FOOD'!N164+'LAP. PENJUALAN GRAB FOOD'!N165+'LAP. PENJUALAN '!N203+'LAP. PENJUALAN '!N27 -> 66 | Q28: =SUM(M28:P28) -> 66
A29: 20 | B29: =VENDOR!D30 -> SOSIS | C29: =VENDOR!H30 -> 0 | D29: =VENDOR!AJ30 -> 0 | E29: =VENDOR!AL30 -> 0 | F29: =C29+D29-E29 -> 0 | H29: =G29-(F29-I29) -> 0 | L29: PERKEDEL | M29: ='LAP. PENJUALAN '!N17+'LAP. PENJUALAN GRAB FOOD'!N17+'LAP. PENJUALAN GO FOOD'!N17+'LAP. PENJUALAN SHOPEE FOOD'!N17+'LAP. PENJUALAN SHOPEE FOOD'!N157+'LAP. PENJUALAN SHOPEE FOOD'!N158+'LAP. PENJUALAN GRAB FOOD'!N152 -> 78 | Q29: =SUM(M29:P29) -> 78 | S29: TEPUNG | V29: HOT SPICY | Y29: BREADER
A30: 21 | B30: =VENDOR!D31 -> PERKEDEL | C30: =VENDOR!H31 -> 7 | D30: =VENDOR!AJ31 -> 140 | E30: =VENDOR!AL31 -> 72 | F30: =C30+D30-E30 -> 75 | G30: =M29 -> 78 | H30: =G30-(F30-I30) -> 3 | I30: ='LEFT OVER'!M21 -> 0 | L30: CRINKLE | Q30: =SUM(M30:P30) -> 0 | S30: AYAM (35G) | T30: =Q11+Q13+Q14+Q19+Q20+Q21+Q22+Q23+Q85+Q86+Q87+Q88+Q89+Q10+Q24+U12 -> 1326.1 | U30: =(T30-V30)/200*7+(V30/130*5) -> 46.493115 | V30: =SUM('[1]LAP. PENJUALAN'!M121:M130,'[1]LAP. PENJUALAN'!M77:M82,'[1]LAP. PENJUALAN GRAB FOOD'!M104:M109,'[1]LAP. PENJUALAN GOJEK'!M104:M109,'[1]LAP. PENJUALAN SHOPEE FOOD'!M104:M109) -> 23 | Y30: PCS | Z30: =T30/200*2 -> 13.261
A31: 22 | B31: =VENDOR!D32 -> CRINKLE | C31: =VENDOR!H32 -> 1.9 | D31: =VENDOR!AJ32 -> 0 | E31: =VENDOR!AL32 -> 0.7 | F31: =C31+D31-E31 -> 1.2 | G31: 2 | H31: =G31-(F31-I31) -> 0.8 | L31: NUGGET COIN | Q31: =SUM(M31:P31) -> 0 | S31: STRIP (40G) | T31: =U11 -> 13 | U31: =T31*0.04 -> 0.52 | Y31: UTUH | Z31: =Q24/25 -> 0.36
A32: 23 | B32: =VENDOR!D33 -> NUGGET COIN | C32: =VENDOR!H33 -> 0 | D32: =VENDOR!AJ33 -> 0 | E32: =VENDOR!AL33 -> 0 | F32: =C32+D32-E32 -> 0 | H32: =G32-(F32-I32) -> 0 | L32: NUGGET STICK | Q32: =SUM(M32:P32) -> 0 | S32: STEAK (40G) | T32: =U12 -> 49 | U32: =T32*0.04 -> 1.96 | Z32: =SUM(Z30:Z31) -> 13.621
A33: 24 | B33: =VENDOR!D34 -> NUGGET STICK | C33: =VENDOR!H34 -> 0 | D33: =VENDOR!AJ34 -> 0 | E33: =VENDOR!AL34 -> 0 | F33: =C33+D33-E33 -> 0 | H33: =G33-(F33-I33) -> 0 | L33: SOSIS MINI JUMBO | Q33: =SUM(M33:P33) -> 0 | S33: UTUH (280G) | T33: =Q24 -> 9 | U33: =T33/25*7 -> 2.52 | V33: BIANG BREADER | W33: =T30/200 -> 6.6305
A34: 25 | B34: =VENDOR!D35 -> SOSIS MINI JUMBO | C34: =VENDOR!H35 -> 0 | D34: =VENDOR!AJ35 -> 0 | E34: =VENDOR!AL35 -> 0 | F34: =C34+D34-E34 -> 0 | H34: =G34-(F34-I34) -> 0 | L34: GULA PASIR | Q34: =X27 -> 1.5793651 | U34: =SUM(U30:U33) -> 51.493115
A35: 26 | B35: =VENDOR!D36 -> INDOMIE GORENG | C35: =VENDOR!H36 -> 0 | D35: =VENDOR!AJ36 -> 0 | E35: =VENDOR!AL36 -> 0 | F35: =C35+D35-E35 -> 0 | H35: =G35-(F35-I35) -> 0 | L35: ICE CREAM | Q35: =SUM(M35:P35) -> 0 | S35: MINYAK
A36: 27 | B36: =VENDOR!D37 -> KERUPUK UDANG | C36: =VENDOR!H37 -> 0 | D36: =VENDOR!AJ37 -> 0 | E36: =VENDOR!AL37 -> 0 | F36: =C36+D36-E36 -> 0 | H36: =G36-(F36-I36) -> 0 | L36: TEH BOTOL SOSRO (TBS) | N36: ='LAP. PENJUALAN '!N219+'LAP. PENJUALAN '!N45+'LAP. PENJUALAN '!N46+'LAP. PENJUALAN '!N47+'LAP. PENJUALAN '!N48+'LAP. PENJUALAN '!N49+'LAP. PENJUALAN GO FOOD'!N47+'LAP. PENJUALAN GO FOOD'!N187 -> 8 | Q36: =SUM(M36:P36) -> 8 | S36: AYAM | T36: =T30 -> 1326.1 | U36: SAMBAL | V36: =SUM(W45:W47) -> 0.072211538 | W36: =T30+Q29+M27+Q24 -> 1443.1
A37: 28 | B37: =VENDOR!D38 -> BUN BURGER BEEF | C37: =VENDOR!H38 -> 0 | D37: =VENDOR!AJ38 -> 0 | E37: =VENDOR!AL38 -> 0 | F37: =C37+D37-E37 -> 0 | H37: =G37-(F37-I37) -> 0 | L37: TEH SOSRO POUCH (TBO) | Q37: =SUM(M37:P37) -> 0 | S37: STRIP | T37: =T31 -> 13 | U37: NASGOR | V37: =U13*0.01 -> 0.43
A38: 29 | B38: =VENDOR!D39 -> CHEESE UNTUK BEEF | C38: =VENDOR!H39 -> 0 | D38: =VENDOR!AJ39 -> 0 | E38: =VENDOR!AL39 -> 0 | F38: =C38+D38-E38 -> 0 | H38: =G38-(F38-I38) -> 0 | L38: FRUIT TEA BOTOL | N38: ='LAP. PENJUALAN '!N221+'LAP. PENJUALAN GRAB FOOD'!N192 -> 2 | P38: ='LAP. PENJUALAN GO FOOD'!N189 -> 0 | Q38: =SUM(M38:P38) -> 2 | S38: STEAK | T38: =T32 -> 49 | U38: A UTUH | V38: =Q24*8/33 -> 2.1818182
L39: FRUIT TEA POUCH (FTG) | Q39: =SUM(M39:P39) -> 0 | S39: FF | T39: =M27 -> 30
A40: 30 | B40: =VENDOR!D46 -> GULA PASIR | C40: =VENDOR!H46 -> 4.5 | D40: =VENDOR!AJ46 -> 5 | E40: =VENDOR!AL46 -> 3 | F40: =C40+D40-E40 -> 6.5 | G40: 7 | H40: =G40-(F40-I40) -> 0.5 | L40: TEBS | Q40: =SUM(M40:P40) -> 0 | S40: PERKEDEL | T40: =M29 -> 78
A41: 31 | B41: =VENDOR!D47 -> ICE CREAM | C41: =VENDOR!H47 -> 0 | D41: =VENDOR!AJ47 -> 0 | E41: =VENDOR!AL47 -> 0 | F41: =C41+D41-E41 -> 0 | H41: =G41-(F41-I41) -> 0 | L41: AIR MINERAL BOTOL (AMB) | N41: ='LAP. PENJUALAN '!N216+'LAP. PENJUALAN '!N173+'LAP. PENJUALAN GRAB FOOD'!N187+'LAP. PENJUALAN GO FOOD'!N184+'LAP. PENJUALAN SHOPEE FOOD'!N181+'LAP. PENJUALAN '!N262 -> 47 | Q41: =SUM(M41:P41) -> 47 | S41: PATTY | T41: =M15 -> 0
A42: 32 | B42: =VENDOR!D48 -> ICE CREAM EMBER | C42: =VENDOR!H48 -> 0 | D42: =VENDOR!AJ48 -> 0 | E42: =VENDOR!AL48 -> 0 | F42: =C42+D42-E42 -> 0 | H42: =G42-(F42-I42) -> 0 | L42: AIR MINERAL CUP (AMC) | Q42: =SUM(M42:P42) -> 0 | S42: TOTAL | T42: =SUM(T36:T41)/33 -> 45.336364 | V42: =T42+V36+V37+V38 -> 48.020393
L43: MILO | N43: ='LAP. PENJUALAN '!N83+'LAP. PENJUALAN '!N84+'LAP. PENJUALAN '!N85+'LAP. PENJUALAN '!N86+'LAP. PENJUALAN '!N41+'LAP. PENJUALAN '!N245+'LAP. PENJUALAN GRAB FOOD'!N216+'LAP. PENJUALAN GRAB FOOD'!N83+'LAP. PENJUALAN GRAB FOOD'!N84+'LAP. PENJUALAN GRAB FOOD'!N85+'LAP. PENJUALAN GRAB FOOD'!N86+'LAP. PENJUALAN GRAB FOOD'!N41+'LAP. PENJUALAN GO FOOD'!N213+'LAP. PENJUALAN GO FOOD'!N83+'LAP. PENJUALAN GO FOOD'!N84+'LAP. PENJUALAN GO FOOD'!N85+'LAP. PENJUALAN GO FOOD'!N86+'LAP. PENJUALAN GO FOOD'!N87+'LAP. PENJUALAN GO FOOD'!N41+'LAP. PENJUALAN SHOPEE FOOD'!N210+'LAP. PENJUALAN SHOPEE FOOD'!N83+'LAP. PENJUALAN SHOPEE FOOD'!N84+'LAP. PENJUALAN SHOPEE FOOD'!N85+'LAP. PENJUALAN SHOPEE FOOD'!N86+'LAP. PENJUALAN SHOPEE FOOD'!N41 -> 12 | Q43: =N43/37 -> 0.32432432
A44: 33 | B44: =VENDOR!D51 -> TEH BOTOL SOSRO (TBS) | C44: =VENDOR!H51 -> 16 | D44: =VENDOR!AJ51 -> 48 | E44: =VENDOR!AL51 -> 56 | F44: =C44+D44-E44 -> 8 | G44: =N36 -> 8 | H44: =G44-(F44-I44) -> 0 | L44: NESTEA | N44: ='LAP. PENJUALAN '!N39+'LAP. PENJUALAN '!N40+'LAP. PENJUALAN '!N42+'LAP. PENJUALAN '!N51+'LAP. PENJUALAN '!N52+'LAP. PENJUALAN '!N53+'LAP. PENJUALAN '!N59+'LAP. PENJUALAN '!N60+'LAP. PENJUALAN '!N61+'LAP. PENJUALAN '!N67+'LAP. PENJUALAN '!N68+'LAP. PENJUALAN '!N69+'LAP. PENJUALAN '!N75+'LAP. PENJUALAN '!N76+'LAP. PENJUALAN '!N77+'LAP. PENJUALAN '!N105+'LAP. PENJUALAN '!N105+'LAP. PENJUALAN '!N105+'LAP. PENJUALAN '!N105+'LAP. PENJUALAN '!N122+'LAP. PENJUALAN '!N123+'LAP. PENJUALAN '!N124+'LAP. PENJUALAN '!N244+'LAP. PENJUALAN GRAB FOOD'!N40+'LAP. PENJUALAN GRAB FOOD'!N51+'LAP. PENJUALAN GRAB FOOD'!N52+'LAP. PENJUALAN GRAB FOOD'!N53+'LAP. PENJUALAN GRAB FOOD'!N59+'LAP. PENJUALAN GRAB FOOD'!N60+'LAP. PENJUALAN GRAB FOOD'!N61+'LAP. PENJUALAN GRAB FOOD'!N67+'LAP. PENJUALAN GRAB FOOD'!N68+'LAP. PENJUALAN GRAB FOOD'!N69+'LAP. PENJUALAN GRAB FOOD'!N75+'LAP. PENJUALAN GRAB FOOD'!N76+'LAP. PENJUALAN GRAB FOOD'!N77+'LAP. PENJUALAN GRAB FOOD'!N105+'LAP. PENJUALAN GRAB FOOD'!N105+'LAP. PENJUALAN GRAB FOOD'!N105+'LAP. PENJUALAN GRAB FOOD'!N105+'LAP. PENJUALAN GRAB FOOD'!N106+'LAP. PENJUALAN GRAB FOOD'!N106+'LAP. PENJUALAN GRAB FOOD'!N106+'LAP. PENJUALAN GRAB FOOD'!N106+'LAP. PENJUALAN GRAB FOOD'!N215+'LAP. PENJUALAN GO FOOD'!N42+'LAP. PENJUALAN GO FOOD'!N51+'LAP. PENJUALAN GO FOOD'!N52+'LAP. PENJUALAN GO FOOD'!N53+'LAP. PENJUALAN GO FOOD'!N59+'LAP. PENJUALAN GO FOOD'!N60+'LAP. PENJUALAN GO FOOD'!N61+'LAP. PENJUALAN GO FOOD'!N67+'LAP. PENJUALAN GO FOOD'!N68+'LAP. PENJUALAN GO FOOD'!N69+'LAP. PENJUALAN GO FOOD'!N75+'LAP. PENJUALAN GO FOOD'!N76+'LAP. PENJUALAN GO FOOD'!N77+'LAP. PENJUALAN GO FOOD'!N122+'LAP. PENJUALAN GO FOOD'!N124+'LAP. PENJUALAN GO FOOD'!N212+'LAP. PENJUALAN SHOPEE FOOD'!N40+'LAP. PENJUALAN SHOPEE FOOD'!N51+'LAP. PENJUALAN SHOPEE FOOD'!N52+'LAP. PENJUALAN SHOPEE FOOD'!N53+'LAP. PENJUALAN SHOPEE FOOD'!N60+'LAP. PENJUALAN SHOPEE FOOD'!N61+'LAP. PENJUALAN SHOPEE FOOD'!N62+'LAP. PENJUALAN SHOPEE FOOD'!N67+'LAP. PENJUALAN SHOPEE FOOD'!N68+'LAP. PENJUALAN SHOPEE FOOD'!N69+'LAP. PENJUALAN SHOPEE FOOD'!N75+'LAP. PENJUALAN SHOPEE FOOD'!N76+'LAP. PENJUALAN SHOPEE FOOD'!N77+'LAP. PENJUALAN SHOPEE FOOD'!N107+'LAP. PENJUALAN SHOPEE FOOD'!N107+'LAP. PENJUALAN SHOPEE FOOD'!N107+'LAP. PENJUALAN SHOPEE FOOD'!N107+'LAP. PENJUALAN SHOPEE FOOD'!N107 -> 199 | Q44: =T23/42 -> 4.7380952 | S44: CABE | T44: MERAH | U44: IJO | V44: PENJ SAMBAL | W44: MINYAK | X44: SAMBAL UTUH
A45: 34 | B45: =VENDOR!D52 -> TEH SOSRO POUCH (TBO) | C45: =VENDOR!H52 -> 0 | D45: =VENDOR!AJ52 -> 48 | E45: =VENDOR!AL52 -> 48 | F45: =C45+D45-E45 -> 0 | G45: ='LAP. PENJUALAN '!N266 -> 0 | H45: =G45-(F45-I45) -> 0 | L45: ORANGE | Q45: =SUM(M45:P45)/35 -> 0 | S45: GEPREK | T45: =SUM(V45+X45)*1 -> 0.15384615 | V45: =SUM('[1]LAP. PENJUALAN'!M42:M48,'[1]LAP. PENJUALAN'!M136:M137,'[1]LAP. PENJUALAN GRAB FOOD'!M42:M48,'[1]LAP. PENJUALAN GOJEK'!M43:M48,'[1]LAP. PENJUALAN SHOPEE FOOD'!M42:M48,'[1]LAP. PENJUALAN'!M138)/65 -> 0.15384615 | W45: =SUM(X45,V45)*0.25 -> 0.038461538 | X45: =SUM('[1]LAP. PENJUALAN'!M116,'[1]LAP. PENJUALAN'!M113,'[1]LAP. PENJUALAN GRAB FOOD'!M78,'[1]LAP. PENJUALAN GRAB FOOD'!M81,'[1]LAP. PENJUALAN GOJEK'!M79,'[1]LAP. PENJUALAN GOJEK'!M81,'[1]LAP. PENJUALAN SHOPEE FOOD'!M78,'[1]LAP. PENJUALAN SHOPEE FOOD'!M81)*5 -> 0
A46: 35 | B46: =VENDOR!D53 -> FRUIT TEA BOTOL | C46: =VENDOR!H53 -> 3 | D46: =VENDOR!AJ53 -> 12 | E46: =VENDOR!AL53 -> 13 | F46: =C46+D46-E46 -> 2 | G46: =Q38 -> 2 | H46: =G46-(F46-I46) -> 0 | L46: BUAH FROZEN JAMBU | Q46: =SUM(M46:P46) -> 0 | S46: MATAH | T46: =V46*0.15 -> 0.015 | V46: =SUM('[1]LAP. PENJUALAN'!M50:M52,'[1]LAP. PENJUALAN'!M56,'[1]LAP. PENJUALAN GRAB FOOD'!M50:M52,'[1]LAP. PENJUALAN GRAB FOOD'!M55,'[1]LAP. PENJUALAN GOJEK'!M50:M52,'[1]LAP. PENJUALAN GOJEK'!M56,'[1]LAP. PENJUALAN SHOPEE FOOD'!M50:M52,'[1]LAP. PENJUALAN SHOPEE FOOD'!M56)/20 -> 0.1 | W46: =V46*0.15 -> 0.015
A47: 36 | B47: =VENDOR!D54 -> FRUIT TEA POUCH (FTG) | C47: =VENDOR!H54 -> 0 | D47: =VENDOR!AJ54 -> 0 | E47: =VENDOR!AL54 -> 0 | F47: =C47+D47-E47 -> 0 | H47: =G47-(F47-I47) -> 0 | L47: BUAH FROZEN MELON | Q47: =SUM(M47:P47) -> 0 | S47: TERASI | T47: =V47*0.125 -> 0.05859375 | V47: =SUM('[1]LAP. PENJUALAN'!M58:M64,'[1]LAP. PENJUALAN GRAB FOOD'!M58:M64,'[1]LAP. PENJUALAN GOJEK'!M58:M64,'[1]LAP. PENJUALAN SHOPEE FOOD'!M58:M64)/32 -> 0.46875 | W47: =V47*0.04 -> 0.01875
A48: 37 | B48: =VENDOR!D55 -> TEBS | C48: =VENDOR!H55 -> 2 | D48: =VENDOR!AJ55 -> 12 | E48: =VENDOR!AL55 -> 14 | F48: =C48+D48-E48 -> 0 | G48: ='LAP. PENJUALAN '!N223+'LAP. PENJUALAN GRAB FOOD'!N194+'LAP. PENJUALAN GO FOOD'!N191+'LAP. PENJUALAN SHOPEE FOOD'!N188 -> 0 | H48: =G48-(F48-I48) -> 0 | L48: BUAH FROZEN STAWBERRY | Q48: =SUM(M48:P48) -> 0 | T48: =SUM(T45:T47) -> 0.2274399 | U48: =SUM(U45:U461) -> 0
A49: 38 | B49: =VENDOR!D56 -> AIR MINERAL BOTOL (AMB) | C49: =VENDOR!H56 -> 218 | D49: =VENDOR!AJ56 -> 104 | E49: =VENDOR!AL56 -> 275 | F49: =C49+D49-E49 -> 47 | G49: =N41 -> 47 | H49: =G49-(F49-I49) -> 0 | L49: BUAH FROZEN SIRSAK | Q49: =SUM(M49:P49) -> 0
A50: 39 | B50: =VENDOR!D57 -> AIR MINERAL CUP (AMC) | C50: =VENDOR!H57 -> 46 | D50: =VENDOR!AJ57 -> 0 | E50: =VENDOR!AL57 -> 46 | F50: =C50+D50-E50 -> 0 | G50: =N42+'LAP. PENJUALAN '!J163 -> 0 | H50: =G50-(F50-I50) -> 0 | L50: BUAH FROZEN MANGGA | Q50: =SUM(M50:P50) -> 0 | S50: TELOR
A51: 40 | B51: =VENDOR!D58 -> MILO | C51: =VENDOR!H58 -> 4.91 | D51: =VENDOR!AJ58 -> 0 | E51: =VENDOR!AL58 -> 3.69 | F51: =C51+D51-E51 -> 1.22 | G51: =Q43+0.5 -> 0.82432432 | H51: =G51-(F51-I51) -> -0.035675676 | I51: ='LEFT OVER'!M26 -> 0.36 | L51: BUAH FROZEN DURIAN | Q51: =SUM(M51:P51) -> 0 | S51: PERKEDEL (10) | T51: =M29 -> 78 | U51: =T51/10 -> 7.8
A52: 41 | B52: =VENDOR!D59 -> NESTEA | C52: =VENDOR!H59 -> 5.79 | D52: =VENDOR!AJ59 -> 0 | E52: =VENDOR!AL59 -> 3.2 | F52: =C52+D52-E52 -> 2.59 | G52: =Q44 -> 4.7380952 | H52: =G52-(F52-I52) -> 2.1480952 | L52: TEH POCI KUNING / VANILLA | N52: ='LAP. PENJUALAN '!N34+'LAP. PENJUALAN '!N35+'LAP. PENJUALAN '!N36+'LAP. PENJUALAN '!N37+'LAP. PENJUALAN '!N38+'LAP. PENJUALAN '!N125+'LAP. PENJUALAN '!N126+'LAP. PENJUALAN '!N127+'LAP. PENJUALAN '!N248+'LAP. PENJUALAN GRAB FOOD'!N34+'LAP. PENJUALAN GRAB FOOD'!N35+'LAP. PENJUALAN GRAB FOOD'!N36+'LAP. PENJUALAN GRAB FOOD'!N37+'LAP. PENJUALAN GRAB FOOD'!N38+'LAP. PENJUALAN GRAB FOOD'!N219+'LAP. PENJUALAN GO FOOD'!N34+'LAP. PENJUALAN GO FOOD'!N35+'LAP. PENJUALAN GO FOOD'!N36+'LAP. PENJUALAN GO FOOD'!N37+'LAP. PENJUALAN GO FOOD'!N38+'LAP. PENJUALAN GO FOOD'!N216+'LAP. PENJUALAN SHOPEE FOOD'!N34+'LAP. PENJUALAN SHOPEE FOOD'!N35+'LAP. PENJUALAN SHOPEE FOOD'!N36+'LAP. PENJUALAN SHOPEE FOOD'!N37+'LAP. PENJUALAN SHOPEE FOOD'!N38+'LAP. PENJUALAN SHOPEE FOOD'!N213 -> 185 | Q52: =SUM(M52:P52)/36 -> 5.1388889 | S52: STEAK (5) | T52: =U12 -> 49 | U52: =T52/5 -> 9.8
A53: 42 | B53: =VENDOR!D60 -> ORANGE | C53: =VENDOR!H60 -> 0 | D53: =VENDOR!AJ60 -> 0 | E53: =VENDOR!AL60 -> 0 | F53: =C53+D53-E53 -> 0 | H53: =G53-(F53-I53) -> 0 | L53: MILK SHAKE COKLAT | Q53: =SUM(M53:P53) -> 0 | S53: NASGOR (1,5) | T53: =U13 -> 43 | U53: =T53*1.5 -> 64.5
A54: 43 | B54: =VENDOR!D61 -> BUAH FROZEN JAMBU | C54: =VENDOR!H61 -> 0 | D54: =VENDOR!AJ61 -> 0 | E54: =VENDOR!AL61 -> 0 | F54: =C54+D54-E54 -> 0 | H54: =G54-(F54-I54) -> 0 | L54: MILK SHAKE CAPPUCINO | Q54: =SUM(M54:P54) -> 0 | S54: PATTY (9) | T54: =M15 -> 0 | U54: =T54/9 -> 0
A55: 44 | B55: =VENDOR!D62 -> BUAH FROZEN MELON | C55: =VENDOR!H62 -> 0 | D55: =VENDOR!AJ62 -> 0 | E55: =VENDOR!AL62 -> 0 | F55: =C55+D55-E55 -> 0 | H55: =G55-(F55-I55) -> 0 | L55: MILK SHAKE MANGGA | Q55: =SUM(M55:P55) -> 0 | U55: =SUM(U51:U54) -> 82.1
A56: 45 | B56: =VENDOR!D63 -> BUAH FROZEN STRAWBERRY | C56: =VENDOR!H63 -> 0 | D56: =VENDOR!AJ63 -> 0 | E56: =VENDOR!AL63 -> 0 | F56: =C56+D56-E56 -> 0 | H56: =G56-(F56-I56) -> 0 | L56: MILK SHAKE STRAWBERRY | Q56: =SUM(M56:P56) -> 0
A57: 46 | B57: =VENDOR!D64 -> BUAH FROZEN SIRSAK | C57: =VENDOR!H64 -> 0 | D57: =VENDOR!AJ64 -> 0 | E57: =VENDOR!AL64 -> 0 | F57: =C57+D57-E57 -> 0 | H57: =G57-(F57-I57) -> 0 | L57: STEE | Q57: =SUM(M57:P57) -> 0 | T57: P KOSEK | U57: =SUM('LAP. PENJUALAN '!N51:N57)+'LAP. PENJUALAN '!N170+'LAP. PENJUALAN GRAB FOOD'!N51+'LAP. PENJUALAN GRAB FOOD'!N52+'LAP. PENJUALAN GRAB FOOD'!N53+'LAP. PENJUALAN GRAB FOOD'!N54+'LAP. PENJUALAN GRAB FOOD'!N55+'LAP. PENJUALAN GRAB FOOD'!N56+'LAP. PENJUALAN GRAB FOOD'!N57+'LAP. PENJUALAN GRAB FOOD'!N157+'LAP. PENJUALAN GRAB FOOD'!N168+'LAP. PENJUALAN GRAB FOOD'!N181*4+'LAP. PENJUALAN GRAB FOOD'!N235+'LAP. PENJUALAN GRAB FOOD'!N236+'LAP. PENJUALAN GO FOOD'!N51+'LAP. PENJUALAN GO FOOD'!N52+'LAP. PENJUALAN GO FOOD'!N53+'LAP. PENJUALAN GO FOOD'!N54+'LAP. PENJUALAN GO FOOD'!N55+'LAP. PENJUALAN GO FOOD'!N56+'LAP. PENJUALAN GO FOOD'!N57+'LAP. PENJUALAN SHOPEE FOOD'!N51+'LAP. PENJUALAN SHOPEE FOOD'!N53+'LAP. PENJUALAN SHOPEE FOOD'!N53+'LAP. PENJUALAN SHOPEE FOOD'!N54+'LAP. PENJUALAN SHOPEE FOOD'!N55+'LAP. PENJUALAN SHOPEE FOOD'!N56+'LAP. PENJUALAN SHOPEE FOOD'!N57+'LAP. PENJUALAN GRAB FOOD'!N236+'LAP. PENJUALAN GRAB FOOD'!N235+'LAP. PENJUALAN GRAB FOOD'!N157+'LAP. PENJUALAN GRAB FOOD'!N181+'LAP. PENJUALAN GRAB FOOD'!N181+'LAP. PENJUALAN GRAB FOOD'!N181+'LAP. PENJUALAN GRAB FOOD'!N181 -> 145 | V57: =U57/65 -> 2.2307692
A58: 47 | B58: =VENDOR!D65 -> BUAH FROZEN MANGGA | C58: =VENDOR!H65 -> 0 | D58: =VENDOR!AJ65 -> 0 | E58: =VENDOR!AL65 -> 0 | F58: =C58+D58-E58 -> 0 | H58: =G58-(F58-I58) -> 0 | L58: THAI GREEN TEA | Q58: =SUM(M58:P58) -> 0 | T58: P MATAH | U58: =SUM('LAP. PENJUALAN '!N59:N65)+'LAP. PENJUALAN '!N171+'LAP. PENJUALAN GRAB FOOD'!N59+'LAP. PENJUALAN GRAB FOOD'!N60+'LAP. PENJUALAN GRAB FOOD'!N61+'LAP. PENJUALAN GRAB FOOD'!N62+'LAP. PENJUALAN GRAB FOOD'!N63+'LAP. PENJUALAN GRAB FOOD'!N64+'LAP. PENJUALAN GRAB FOOD'!N65+'LAP. PENJUALAN GRAB FOOD'!N176+'LAP. PENJUALAN GRAB FOOD'!N232+'LAP. PENJUALAN GO FOOD'!N60+'LAP. PENJUALAN GO FOOD'!N59+'LAP. PENJUALAN GO FOOD'!N61+'LAP. PENJUALAN GO FOOD'!N62+'LAP. PENJUALAN GO FOOD'!N63+'LAP. PENJUALAN GO FOOD'!N64+'LAP. PENJUALAN GO FOOD'!N65+'LAP. PENJUALAN SHOPEE FOOD'!N59+'LAP. PENJUALAN SHOPEE FOOD'!N60+'LAP. PENJUALAN SHOPEE FOOD'!N61+'LAP. PENJUALAN SHOPEE FOOD'!N63+'LAP. PENJUALAN SHOPEE FOOD'!N62+'LAP. PENJUALAN SHOPEE FOOD'!N64+'LAP. PENJUALAN SHOPEE FOOD'!N65 -> 79 | V58: =U58/20 -> 3.95
A59: 48 | B59: =VENDOR!D66 -> BUAH FROZEN DURIAN | C59: =VENDOR!H66 -> 0 | D59: =VENDOR!AJ66 -> 0 | E59: =VENDOR!AL66 -> 0 | F59: =C59+D59-E59 -> 0 | H59: =G59-(F59-I59) -> 0 | L59: RED VALVET | Q59: =SUM(M59:P59) -> 0 | T59: P TERASI | U59: ='LAP. PENJUALAN '!N67+'LAP. PENJUALAN '!N68+'LAP. PENJUALAN '!N69+'LAP. PENJUALAN '!N70+'LAP. PENJUALAN '!N71+'LAP. PENJUALAN '!N72+'LAP. PENJUALAN '!N73+'LAP. PENJUALAN GRAB FOOD'!N67+'LAP. PENJUALAN GRAB FOOD'!N68+'LAP. PENJUALAN GRAB FOOD'!N69+'LAP. PENJUALAN GRAB FOOD'!N70+'LAP. PENJUALAN GRAB FOOD'!N71+'LAP. PENJUALAN GRAB FOOD'!N72+'LAP. PENJUALAN GRAB FOOD'!N73+'LAP. PENJUALAN GRAB FOOD'!N237+'LAP. PENJUALAN GO FOOD'!N67+'LAP. PENJUALAN GO FOOD'!N68+'LAP. PENJUALAN GO FOOD'!N69+'LAP. PENJUALAN GO FOOD'!N70+'LAP. PENJUALAN GO FOOD'!N71+'LAP. PENJUALAN GO FOOD'!N72+'LAP. PENJUALAN GO FOOD'!N73+'LAP. PENJUALAN SHOPEE FOOD'!N67+'LAP. PENJUALAN SHOPEE FOOD'!N68+'LAP. PENJUALAN SHOPEE FOOD'!N69+'LAP. PENJUALAN SHOPEE FOOD'!N70+'LAP. PENJUALAN SHOPEE FOOD'!N71+'LAP. PENJUALAN SHOPEE FOOD'!N72+'LAP. PENJUALAN SHOPEE FOOD'!N73 -> 22 | V59: =U59/32 -> 0.6875
A60: 49 | B60: =VENDOR!D67 -> TEH POCI KUNING / VANILA | C60: =VENDOR!H67 -> 73 | D60: =VENDOR!AJ67 -> 0 | E60: =VENDOR!AL67 -> 64 | F60: =C60+D60-E60 -> 9 | G60: =Q52+5 -> 10.138889 | H60: =G60-(F60-I60) -> 1.1388889 | L60: MILKY MANGGO | Q60: =SUM(M60:P60) -> 0 | T60: CABE RAWIT | U60: =V57*1 -> 2.2307692
A61: 50 | B61: =VENDOR!D68 -> MILK SHAKE COKLAT | C61: =VENDOR!H68 -> 15 | D61: =VENDOR!AJ68 -> 0 | E61: =VENDOR!AL68 -> 14 | F61: =C61+D61-E61 -> 1 | G61: ='LAP. PENJUALAN '!N240 -> 1 | H61: =G61-(F61-I61) -> 0 | L61: AIR MINERAL BOTOL (AMB) 330 ML | Q61: =SUM(M61:P61) -> 0 | U61: =V58*0.15 -> 0.5925
A62: 51 | B62: =VENDOR!D69 -> MILK SHAKE CAPPUCINO | C62: =VENDOR!H69 -> 0 | D62: =VENDOR!AJ69 -> 0 | E62: =VENDOR!AL69 -> 0 | F62: =C62+D62-E62 -> 0 | H62: =G62-(F62-I62) -> 0 | L62: 0 | Q62: =SUM(M62:P62) -> 0 | U62: =V59*0.125 -> 0.0859375
A63: 52 | B63: =VENDOR!D70 -> MILK SHAKE MANGGA | C63: =VENDOR!H70 -> 0 | D63: =VENDOR!AJ70 -> 0 | E63: =VENDOR!AL70 -> 0 | F63: =C63+D63-E63 -> 0 | H63: =G63-(F63-I63) -> 0 | L63: TEPUNG BRIDER 500 GR | Q63: =SUM(M63:P63) -> 0 | U63: =SUM(U60:U62) -> 2.9092067
A64: 53 | B64: =VENDOR!D71 -> MILK SHAKE STRAWBERRY | C64: =VENDOR!H71 -> 0 | D64: =VENDOR!AJ71 -> 0 | E64: =VENDOR!AL71 -> 0 | F64: =C64+D64-E64 -> 0 | G64: ='LAP. PENJUALAN '!N242 -> 0 | H64: =G64-(F64-I64) -> 0 | L64: BUTTER MIX | Q64: =SUM(M64:P64) -> 0
A65: 54 | B65: =VENDOR!D72 -> STEE | C65: =VENDOR!H72 -> 112 | D65: =VENDOR!AJ72 -> 240 | E65: =VENDOR!AL72 -> 159 | F65: =C65+D65-E65 -> 193 | G65: ='LAP. PENJUALAN '!N182+'LAP. PENJUALAN '!N219 -> 193 | H65: =G65-(F65-I65) -> 0 | L65: P.STEAK | Q65: =SUM(M65:P65) -> 0
A66: 55 | B66: =VENDOR!D73 -> THAI GREEN TEA | C66: =VENDOR!H73 -> 1 | D66: =VENDOR!AJ73 -> 0 | E66: =VENDOR!AL73 -> 0 | F66: =C66+D66-E66 -> 1 | G66: ='LAP. PENJUALAN '!N251+'LAP. PENJUALAN GRAB FOOD'!N222+'LAP. PENJUALAN GO FOOD'!N219+'LAP. PENJUALAN SHOPEE FOOD'!N216 -> 1 | H66: =G66-(F66-I66) -> 0 | L66: P. NASGOR | M66: =U13 -> 43 | Q66: =SUM(M66:P66) -> 43
A67: 56 | B67: =VENDOR!D74 -> RED VALVET | C67: =VENDOR!H74 -> 11 | D67: =VENDOR!AJ74 -> 0 | E67: =VENDOR!AL74 -> 9 | F67: =C67+D67-E67 -> 2 | G67: ='LAP. PENJUALAN '!N253+'LAP. PENJUALAN GRAB FOOD'!N224+'LAP. PENJUALAN GO FOOD'!N221+'LAP. PENJUALAN SHOPEE FOOD'!N218 -> 2 | H67: =G67-(F67-I67) -> 0 | L67: MAYONAISE | Q67: =SUM(M67:P67) -> 0
A68: 57 | B68: =VENDOR!D75 -> MILKY MANGGO | C68: =VENDOR!H75 -> 10 | D68: =VENDOR!AJ75 -> 0 | E68: =VENDOR!AL75 -> 10 | F68: =C68+D68-E68 -> 0 | G68: ='LAP. PENJUALAN '!N252+'LAP. PENJUALAN GRAB FOOD'!N223+'LAP. PENJUALAN GO FOOD'!N220+'LAP. PENJUALAN SHOPEE FOOD'!N217 -> 0 | H68: =G68-(F68-I68) -> 0 | L68: T. KENTANG | Q68: =SUM(M68:P68) -> 0
A69: 58 | B69: =VENDOR!D76 -> AIR MINERAL BOTOL (AMB) 330 ML | C69: =VENDOR!H76 -> 0 | D69: =VENDOR!AJ76 -> 0 | E69: =VENDOR!AL76 -> 0 | F69: =C69+D69-E69 -> 0 | H69: =G69-(F69-I69) -> 0 | L69: TEPUNG CAKRA | Q69: =SUM(M69:P69) -> 0
A70: 59 | B70: =VENDOR!D77 -> TEH RC | C70: =VENDOR!H77 -> 0 | D70: =VENDOR!AJ77 -> 0 | E70: =VENDOR!AL77 -> 0 | F70: =C70+D70-E70 -> 0 | H70: =G70-(F70-I70) -> 0 | L70: CHEESE MELT 100 GR | Q70: =SUM(M70:P70)/20 -> 0
A71: 60 | B71: =VENDOR!D133 -> MINYAK GORENG | C71: =VENDOR!H133 -> 93.45 | D71: =VENDOR!AJ133 -> 2 | E71: =VENDOR!AL133 -> 46.1 | F71: =C71+D71-E71 -> 49.35 | G71: =V42 -> 48.020393 | H71: =G71-(F71-I71) -> 0.82039336 | I71: 2.15 | L71: PREMIK SAMBAL TERASI | Q71: =SUM(M71:P71) -> 0
A72: 61 | B72: =VENDOR!D137 -> TELUR | C72: =VENDOR!H137 -> 6 | D72: =VENDOR!AJ137 -> 92 | E72: =VENDOR!AL137 -> 35 | F72: =C72+D72-E72 -> 63 | G72: 64.5 | H72: =G72-(F72-I72) -> 1.5 | L72: P. GEPREK | Q72: =SUM(M72:P72) -> 0
A73: 62 | B73: =VENDOR!D138 -> CABE RAWIT MERAH PETIK | C73: =VENDOR!H138 -> 0.25 | D73: =VENDOR!AJ138 -> 3.4 | E73: =VENDOR!AL138 -> 0.25 | F73: =C73+D73-E73 -> 3.4 | G73: =U63+1.5 -> 4.4092067 | H73: =G73-(F73-I73) -> 1.0092067 | L73: P.SAMBAL MATAH | Q73: =SUM(M73:P73) -> 0
A74: 63 | B74: =VENDOR!D139 -> CABE RAWIT HIJAU PETIK | C74: =VENDOR!H139 -> 0 | D74: =VENDOR!AJ139 -> 0 | E74: =VENDOR!AL139 -> 0 | F74: =C74+D74-E74 -> 0 | H74: =G74-(F74-I74) -> 0 | L74: P. PERKEDEL | Q74: =SUM(M74:P74) -> 0
A75: 64 | B75: =VENDOR!D140 -> MARINADE 1000 GR | C75: =VENDOR!H140 -> 3 | D75: =VENDOR!AJ140 -> 3.326087 | E75: =VENDOR!AL140 -> 2.86 | F75: =C75+D75-E75 -> 3.466087 | G75: =T30/414 -> 3.2031401 | H75: =G75-(F75-I75) -> -0.26294686 | L75: MINYAK GORENG | Q75: =SUM(M75:P75) -> 0
A76: 65 | B76: =VENDOR!D141 -> TEPUNG BRIDER 500 GR | C76: =VENDOR!H141 -> 58 | D76: =VENDOR!AJ141 -> 0 | E76: =VENDOR!AL141 -> 46 | F76: =C76+D76-E76 -> 12 | G76: =Z32 -> 13.621 | H76: =G76-(F76-I76) -> 1.621 | L76: LEVEL 1 | Q76: =SUM(M76:P76) -> 0
A77: 66 | B77: =VENDOR!D142 -> BUTTER MIX | C77: =VENDOR!H142 -> 5 | D77: =VENDOR!AJ142 -> 0 | E77: =VENDOR!AL142 -> 3 | F77: =C77+D77-E77 -> 2 | G77: 1.55 | H77: =G77-(F77-I77) -> -0.15 | I77: 0.3 | L77: LEVEL 2 | M77: ='LAP. PENJUALAN '!N75+'LAP. PENJUALAN '!N76+'LAP. PENJUALAN '!N77+'LAP. PENJUALAN '!N78+'LAP. PENJUALAN '!N79+'LAP. PENJUALAN '!N80+'LAP. PENJUALAN '!N81+'LAP. PENJUALAN GRAB FOOD'!N75+'LAP. PENJUALAN GRAB FOOD'!N76+'LAP. PENJUALAN GRAB FOOD'!N77+'LAP. PENJUALAN GRAB FOOD'!N78+'LAP. PENJUALAN GRAB FOOD'!N79+'LAP. PENJUALAN GRAB FOOD'!N80+'LAP. PENJUALAN GRAB FOOD'!N81+'LAP. PENJUALAN GRAB FOOD'!N82+'LAP. PENJUALAN GO FOOD'!N75+'LAP. PENJUALAN GO FOOD'!N76+'LAP. PENJUALAN GO FOOD'!N77+'LAP. PENJUALAN GO FOOD'!N78+'LAP. PENJUALAN GO FOOD'!N79+'LAP. PENJUALAN GO FOOD'!N80+'LAP. PENJUALAN GO FOOD'!N81+'LAP. PENJUALAN GO FOOD'!N82+'LAP. PENJUALAN SHOPEE FOOD'!N75+'LAP. PENJUALAN SHOPEE FOOD'!N76+'LAP. PENJUALAN SHOPEE FOOD'!N77+'LAP. PENJUALAN SHOPEE FOOD'!N78+'LAP. PENJUALAN SHOPEE FOOD'!N79+'LAP. PENJUALAN SHOPEE FOOD'!N80+'LAP. PENJUALAN SHOPEE FOOD'!N81+'LAP. PENJUALAN GRAB FOOD'!N179+'LAP. PENJUALAN GRAB FOOD'!N174+'LAP. PENJUALAN GRAB FOOD'!N178+'LAP. PENJUALAN GRAB FOOD'!N170+'LAP. PENJUALAN GRAB FOOD'!N233 -> 31 | Q77: =SUM(M77:P77)/60 -> 0.51666667
A78: 67 | B78: =VENDOR!D143 -> P. STEAK | C78: =VENDOR!H143 -> 39 | D78: =VENDOR!AJ143 -> 0 | E78: =VENDOR!AL143 -> 34.7 | F78: =C78+D78-E78 -> 4.3 | G78: =X12 -> 4.0833333 | H78: =G78-(F78-I78) -> -0.21666667 | Q78: =M77/20 -> 1.55
A79: 68 | B79: =VENDOR!D144 -> P. NASGOR | C79: =VENDOR!H144 -> 50 | D79: =VENDOR!AJ144 -> 0 | E79: =VENDOR!AL144 -> 9 | F79: =C79+D79-E79 -> 41 | G79: =Q66 -> 43 | H79: =G79-(F79-I79) -> 2 | Q79: =SUM(M79:P79)/130 -> 0
A80: 69 | B80: =VENDOR!D145 -> MAYONAISE | C80: =VENDOR!H145 -> 3 | D80: =VENDOR!AJ145 -> 0 | E80: =VENDOR!AL145 -> 1 | F80: =C80+D80-E80 -> 2 | G80: =Q28/70 -> 0.94285714 | H80: =G80-(F80-I80) -> -0.057142857 | I80: 1 | J80: DRESSING | L80: 0 | Q80: =SUM(M80:P80) -> 0
A81: 70 | B81: =VENDOR!D146 -> T. KENTANG | C81: =VENDOR!H146 -> 7 | D81: =VENDOR!AJ146 -> -4 | E81: =VENDOR!AL146 -> 1 | F81: =C81+D81-E81 -> 2 | G81: 2 | H81: =G81-(F81-I81) -> 0 | L81: 0 | Q81: =SUM(M81:P81) -> 0
A82: 71 | B82: =VENDOR!D147 -> TEPUNG CAKRA | C82: =VENDOR!H147 -> 2 | D82: =VENDOR!AJ147 -> 100 | E82: =VENDOR!AL147 -> 52 | F82: =C82+D82-E82 -> 50 | G82: =U34 -> 51.493115 | H82: =G82-(F82-I82) -> 1.4931154 | L82: INDOMIE GORENG | Q82: =SUM(M82:P82) -> 0
A83: 72 | B83: =VENDOR!D148 -> SAMBAL JERIGEN | C83: =VENDOR!H148 -> 1.7 | D83: =VENDOR!AJ148 -> 3 | E83: =VENDOR!AL148 -> 4 | F83: =C83+D83-E83 -> 0.7 | G83: 2 | H83: =G83-(F83-I83) -> 1.3 | Q83: =SUM(M83:P83) -> 0 | R83: =Q83/60 -> 0
A84: 73 | B84: =VENDOR!D149 -> TOMATO JERIGEN | C84: =VENDOR!H149 -> 0.45 | D84: =VENDOR!AJ149 -> 0 | E84: =VENDOR!AL149 -> 0 | F84: =C84+D84-E84 -> 0.45 | G84: 0.9 | H84: =G84-(F84-I84) -> 0.45 | Q84: =SUM(M84:P84) -> 0
A85: 74 | B85: =VENDOR!D150 -> SAMBAL SACHET | C85: =VENDOR!H150 -> 2108 | D85: =VENDOR!AJ150 -> 2500 | E85: =VENDOR!AL150 -> 3481 | F85: =C85+D85-E85 -> 1127 | G85: =VENDOR!AN150 -> 1127 | H85: =G85-(F85-I85) -> 0 | L85: DADA MENTOK TAKJIL | Q85: =SUM(M85:P85) -> 0
A86: 75 | B86: =VENDOR!D151 -> TOMATO SACHET | C86: =VENDOR!H151 -> 2264 | D86: =VENDOR!AJ151 -> 2500 | E86: =VENDOR!AL151 -> 3717 | F86: =C86+D86-E86 -> 1047 | G86: =VENDOR!AN151 -> 1047 | H86: =G86-(F86-I86) -> 0 | L86: DADA TAKJIL | Q86: =SUM(M86:P86) -> 0
A87: 76 | B87: =VENDOR!D152 -> LEVEL 1 | C87: =VENDOR!H152 -> 0 | D87: =VENDOR!AJ152 -> 0 | E87: =VENDOR!AL152 -> 0 | F87: =C87+D87-E87 -> 0 | H87: =G87-(F87-I87) -> 0 | L87: PAHA ATAS TAKJIL | Q87: =SUM(M87:P87) -> 0
A88: 77 | B88: =VENDOR!D153 -> LEVEL 2 | C88: =VENDOR!H153 -> 12 | D88: =VENDOR!AJ153 -> 0 | E88: =VENDOR!AL153 -> 11.5 | F88: =C88+D88-E88 -> 0.5 | G88: =M77/60+0.3 -> 0.81666667 | H88: =G88-(F88-I88) -> 0.31666667 | L88: PAHA BAWAH TAKJIL | Q88: =SUM(M88:P88) -> 0
A89: 78 | B89: =VENDOR!D154 -> CHEESE MELT 100 GR | C89: =VENDOR!H154 -> 30.5 | D89: =VENDOR!AJ154 -> 0 | E89: =VENDOR!AL154 -> 28.7 | F89: =C89+D89-E89 -> 1.8 | G89: =Q78 -> 1.55 | H89: =G89-(F89-I89) -> 0.15 | I89: 0.4 | L89: SAYAP TAKJIL | Q89: =SUM(M89:P89) -> 0
A90: 79 | B90: =VENDOR!D155 -> PREMIK SAMBAL TERASI | C90: =VENDOR!H155 -> 10 | D90: =VENDOR!AJ155 -> 0 | E90: =VENDOR!AL155 -> 9 | F90: =C90+D90-E90 -> 1 | G90: =V59 -> 0.6875 | H90: =G90-(F90-I90) -> -0.3125 | L90: DADA MENTOK GEMPUR | Q90: =SUM(M90:P90) -> 0
A91: 80 | B91: =VENDOR!D156 -> P. GEPREK | C91: =VENDOR!H156 -> 40.2 | D91: =VENDOR!AJ156 -> 0 | E91: =VENDOR!AL156 -> 38 | F91: =C91+D91-E91 -> 2.2 | G91: =V57+1 -> 3.2307692 | H91: =G91-(F91-I91) -> 1.0307692 | L91: DADA GEMPUR | Q91: =SUM(M91:P91) -> 0
A92: 81 | B92: =VENDOR!D157 -> P. SAMBAL MATAH | C92: =VENDOR!H157 -> 46.5 | D92: =VENDOR!AJ157 -> 0 | E92: =VENDOR!AL157 -> 44.5 | F92: =C92+D92-E92 -> 2 | G92: =V58 -> 3.95 | H92: =G92-(F92-I92) -> 1.95 | L92: PAHA ATAS GEMPUR | Q92: =SUM(M92:P92) -> 0
A93: 82 | B93: =VENDOR!D158 -> P. PERKEDEL | C93: =VENDOR!H158 -> 14 | D93: =VENDOR!AJ158 -> -4 | E93: =VENDOR!AL158 -> 4 | F93: =C93+D93-E93 -> 6 | G93: 6 | H93: =G93-(F93-I93) -> 0 | L93: PAHA BAWAH GEMPUR | Q93: =SUM(M93:P93) -> 0
A94: 83 | B94: =VENDOR!D159 -> P. PATTY | C94: =VENDOR!H159 -> 7 | D94: =VENDOR!AJ159 -> -1 | E94: =VENDOR!AL159 -> 6 | F94: =C94+D94-E94 -> 0 | H94: =G94-(F94-I94) -> 0 | L94: SAYAP TGEMPUR | Q94: =SUM(M94:P94) -> 0
A95: 84 | B95: =VENDOR!D160 -> BUMBU KRIUK (BIANG BREADER) | C95: =VENDOR!H160 -> 10 | D95: =VENDOR!AJ160 -> 0 | E95: =VENDOR!AL160 -> 6 | F95: =C95+D95-E95 -> 4 | G95: =W33 -> 6.6305 | H95: =G95-(F95-I95) -> 2.6305 | L95: AYAM UTUH | Q95: =SUM(M95:P95) -> 0
A96: 85 | B96: =VENDOR!D161 -> TOMAT POUCH | C96: =VENDOR!H161 -> 0 | D96: =VENDOR!AJ161 -> 3 | E96: =VENDOR!AL161 -> 3 | F96: =C96+D96-E96 -> 0 | H96: =G96-(F96-I96) -> 0 | L96: TELUR CATERING STAFF | Q96: =SUM(M96:P96) -> 0
A97: 86 | B97: =VENDOR!D162 -> SAMBAL POUCH | C97: =VENDOR!H162 -> 0 | D97: =VENDOR!AJ162 -> 0 | E97: =VENDOR!AL162 -> 0 | F97: =C97+D97-E97 -> 0 | H97: =G97-(F97-I97) -> 0 | Q97: =SUM(M97:P97) -> 0
A98: 87 | B98: =VENDOR!D163 -> MAIZENA | C98: =VENDOR!H163 -> 0 | D98: =VENDOR!AJ163 -> 0 | E98: =VENDOR!AL163 -> 0 | F98: =C98+D98-E98 -> 0 | H98: =G98-(F98-I98) -> 0
A99: 88 | B99: =VENDOR!D164 -> CHILLI POWDER | C99: =VENDOR!H164 -> 1.3 | D99: =VENDOR!AJ164 -> 0 | E99: =VENDOR!AL164 -> 1.2 | F99: =C99+D99-E99 -> 0.1 | G99: 1 | H99: =G99-(F99-I99) -> 0.9
A100: 89 | B100: =VENDOR!D165 -> DAUN BAYAM | C100: =VENDOR!H165 -> 0 | D100: =VENDOR!AJ165 -> 0 | E100: =VENDOR!AL165 -> 0 | F100: =C100+D100-E100 -> 0 | H100: =G100-(F100-I100) -> 0
A101: 90 | B101: =VENDOR!D166 -> P. GREEN CRISPY | C101: =VENDOR!H166 -> 0 | D101: =VENDOR!AJ166 -> 0 | E101: =VENDOR!AL166 -> 0 | F101: =C101+D101-E101 -> 0 | H101: =G101-(F101-I101) -> 0
A102: 91 | B102: =VENDOR!D191 -> TELUR CATERING STAFF | C102: =VENDOR!H191 -> 0 | D102: =VENDOR!AJ191 -> 0 | E102: =VENDOR!AL191 -> 0 | F102: =C102+D102-E102 -> 0 | H102: =G102-(F102-I102) -> 0
A103: 92 | B103: =VENDOR!D167 -> BRIDER HOT SPICY | C103: =VENDOR!H167 -> 0 | D103: =VENDOR!AJ167 -> 0 | E103: =VENDOR!AL167 -> 0 | F103: =C103+D103-E103 -> 0 | G103: =L103 -> 0.9 | H103: =G103-(F103-I103) -> 0.9 | L103: =SUM('SALES CONTROL'!L19/130) -> 0.9
A104: 93
...

Sheet LAPORAN KAS PERIODE
B2: LAPORAN KAS & PENJUALAN PER PERIODE
K3: CABANG : | L3: =LPKK!O4 -> RC SAMATA GOWA
K4: PERIODE : | L4: =LPKK!O5 -> 8-14 JANUARI 2025
B6: TANGGAL | C6: ='LAP. PENJUALAN '!D6 -> 46030 | D6: ='LAP. PENJUALAN '!E6 -> 46031 | E6: ='LAP. PENJUALAN '!F6 -> 46032 | F6: ='LAP. PENJUALAN '!G6 -> 46033 | G6: ='LAP. PENJUALAN '!H6 -> 46034 | H6: ='LAP. PENJUALAN '!I6 -> 46035 | I6: ='LAP. PENJUALAN '!J6 -> 46036 | J6: ='LAP. PENJUALAN '!K6 -> 0 | ... L6: ='LAP. PENJUALAN '!M6 -> 0 | M6: TOTAL
B7: HARI | C7: ='LAP. PENJUALAN '!D7 -> KAMIS | D7: ='LAP. PENJUALAN '!E7 -> JUMAT | E7: ='LAP. PENJUALAN '!F7 -> SABTU | F7: ='LAP. PENJUALAN '!G7 -> MINGGU | G7: ='LAP. PENJUALAN '!H7 -> SENIN | H7: ='LAP. PENJUALAN '!I7 -> SELASA | I7: ='LAP. PENJUALAN '!J7 -> RABU | J7: ='LAP. PENJUALAN '!K7 -> 0 | ... L7: ='LAP. PENJUALAN '!M7 -> 0
B8: Penjualan Kotor | C8: ='LAP TAMBAHAN '!D296+'LAP. PENJUALAN GRAB FOOD'!D243+'LAP. PENJUALAN GO FOOD'!D240+'LAP. PENJUALAN SHOPEE FOOD'!D237+'LAP. PENJUALAN PPN 10 %'!D270+'LAP. PENJUALAN '!D273 -> 3392759 | D8: ='LAP TAMBAHAN '!E296+'LAP. PENJUALAN GRAB FOOD'!E243+'LAP. PENJUALAN GO FOOD'!E240+'LAP. PENJUALAN SHOPEE FOOD'!E237+'LAP. PENJUALAN PPN 10 %'!E270+'LAP. PENJUALAN '!E273 -> 4301026 | E8: ='LAP TAMBAHAN '!F296+'LAP. PENJUALAN GRAB FOOD'!F243+'LAP. PENJUALAN GO FOOD'!F240+'LAP. PENJUALAN SHOPEE FOOD'!F237+'LAP. PENJUALAN PPN 10 %'!F270+'LAP. PENJUALAN '!F273 -> 4152270 | F8: ='LAP TAMBAHAN '!G296+'LAP. PENJUALAN GRAB FOOD'!G243+'LAP. PENJUALAN GO FOOD'!G240+'LAP. PENJUALAN SHOPEE FOOD'!G237+'LAP. PENJUALAN PPN 10 %'!G270+'LAP. PENJUALAN '!G273 -> 4562310 | G8: ='LAP TAMBAHAN '!H296+'LAP. PENJUALAN GRAB FOOD'!H243+'LAP. PENJUALAN GO FOOD'!H240+'LAP. PENJUALAN SHOPEE FOOD'!H237+'LAP. PENJUALAN PPN 10 %'!H270+'LAP. PENJUALAN '!H273 -> 4036126 | H8: ='LAP TAMBAHAN '!I296+'LAP. PENJUALAN GRAB FOOD'!I243+'LAP. PENJUALAN GO FOOD'!I240+'LAP. PENJUALAN SHOPEE FOOD'!I237+'LAP. PENJUALAN PPN 10 %'!I270+'LAP. PENJUALAN '!I273 -> 3330020 | I8: ='LAP TAMBAHAN '!J296+'LAP. PENJUALAN GRAB FOOD'!J243+'LAP. PENJUALAN GO FOOD'!J240+'LAP. PENJUALAN SHOPEE FOOD'!J237+'LAP. PENJUALAN PPN 10 %'!J270+'LAP. PENJUALAN '!J273 -> 4353210 | J8: ='LAP TAMBAHAN '!K296+'LAP. PENJUALAN GRAB FOOD'!K243+'LAP. PENJUALAN GO FOOD'!K240+'LAP. PENJUALAN SHOPEE FOOD'!K237+'LAP. PENJUALAN PPN 10 %'!K270+'LAP. PENJUALAN '!K273 -> 0 | ... L8: ='LAP TAMBAHAN '!M296+'LAP. PENJUALAN GRAB FOOD'!M243+'LAP. PENJUALAN GO FOOD'!M240+'LAP. PENJUALAN SHOPEE FOOD'!M237+'LAP. PENJUALAN PPN 10 %'!M270+'LAP. PENJUALAN '!M273 -> 0 | M8: =SUM(C8:L8) -> 28127721
B9: Komisi Gofood | C9: 52782 | D9: 54591 | E9: 20491 | F9: 40509 | G9: 46155 | H9: 33868 | I9: 27464 | M9: =SUM(C9:L9) -> 275860
B10: Komisi Grabfood | C10: 219642 | D10: 294182 | E10: 366099 | F10: 415834 | G10: 287175 | H10: 163970 | I10: 274680 | M10: =SUM(C10:L10) -> 2021582
B11: Komisi Shopee Food | C11: 116503 | D11: 25952 | E11: 40933 | F11: 28928 | G11: 38587 | H11: 37930 | I11: 40773 | M11: =SUM(C11:L11) -> 329606
B12: Koreksi | E12: 46000 | I12: 28750 | M12: =SUM(C12:L12) -> 74750
B13: Penjualan Koin Kidy Ride | M13: =SUM(C13:L13) -> 0
B14: Discount | C14: 25500 | D14: 39000 | E14: 24000 | F14: 73000 | G14: 40000 | H14: 63000 | I14: 6000 | M14: =SUM(C14:L14) -> 270500
B15: Tax/Pajak (Full PPN) | M15: =SUM(C15:L15) -> 0
B16: Penjualan Bersih | C16: =C8-C9-C10-C11-C12-C14-C15-C13 -> 2978332 | D16: =D8-D9-D10-D11-D12-D14-D15-D13 -> 3887301 | E16: =E8-E9-E10-E11-E12-E14-E15-E13 -> 3654747 | F16: =F8-F9-F10-F11-F12-F14-F15-F13 -> 4004039 | G16: =G8-G9-G10-G11-G12-G14-G15-G13 -> 3624209 | H16: =H8-H9-H10-H11-H12-H14-H15-H13 -> 3031252 | I16: =I8-I9-I10-I11-I12-I14-I15-I13 -> 3975543 | J16: =J8-J9-J10-J11-J12-J14-J15-J13 -> 0 | ... L16: =L8-L9-L10-L11-L12-L14-L15-L13 -> 0 | M16: =SUM(C16:L16) -> 25155423
M17: =SUM(C17:L17) -> 0
B18: Transferan Gofood | C18: 221018 | D18: 226409 | E18: 81209 | F18: 165791 | G18: 193945 | H18: 138931 | I18: 112586 | M18: =SUM(C18:L18) -> 1139889
B19: Transferan Grabfood | C19: 379318 | D19: 541038 | E19: 634741 | F19: 678466 | G19: 489505 | H19: 267530 | I19: 458640 | M19: =SUM(C19:L19) -> 3449238
B20: Transferan Shopee Food | C20: 349496 | D20: 77854 | E20: 122797 | F20: 86928 | G20: 115759 | H20: 113790 | I20: 122317 | M20: =SUM(C20:L20) -> 988941 | N20: =SUM(L18:L21) -> 0
B21: Pembayaran QRIS | C21: 942854 | D21: 1894644 | E21: 1622562 | F21: 1730799 | G21: 1387718 | H21: 1287425 | I21: 2132964 | M21: =SUM(C21:L21) -> 10998966
B22: Penjualan Rocket Kids | M22: =SUM(C22:L22) -> 0 | N22: =SUM(M18:M21) -> 16577034
B23: Selisih Kas | M23: =SUM(C23:L23) -> 0 | N23: =N22+M29 -> 26298338
C24: 6647 | D24: 13356 | E24: 11438 | F24: 12201 | G24: 9783 | H24: 9076 | I24: 14931 | M24: =SUM(C24:L24) -> 77432
B25: Kas yang harus disetor | C25: =C16-C18-C19-C20-C21-C22-C23 -> 1085646 | D25: =D16-D18-D19-D20-D21-D22-D23 -> 1147356 | E25: =E16-E18-E19-E20-E21-E22-E23 -> 1193438 | F25: =F16-F18-F19-F20-F21-F22-F23 -> 1342055 | G25: =G16-G18-G19-G20-G21-G22-G23 -> 1437282 | H25: =H16-H18-H19-H20-H21-H22-H23 -> 1223576 | I25: =I16-I18-I19-I20-I21-I22-I23 -> 1149036 | J25: =J16-J18-J19-J20-J21-J22-J23 -> 0 | ... L25: =L16-L18-L19-L20-L21-L22-L23 -> 0 | M25: =SUM(C25:L25) -> 8578389
B26: No. Rizet PLU / TTL | M26: =SUM(C26:L26) -> 0 | N26: =M25+M26 -> 8578389
B27: Penjualan Mikas | M27: =SUM(C27:L27) -> 0
B28: Penjualan lain - lain | M28: =SUM(C28:L28) -> 0
B29: Setor Bank | C29: 4621304 | I29: 5100000 | M29: =SUM(C29:L29) -> 9721304
B30: Setor Pihak Gedung | M30: =SUM(C30:L30) -> 0
B31: Jumlah Pembeli | C31: ='LAP TAMBAHAN '!D297 -> 101 | D31: ='LAP TAMBAHAN '!E297 -> 110 | E31: ='LAP TAMBAHAN '!F297 -> 105 | F31: ='LAP TAMBAHAN '!G297 -> 125 | G31: ='LAP TAMBAHAN '!H297 -> 116 | H31: ='LAP TAMBAHAN '!I297 -> 104 | I31: ='LAP TAMBAHAN '!J297 -> 118 | J31: ='LAP TAMBAHAN '!K297 -> 0 | ... L31: ='LAP TAMBAHAN '!M297 -> 0 | M31: =SUM(C31:L31) -> 779
L33: PARAF
L36: (..........................)

Sheet LAP. PENJUALAN 
D1: 27
A2: LAPORAN PENJUALAN
N3: Cabang : | O3: =LPKK!O4 -> RC SAMATA GOWA | U3: PRINT LEMBAR 1
N4: Periode : | O4: =LPKK!O5 -> 8-14 JANUARI 2025
A6: NO | B6: PRODUCT | C6: =B6 -> PRODUCT | D6: 46030 | E6: 46031 | F6: 46032 | G6: 46033 | H6: 46034 | I6: 46035 | J6: 46036 | N6: TOTAL | P6: % | Q6: FC ITEM | R6: CON FC | S6: HARGA
D7: KAMIS | E7: JUMAT | F7: SABTU | G7: MINGGU | H7: SENIN | I7: SELASA | J7: RABU | N7: UNIT | O7: ( Rp ) | S7: ( UNIT )
A8: 1 | B8: Dada | C8: =B8 -> Dada | D8: 22 | E8: 22 | F8: 30 | G8: 29 | H8: 25 | I8: 6 | J8: 15 | N8: =SUM(D8:M8) -> 149 | O8: =N8*S8 -> 2086000 | P8: =(O8/O273)*100 -> 10.470442 | Q8: ='[1]FC ITEM KELAS 3A'!G7 -> 0.62127468 | R8: =P8*Q8 -> 6.5050206 | S8: 14000 | W8: =D8*S8 -> 308000 | X8: =E8*S8 -> 308000 | Y8: =F8*S8 -> 420000 | Z8: =G8*S8 -> 406000 | AA8: =H8*S8 -> 350000 | AB8: =I8*S8 -> 84000 | AC8: =J8*S8 -> 210000 | AD8: =K8*S8 -> 0 | AE8: =L8*S8 -> 0 | AF8: =M8*S8 -> 0
A9: 2 | B9: Paha Atas | C9: =B9 -> Paha Atas | D9: 12 | E9: 12 | F9: 20 | G9: 29 | H9: 18 | I9: 8 | J9: 6 | N9: =SUM(D9:M9) -> 105 | O9: =N9*S9 -> 1470000 | P9: =(O9/O273)*100 -> 7.3784995 | Q9: ='[1]FC ITEM KELAS 3A'!G8 -> 0.52742679 | R9: =P9*Q9 -> 3.8916183 | S9: 14000 | W9: =D9*S9 -> 168000 | X9: =E9*S9 -> 168000 | Y9: =F9*S9 -> 280000 | Z9: =G9*S9 -> 406000 | AA9: =H9*S9 -> 252000 | AB9: =I9*S9 -> 112000 | AC9: =J9*S9 -> 84000 | AD9: =K9*S9 -> 0 | AE9: =L9*S9 -> 0 | AF9: =M9*S9 -> 0
A10: 3 | B10: Paha Bawah | C10: =B10 -> Paha Bawah | D10: 14 | E10: 10 | F10: 18 | G10: 19 | H10: 14 | I10: 10 | J10: 21 | N10: =SUM(D10:M10) -> 106 | O10: =N10*S10 -> 1272000 | P10: =(O10/O273)*100 -> 6.3846608 | Q10: ='[1]FC ITEM KELAS 3A'!G9 -> 0.46487807 | R10: =P10*Q10 -> 2.9680888 | S10: 12000 | W10: =D10*S10 -> 168000 | X10: =E10*S10 -> 120000 | Y10: =F10*S10 -> 216000 | Z10: =G10*S10 -> 228000 | AA10: =H10*S10 -> 168000 | AB10: =I10*S10 -> 120000 | AC10: =J10*S10 -> 252000 | AD10: =K10*S10 -> 0 | AE10: =L10*S10 -> 0 | AF10: =M10*S10 -> 0
A11: 4 | B11: Sayap | C11: =B11 -> Sayap | D11: 7 | E11: 8 | F11: 6 | G11: 11 | H11: 18 | I11: 11 | J11: 9 | N11: =SUM(D11:M11) -> 70 | O11: =N11*S11 -> 770000 | P11: =(O11/O273)*100 -> 3.8649283 | Q11: ='[1]FC ITEM KELAS 3A'!G10 -> 0.54622367 | R11: =P11*Q11 -> 2.1111153 | S11: 11000 | W11: =D11*S11 -> 77000 | X11: =E11*S11 -> 88000 | Y11: =F11*S11 -> 66000 | Z11: =G11*S11 -> 121000 | AA11: =H11*S11 -> 198000 | AB11: =I11*S11 -> 121000 | AC11: =J11*S11 -> 99000 | AD11: =K11*S11 -> 0 | AE11: =L11*S11 -> 0 | AF11: =M11*S11 -> 0
A12: 5 | B12: Chicken Strips | C12: =B12 -> Chicken Strips | D12: 1 | E12: 2 | F12: 2 | G12: 1 | H12: 1 | J12: 1 | N12: =SUM(D12:M12) -> 8 | O12: =N12*S12 -> 112000 | P12: =(O12/O273)*100 -> 0.56217139 | Q12: ='[1]FC ITEM KELAS 3A'!G11 -> 0.39301912 | R12: =P12*Q12 -> 0.2209441 | S12: 14000 | W12: =D12*S12 -> 14000 | X12: =E12*S12 -> 28000 | Y12: =F12*S12 -> 28000 | Z12: =G12*S12 -> 14000 | AA12: =H12*S12 -> 14000 | AB12: =I12*S12 -> 0 | AC12: =J12*S12 -> 14000 | AD12: =K12*S12 -> 0 | AE12: =L12*S12 -> 0 | AF12: =M12*S12 -> 0
A13: 6 | B13: Chicken Steak | C13: =B13 -> Chicken Steak | D13: 2 | F13: 1 | N13: =SUM(D13:M13) -> 3 | O13: =N13*S13 -> 45000 | P13: =(O13/O273)*100 -> 0.22587243 | Q13: ='[1]FC ITEM KELAS 3A'!G12 -> 0.57043025 | R13: =P13*Q13 -> 0.12884447 | S13: 15000 | W13: =D13*S13 -> 30000 | X13: =E13*S13 -> 0 | Y13: =F13*S13 -> 15000 | Z13: =G13*S13 -> 0 | AA13: =H13*S13 -> 0 | AB13: =I13*S13 -> 0 | AC13: =J13*S13 -> 0 | AD13: =K13*S13 -> 0 | AE13: =L13*S13 -> 0 | AF13: =M13*S13 -> 0
N14: =SUM(D14:M14) -> 0 | O14: =N14*S14 -> 0 | P14: =(O14/O273)*100 -> 0 | R14: =P14*Q14 -> 0 | W14: =D14*S14 -> 0 | X14: =E14*S14 -> 0 | Y14: =F14*S14 -> 0 | Z14: =G14*S14 -> 0 | AA14: =H14*S14 -> 0 | AB14: =I14*S14 -> 0 | AC14: =J14*S14 -> 0 | AD14: =K14*S14 -> 0 | AE14: =L14*S14 -> 0 | AF14: =M14*S14 -> 0
A15: 7 | B15: French Fries | C15: =B15 -> French Fries | D15: 1 | E15: 2 | F15: 2 | G15: 4 | I15: 2 | J15: 3 | N15: =SUM(D15:M15) -> 14 | O15: =N15*S15 -> 140000 | P15: =(O15/O273)*100 -> 0.70271423 | Q15: ='[1]FC ITEM KELAS 3A'!G14 -> 0.46658333 | R15: =P15*Q15 -> 0.32787475 | S15: 10000 | W15: =D15*S15 -> 10000 | X15: =E15*S15 -> 20000 | Y15: =F15*S15 -> 20000 | Z15: =G15*S15 -> 40000 | AA15: =H15*S15 -> 0 | AB15: =I15*S15 -> 20000 | AC15: =J15*S15 -> 30000 | AD15: =K15*S15 -> 0 | AE15: =L15*S15 -> 0 | AF15: =M15*S15 -> 0
A16: 8 | B16: Nasi | C16: =B16 -> Nasi | D16: 9 | E16: 32 | F16: 23 | G16: 31 | H16: 32 | I16: 14 | J16: 37 | N16: =SUM(D16:M16) -> 178 | O16: =N16*S16 -> 890000 | P16: =(O16/O273)*100 -> 4.4672548 | Q16: ='[1]FC ITEM KELAS 3A'!G15 -> 0.40704067 | R16: =P16*Q16 -> 1.8183544 | S16: 5000 | W16: =D16*S16 -> 45000 | X16: =E16*S16 -> 160000 | Y16: =F16*S16 -> 115000 | Z16: =G16*S16 -> 155000 | AA16: =H16*S16 -> 160000 | AB16: =I16*S16 -> 70000 | AC16: =J16*S16 -> 185000 | AD16: =K16*S16 -> 0 | AE16: =L16*S16 -> 0 | AF16: =M16*S16 -> 0
A17: 9 | B17: Perkedel | C17: =B17 -> Perkedel | D17: 7 | E17: 11 | F17: 8 | G17: 12 | H17: 15 | I17: 10 | J17: 3 | N17: =SUM(D17:M17) -> 66 | O17: =N17*S17 -> 330000 | P17: =(O17/O273)*100 -> 1.6563978 | Q17: ='[1]FC ITEM KELAS 3A'!G16 -> 0.55056766 | R17: =P17*Q17 -> 0.91195908 | S17: 5000 | W17: =D17*S17 -> 35000 | X17: =E17*S17 -> 55000 | Y17: =F17*S17 -> 40000 | Z17: =G17*S17 -> 60000 | AA17: =H17*S17 -> 75000 | AB17: =I17*S17 -> 50000 | AC17: =J17*S17 -> 15000 | AD17: =K17*S17 -> 0 | AE17: =L17*S17 -> 0 | AF17: =M17*S17 -> 0
A18: 10 | B18: Chicken Burger | C18: =B18 -> Chicken Burger | D18: 5 | E18: 4 | F18: 2 | G18: 4 | H18: 8 | I18: 3 | N18: =SUM(D18:M18) -> 26 | O18: =N18*S18 -> 390000 | P18: =(O18/O273)*100 -> 1.9575611 | Q18: ='[1]FC ITEM KELAS 3A'!G17 -> 0.58816453 | R18: =P18*Q18 -> 1.151368 | S18: 15000 | W18: =D18*S18 -> 75000 | X18: =E18*S18 -> 60000 | Y18: =F18*S18 -> 30000 | Z18: =G18*S18 -> 60000 | AA18: =H18*S18 -> 120000 | AB18: =I18*S18 -> 45000 | AC18: =J18*S18 -> 0 | AD18: =K18*S18 -> 0 | AE18: =L18*S18 -> 0 | AF18: =M18*S18 -> 0
A19: 11 | B19: Cheese Burger | C19: =B19 -> Cheese Burger | D19: 1 | G19: 1 | H19: 2 | I19: 3 | J19: 3 | N19: =SUM(D19:M19) -> 10 | O19: =N19*S19 -> 170000 | P19: =(O19/O273)*100 -> 0.85329586 | Q19: ='[1]FC ITEM KELAS 3A'!G18 -> 0.56308147 | R19: =P19*Q19 -> 0.48047508 | S19: 17000 | W19: =D19*S19 -> 17000 | X19: =E19*S19 -> 0 | Y19: =F19*S19 -> 0 | Z19: =G19*S19 -> 17000 | AA19: =H19*S19 -> 34000 | AB19: =I19*S19 -> 51000 | AC19: =J19*S19 -> 51000 | AD19: =K19*S19 -> 0 | AE19: =L19*S19 -> 0 | AF19: =M19*S19 -> 0
A20: 12 | B20: Nasi Goreng | C20: Mix Platter | N20: =SUM(D20:M20) -> 0 | O20: =N20*S20 -> 0 | P20: =(O20/O273)*100 -> 0 | R20: =P20*Q20 -> 0 | W20: =D20*S20 -> 0 | X20: =E20*S20 -> 0 | Y20: =F20*S20 -> 0 | Z20: =G20*S20 -> 0 | AA20: =H20*S20 -> 0 | AB20: =I20*S20 -> 0 | AC20: =J20*S20 -> 0 | AD20: =K20*S20 -> 0 | AE20: =L20*S20 -> 0 | AF20: =M20*S20 -> 0
A21: 13 | B21: Telur Ceplok | C21: =B21 -> Telur Ceplok | N21: =SUM(D21:M21) -> 0 | O21: =N21*S21 -> 0 | P21: =(O21/O273)*100 -> 0 | Q21: ='[1]FC ITEM KELAS 3A'!G23 -> 0.41839 | R21: =P21*Q21 -> 0 | S21: 5000 | W21: =D21*S21 -> 0 | X21: =E21*S21 -> 0 | Y21: =F21*S21 -> 0 | Z21: =G21*S21 -> 0 | AA21: =H21*S21 -> 0 | AB21: =I21*S21 -> 0 | AC21: =J21*S21 -> 0 | AD21: =K21*S21 -> 0 | AE21: =L21*S21 -> 0 | AF21: =M21*S21 -> 0
A22: 14 | B22: Nasi Goreng Telur Ceplok | C22: =B22 -> Nasi Goreng Telur Ceplok | F22: 6 | G22: 2 | H22: 3 | N22: =SUM(D22:M22) -> 11 | O22: =N22*S22 -> 176000 | P22: =(O22/O273)*100 -> 0.88341218 | Q22: ='[1]FC ITEM KELAS 3A'!G21 -> 0.67452333 | R22: =P22*Q22 -> 0.59588213 | S22: 16000 | W22: =D22*S22 -> 0 | X22: =E22*S22 -> 0 | Y22: =F22*S22 -> 96000 | Z22: =G22*S22 -> 32000 | AA22: =H22*S22 -> 48000 | AB22: =I22*S22 -> 0 | AC22: =J22*S22 -> 0 | AD22: =K22*S22 -> 0 | AE22: =L22*S22 -> 0 | AF22: =M22*S22 -> 0
N23: =SUM(D23:M23) -> 0 | O23: =N23*S23 -> 0 | P23: =(O23/O273)*100 -> 0 | R23: =P23*Q23 -> 0 | W23: =D23*S23 -> 0 | X23: =E23*S23 -> 0 | Y23: =F23*S23 -> 0 | Z23: =G23*S23 -> 0 | AA23: =H23*S23 -> 0 | AB23: =I23*S23 -> 0 | AC23: =J23*S23 -> 0 | AD23: =K23*S23 -> 0 | AE23: =L23*S23 -> 0 | AF23: =M23*S23 -> 0
A24: 15 | B24: Paket Segar 1 Dine In (Es Teh / S-tee) | C24: =B24 -> Paket Segar 1 Dine In (Es Teh / S-tee) | N24: =SUM(D24:M24) -> 0 | O24: =N24*S24 -> 0 | P24: =(O24/O273)*100 -> 0 | R24: =P24*Q24 -> 0 | W24: =D24*S24 -> 0 | X24: =E24*S24 -> 0 | Y24: =F24*S24 -> 0 | Z24: =G24*S24 -> 0 | AA24: =H24*S24 -> 0 | AB24: =I24*S24 -> 0 | AC24: =J24*S24 -> 0 | AD24: =K24*S24 -> 0 | AE24: =L24*S24 -> 0 | AF24: =M24*S24 -> 0
